Workbook
Name SegmentaciónDeDatos_Auditoría: #N/A
Name SegmentaciónDeDatos_Responsable: #N/A
Name SegmentaciónDeDatos_Vigencia: #N/A

Sheet Tablero
G29: Fecha Última actualización | I29: 46183.437

Sheet Calculos 2
A3: Etiquetas de fila | B3: Cuenta de No. Hallazgo | C3: Suma de Total Planes de acción | D3: Suma de Abiertos | E3: Suma de Vencidos | F3: Suma de Finalizados | G3: Suma de Auditoría
A4: 2023 | B4: 19 | C4: 24 | D4: 0 | E4: 0 | F4: 24 | G4: 1672
A5: 2024 | B5: 19 | C5: 26 | D5: 0 | E5: 2 | F5: 24 | G5: 1710
A6: 2025 | B6: 29 | C6: 34 | D6: 11 | E6: 4 | F6: 19 | G6: 2610
A7: Total general | B7: 67 | C7: 84 | D7: 11 | E7: 6 | F7: 67 | G7: 5992
A9: Etiquetas de fila | B9: Suma de Total Planes de acción | C9: Suma de Abiertos | D9: Suma de Vencidos | E9: Suma de Finalizados
A10: DIRECCIÓNDEGESTIÓNFINANCIERA | B10: 15 | C10: 1 | D10: 1 | E10: 13
A11: DIRECCIÓNDEGESTIÓNFINANCIERA/DIRECCIÓNDERECURSOSFÍSICOSYNEGOCIOS | B11: 1 | C11: 1 | D11: 0 | E11: 0
A12: DIRECCIÓNDEGESTIÓNFINANCIERA/SUBGERENCIAJURÍDICA | B12: 1 | C12: 0 | D12: 0 | E12: 1
A13: DIRECCIÓNDEGESTIÓNHUMANA | B13: 10 | C13: 0 | D13: 0 | E13: 10
A14: DIRECCIÓNDEINFRAESTRUCTURA | B14: 2 | C14: 1 | D14: 0 | E14: 1
A15: DIRECCIÓNDERECURSOSFÍSICOS | B15: 2 | C15: 0 | D15: 0 | E15: 2
A16: DIRECCIÓNDERECURSOSFÍSICOSYNEGOCIOS | B16: 4 | C16: 1 | D16: 0 | E16: 3
A17: DIRECCIÓNDERECURSOSFÍSICOSYNEGOCIOS/SUBGERENCIAJURÍDICA | B17: 1 | C17: 1 | D17: 0 | E17: 0
A18: DIRECCIÓNDERECURSOSTECNOLÓGICOS DIRECCIÓNDEGESTIÓNFINANCIERA | B18: 1 | C18: 0 | D18: 0 | E18: 1
A19: DIRECCIÓNDESEGURIDADOPERACIONAL | B19: 1 | C19: 0 | D19: 0 | E19: 1
A20: DIRECCIÓNDESERVICIOALTRANSPORTADOR | B20: 2 | C20: 0 | D20: 0 | E20: 2
A21: DIRECCIÓNDESERVICIOALTRANSPORTADOR/DIRECCIÓNDERECURSOSTECNOLÓGICOS | B21: 1 | C21: 0 | D21: 0 | E21: 1
... A35: Total general | B35: 84 | C35: 11 | D35: 6 | E35: 67

Sheet Hoja5
C3: Tabla 1: Planes de Acción por Auditoría | K3: Tabla 2: Planes de Acción por unico Responsable
C5: Vigencia | D5: PAD | E5: Total Hallazgos | F5: Total Planes de Acción | G5: Abierto en término | H5: Vencido | I5: Finalizado | K5: Área Responsable | L5: Total Planes de Acción | M5: Abierto en término | N5: Vencido | O5: Finalizado
C6: 2023 | D6: 88 | E6: 19 | F6: =+GETPIVOTDATA("Suma de Total Planes de acción",'Calculos 2'!$A$3,"Vigencia",2023) -> 24 | G6: =+GETPIVOTDATA("Suma de Abiertos",'Calculos 2'!$A$3,"Vigencia",2023) -> 0 | H6: =+GETPIVOTDATA("Suma de Vencidos",'Calculos 2'!$A$3,"Vigencia",2023) -> 0 | I6: =+GETPIVOTDATA("Suma de Finalizados",'Calculos 2'!$A$3,"Vigencia",2023) -> 24 | K6: Dirección de Gestión Financiera | L6: =+GETPIVOTDATA("Suma de Total Planes de acción",'Calculos 2'!$A$9,"Responsable ","DIRECCIÓNDEGESTIÓNFINANCIERA") -> 15 | M6: =+GETPIVOTDATA("Suma de Abiertos",'Calculos 2'!$A$9,"Responsable ","DIRECCIÓNDEGESTIÓNFINANCIERA") -> 1 | N6: =+GETPIVOTDATA("Suma de Vencidos",'Calculos 2'!$A$9,"Responsable ","DIRECCIÓNDEGESTIÓNFINANCIERA") -> 1 | O6: =+GETPIVOTDATA("Suma de Finalizados",'Calculos 2'!$A$9,"Responsable ","DIRECCIÓNDEGESTIÓNFINANCIERA") -> 13
C7: 2024 | D7: 90 | E7: 14 | F7: =+GETPIVOTDATA("Suma de Total Planes de acción",'Calculos 2'!$A$3,"Vigencia",2024) -> 26 | G7: =+GETPIVOTDATA("Suma de Abiertos",'Calculos 2'!$A$3,"Vigencia",2024)+GETPIVOTDATA("Suma de Abiertos",'Calculos 2'!$A$3,"Vigencia",2024) -> 0 | H7: =+GETPIVOTDATA("Suma de Vencidos",'Calculos 2'!$A$3,"Vigencia",2024) -> 2 | I7: =+GETPIVOTDATA("Suma de Finalizados",'Calculos 2'!$A$3,"Vigencia",2024) -> 24 | K7: Dirección de Gestión Humana | L7: =+GETPIVOTDATA("Suma de Total Planes de acción",'Calculos 2'!$A$9,"Responsable ","DIRECCIÓNDEGESTIÓNHUMANA") -> 10 | M7: =+GETPIVOTDATA("Suma de Abiertos",'Calculos 2'!$A$9,"Responsable ","DIRECCIÓNDEGESTIÓNHUMANA") -> 0 | N7: =+GETPIVOTDATA("Suma de Vencidos",'Calculos 2'!$A$9,"Responsable ","DIRECCIÓNDEGESTIÓNHUMANA") -> 0 | O7: =+GETPIVOTDATA("Suma de Finalizados",'Calculos 2'!$A$9,"Responsable ","DIRECCIÓNDEGESTIÓNHUMANA") -> 10
C8: 2025 | D8: 90 | E8: 21 | F8: =+GETPIVOTDATA("Suma de Total Planes de acción",'Calculos 2'!$A$3,"Vigencia",2025) -> 34 | G8: =+GETPIVOTDATA("Suma de Abiertos",'Calculos 2'!$A$3,"Vigencia",2025) -> 11 | H8: =+GETPIVOTDATA("Suma de Vencidos",'Calculos 2'!$A$3,"Vigencia",2025) -> 4 | I8: =+GETPIVOTDATA("Suma de Finalizados",'Calculos 2'!$A$3,"Vigencia",2025) -> 19 | K8: Dirección de Infraestructura | L8: =+GETPIVOTDATA("Suma de Total Planes de acción",'Calculos 2'!$A$9,"Responsable ","DIRECCIÓNDEINFRAESTRUCTURA") -> 2 | M8: =+GETPIVOTDATA("Suma de Abiertos",'Calculos 2'!$A$9,"Responsable ","DIRECCIÓNDEINFRAESTRUCTURA") -> 1 | N8: =+GETPIVOTDATA("Suma de Vencidos",'Calculos 2'!$A$9,"Responsable ","DIRECCIÓNDEINFRAESTRUCTURA") -> 0 | O8: =+GETPIVOTDATA("Suma de Finalizados",'Calculos 2'!$A$9,"Responsable ","DIRECCIÓNDEINFRAESTRUCTURA") -> 1
C9: Total General | F9: =SUM(F6:F8) -> 84 | G9: =SUM(G6:G8) -> 11 | H9: =SUM(H6:H8) -> 6 | I9: =SUM(I6:I8) -> 67 | K9: Dirección de Recursos Físicos y Negocios | L9: =+GETPIVOTDATA("Suma de Total Planes de acción",'Calculos 2'!$A$9,"Responsable ","DIRECCIÓNDERECURSOSFÍSICOS")+GETPIVOTDATA("Suma de Total Planes de acción",'Calculos 2'!$A$9,"Responsable ","DIRECCIÓNDERECURSOSFÍSICOSYNEGOCIOS") -> 6 | M9: =+GETPIVOTDATA("Suma de Abiertos",'Calculos 2'!$A$9,"Responsable ","DIRECCIÓNDERECURSOSFÍSICOS")+GETPIVOTDATA("Suma de Abiertos",'Calculos 2'!$A$9,"Responsable ","DIRECCIÓNDERECURSOSFÍSICOSYNEGOCIOS") -> 1 | N9: =+GETPIVOTDATA("Suma de Vencidos",'Calculos 2'!$A$9,"Responsable ","DIRECCIÓNDERECURSOSFÍSICOS")+GETPIVOTDATA("Suma de Vencidos",'Calculos 2'!$A$9,"Responsable ","DIRECCIÓNDERECURSOSFÍSICOSYNEGOCIOS") -> 0 | O9: =+GETPIVOTDATA("Suma de Finalizados",'Calculos 2'!$A$9,"Responsable ","DIRECCIÓNDERECURSOSFÍSICOS")+GETPIVOTDATA("Suma de Finalizados",'Calculos 2'!$A$9,"Responsable ","DIRECCIÓNDERECURSOSFÍSICOSYNEGOCIOS") -> 5
K10: Dirección de Seguridad Operacional | L10: =+GETPIVOTDATA("Suma de Total Planes de acción",'Calculos 2'!$A$9,"Responsable ","DIRECCIÓNDESEGURIDADOPERACIONAL") -> 1 | M10: =+GETPIVOTDATA("Suma de Abiertos",'Calculos 2'!$A$9,"Responsable ","DIRECCIÓNDESEGURIDADOPERACIONAL") -> 0 | N10: =+GETPIVOTDATA("Suma de Vencidos",'Calculos 2'!$A$9,"Responsable ","DIRECCIÓNDESEGURIDADOPERACIONAL") -> 0 | O10: =+GETPIVOTDATA("Suma de Finalizados",'Calculos 2'!$A$9,"Responsable ","DIRECCIÓNDESEGURIDADOPERACIONAL") -> 1
K11: Dirección de Servicio al Transportador | L11: =+GETPIVOTDATA("Suma de Total Planes de acción",'Calculos 2'!$A$9,"Responsable ","DIRECCIÓNDESERVICIOALTRANSPORTADOR") -> 2 | M11: =+GETPIVOTDATA("Suma de Abiertos",'Calculos 2'!$A$9,"Responsable ","DIRECCIÓNDESERVICIOALTRANSPORTADOR") -> 0 | N11: =+GETPIVOTDATA("Suma de Vencidos",'Calculos 2'!$A$9,"Responsable ","DIRECCIÓNDESERVICIOALTRANSPORTADOR") -> 0 | O11: =+GETPIVOTDATA("Suma de Finalizados",'Calculos 2'!$A$9,"Responsable ","DIRECCIÓNDESERVICIOALTRANSPORTADOR") -> 2
K12: Sub Gerencia Corporativa | L12: =+GETPIVOTDATA("Suma de Total Planes de acción",'Calculos 2'!$A$9,"Responsable ","SUBGERENCIACORPORATIVA") -> 3 | M12: =+GETPIVOTDATA("Suma de Abiertos",'Calculos 2'!$A$9,"Responsable ","SUBGERENCIACORPORATIVA") -> 2 | N12: =+GETPIVOTDATA("Suma de Vencidos",'Calculos 2'!$A$9,"Responsable ","SUBGERENCIACORPORATIVA") -> 0 | O12: =+GETPIVOTDATA("Suma de Finalizados",'Calculos 2'!$A$9,"Responsable ","SUBGERENCIACORPORATIVA") -> 1
K13: Sub Gerencia de Planeación y Proyectos | L13: =+GETPIVOTDATA("Suma de Total Planes de acción",'Calculos 2'!$A$9,"Responsable ","SUBGERENCIADEPLANEACIÓNYPROYECTOS")+GETPIVOTDATA("Suma de Total Planes de acción",'Calculos 2'!$A$9,"Responsable ","SUBGERENCIAPLANEACIÓNYPROYECTOS")+GETPIVOTDATA("Suma de Total Planes de acción",'Calculos 2'!$A$9,"Responsable ","SUBGERENCIAPLANEACIÓNYPROYECTOS(ZPP)") -> 17 | M13: =+GETPIVOTDATA("Suma de Abiertos",'Calculos 2'!$A$9,"Responsable ","SUBGERENCIADEPLANEACIÓNYPROYECTOS")+GETPIVOTDATA("Suma de Abiertos",'Calculos 2'!$A$9,"Responsable ","SUBGERENCIAPLANEACIÓNYPROYECTOS")+GETPIVOTDATA("Suma de Abiertos",'Calculos 2'!$A$9,"Responsable ","SUBGERENCIAPLANEACIÓNYPROYECTOS(ZPP)") -> 0 | N13: =+GETPIVOTDATA("Suma de Vencidos",'Calculos 2'!$A$9,"Responsable ","SUBGERENCIADEPLANEACIÓNYPROYECTOS")+GETPIVOTDATA("Suma de Vencidos",'Calculos 2'!$A$9,"Responsable ","SUBGERENCIAPLANEACIÓNYPROYECTOS")+GETPIVOTDATA("Suma de Vencidos",'Calculos 2'!$A$9,"Responsable ","SUBGERENCIAPLANEACIÓNYPROYECTOS(ZPP)") -> 0 | O13: =+GETPIVOTDATA("Suma de Finalizados",'Calculos 2'!$A$9,"Responsable ","SUBGERENCIADEPLANEACIÓNYPROYECTOS")+GETPIVOTDATA("Suma de Finalizados",'Calculos 2'!$A$9,"Responsable ","SUBGERENCIAPLANEACIÓNYPROYECTOS")+GETPIVOTDATA("Suma de Finalizados",'Calculos 2'!$A$9,"Responsable ","SUBGERENCIAPLANEACIÓNYPROYECTOS(ZPP)") -> 17
K14: Sub Gerencia de Servicios Operacionales e Infraestructura | L14: =+GETPIVOTDATA("Suma de Total Planes de acción",'Calculos 2'!$A$9,"Responsable ","SUBGERENCIADESERVICIOSOPERACIONALESEINFRAESTRUCTURA") -> 2 | M14: =+GETPIVOTDATA("Suma de Abiertos",'Calculos 2'!$A$9,"Responsable ","SUBGERENCIADESERVICIOSOPERACIONALESEINFRAESTRUCTURA") -> 1 | N14: =+GETPIVOTDATA("Suma de Vencidos",'Calculos 2'!$A$9,"Responsable ","SUBGERENCIADESERVICIOSOPERACIONALESEINFRAESTRUCTURA") -> 0 | O14: =+GETPIVOTDATA("Suma de Finalizados",'Calculos 2'!$A$9,"Responsable ","SUBGERENCIADESERVICIOSOPERACIONALESEINFRAESTRUCTURA") -> 1
K15: Sub Gerencia Jurídica | L15: =+GETPIVOTDATA("Suma de Total Planes de acción",'Calculos 2'!$A$9,"Responsable ","SUBGERENCIAJURÍDICA") -> 10 | M15: =+GETPIVOTDATA("Suma de Abiertos",'Calculos 2'!$A$9,"Responsable ","SUBGERENCIAJURÍDICA") -> 3 | N15: =+GETPIVOTDATA("Suma de Vencidos",'Calculos 2'!$A$9,"Responsable ","SUBGERENCIAJURÍDICA") -> 0 | O15: =+GETPIVOTDATA("Suma de Finalizados",'Calculos 2'!$A$9,"Responsable ","SUBGERENCIAJURÍDICA") -> 7
K16: Total General | L16: =SUM(L6:L15) -> 68 | M16: =SUM(M6:M15) -> 9 | N16: =SUM(N6:N15) -> 1 | O16: =SUM(O6:O15) -> 58
K18: Tabla 3: Planes de Acción por Responsable Compartido
K20: Área Responsable | L20: Total Planes de Acción | M20: Abierto en término | N20: Vencido | O20: Finalizado
K21: Dirección de Gestión Financiera Dirección de Recursos Físicos y Negocios | L21: =+GETPIVOTDATA("Suma de Total Planes de acción",'Calculos 2'!$A$9,"Responsable ","DIRECCIÓNDEGESTIÓNFINANCIERA/DIRECCIÓNDERECURSOSFÍSICOSYNEGOCIOS") -> 1 | M21: =+GETPIVOTDATA("Suma de Abiertos",'Calculos 2'!$A$9,"Responsable ","DIRECCIÓNDEGESTIÓNFINANCIERA/DIRECCIÓNDERECURSOSFÍSICOSYNEGOCIOS") -> 1 | N21: =+GETPIVOTDATA("Suma de Vencidos",'Calculos 2'!$A$9,"Responsable ","DIRECCIÓNDEGESTIÓNFINANCIERA/DIRECCIÓNDERECURSOSFÍSICOSYNEGOCIOS") -> 0 | O21: =+GETPIVOTDATA("Suma de Finalizados",'Calculos 2'!$A$9,"Responsable ","DIRECCIÓNDEGESTIÓNFINANCIERA/DIRECCIÓNDERECURSOSFÍSICOSYNEGOCIOS") -> 0
K22: Dirección de Gestión Financiera Sub Gerencia Jurídica | L22: =+GETPIVOTDATA("Suma de Total Planes de acción",'Calculos 2'!$A$9,"Responsable ","DIRECCIÓNDEGESTIÓNFINANCIERA/SUBGERENCIAJURÍDICA") -> 1 | M22: =+GETPIVOTDATA("Suma de Abiertos",'Calculos 2'!$A$9,"Responsable ","DIRECCIÓNDEGESTIÓNFINANCIERA/SUBGERENCIAJURÍDICA") -> 0 | N22: =+GETPIVOTDATA("Suma de Vencidos",'Calculos 2'!$A$9,"Responsable ","DIRECCIÓNDEGESTIÓNFINANCIERA/SUBGERENCIAJURÍDICA") -> 0 | O22: =+GETPIVOTDATA("Suma de Finalizados",'Calculos 2'!$A$9,"Responsable ","DIRECCIÓNDEGESTIÓNFINANCIERA/SUBGERENCIAJURÍDICA") -> 1
K23: Dirección de Recursos Físicos y Negocios Sub Gerencia Jurídica | L23: =+GETPIVOTDATA("Suma de Total Planes de acción",'Calculos 2'!$A$9,"Responsable ","DIRECCIÓNDERECURSOSFÍSICOSYNEGOCIOS/SUBGERENCIAJURÍDICA") -> 1 | M23: =+GETPIVOTDATA("Suma de Abiertos",'Calculos 2'!$A$9,"Responsable ","DIRECCIÓNDERECURSOSFÍSICOSYNEGOCIOS/SUBGERENCIAJURÍDICA") -> 1 | N23: =+GETPIVOTDATA("Suma de Vencidos",'Calculos 2'!$A$9,"Responsable ","DIRECCIÓNDERECURSOSFÍSICOSYNEGOCIOS/SUBGERENCIAJURÍDICA") -> 0 | O23: =+GETPIVOTDATA("Suma de Finalizados",'Calculos 2'!$A$9,"Responsable ","DIRECCIÓNDERECURSOSFÍSICOSYNEGOCIOS/SUBGERENCIAJURÍDICA") -> 0
K24: Dirección de Recursos Tecnológicos Dirección de Gestión Financiera | L24: =+GETPIVOTDATA("Suma de Total Planes de acción",'Calculos 2'!$A$9,"Responsable ","DIRECCIÓNDERECURSOSTECNOLÓGICOS DIRECCIÓNDEGESTIÓNFINANCIERA") -> 1 | M24: =+GETPIVOTDATA("Suma de Abiertos",'Calculos 2'!$A$9,"Responsable ","DIRECCIÓNDERECURSOSTECNOLÓGICOS DIRECCIÓNDEGESTIÓNFINANCIERA") -> 0 | N24: =+GETPIVOTDATA("Suma de Vencidos",'Calculos 2'!$A$9,"Responsable ","DIRECCIÓNDERECURSOSTECNOLÓGICOS DIRECCIÓNDEGESTIÓNFINANCIERA") -> 0 | O24: =+GETPIVOTDATA("Suma de Finalizados",'Calculos 2'!$A$9,"Responsable ","DIRECCIÓNDERECURSOSTECNOLÓGICOS DIRECCIÓNDEGESTIÓNFINANCIERA") -> 1
K25: Dirección de Servicio al Transportador Dirección de Recursos Tecnológicos | L25: =+GETPIVOTDATA("Suma de Total Planes de acción",'Calculos 2'!$A$9,"Responsable ","DIRECCIÓNDESERVICIOALTRANSPORTADOR/DIRECCIÓNDERECURSOSTECNOLÓGICOS") -> 1 | M25: =+GETPIVOTDATA("Suma de Abiertos",'Calculos 2'!$A$9,"Responsable ","DIRECCIÓNDESERVICIOALTRANSPORTADOR/DIRECCIÓNDERECURSOSTECNOLÓGICOS") -> 0 | N25: =+GETPIVOTDATA("Suma de Vencidos",'Calculos 2'!$A$9,"Responsable ","DIRECCIÓNDESERVICIOALTRANSPORTADOR/DIRECCIÓNDERECURSOSTECNOLÓGICOS") -> 0 | O25: =+GETPIVOTDATA("Suma de Finalizados",'Calculos 2'!$A$9,"Responsable ","DIRECCIÓNDESERVICIOALTRANSPORTADOR/DIRECCIÓNDERECURSOSTECNOLÓGICOS") -> 1
K26: Oficina de Auditoría Interna Dirección de Gestión Financiera Sub Gerencia Jurídica | L26: =+GETPIVOTDATA("Suma de Total Planes de acción",'Calculos 2'!$A$9,"Responsable ","OFICINADEAUDITORÍAINTERNASUBGERENCIAJURÍDICADIRECCIÓNFINANCIERA") -> 1 | M26: =+GETPIVOTDATA("Suma de Abiertos",'Calculos 2'!$A$9,"Responsable ","OFICINADEAUDITORÍAINTERNASUBGERENCIAJURÍDICADIRECCIÓNFINANCIERA") -> 0 | N26: =+GETPIVOTDATA("Suma de Vencidos",'Calculos 2'!$A$9,"Responsable ","OFICINADEAUDITORÍAINTERNASUBGERENCIAJURÍDICADIRECCIÓNFINANCIERA") -> 0 | O26: =+GETPIVOTDATA("Suma de Finalizados",'Calculos 2'!$A$9,"Responsable ","OFICINADEAUDITORÍAINTERNASUBGERENCIAJURÍDICADIRECCIÓNFINANCIERA") -> 1
K27: Sub Gerencia Corporativa Dirección de Gestión Financiera | L27: =+GETPIVOTDATA("Suma de Total Planes de acción",'Calculos 2'!$A$9,"Responsable ","SUBGERENCIACORPORATIVA/DIRECCIÓNDEGESTIÓNFINANCIERA") -> 3 | M27: =+GETPIVOTDATA("Suma de Abiertos",'Calculos 2'!$A$9,"Responsable ","SUBGERENCIACORPORATIVA/DIRECCIÓNDEGESTIÓNFINANCIERA") -> 0 | N27: =+GETPIVOTDATA("Suma de Vencidos",'Calculos 2'!$A$9,"Responsable ","SUBGERENCIACORPORATIVA/DIRECCIÓNDEGESTIÓNFINANCIERA") -> 3 | O27: =+GETPIVOTDATA("Suma de Finalizados",'Calculos 2'!$A$9,"Responsable ","SUBGERENCIACORPORATIVA/DIRECCIÓNDEGESTIÓNFINANCIERA") -> 0
K28: Sub Gerencia Corporativa Dirección de Recursos Tecnológicos | L28: =+GETPIVOTDATA("Suma de Total Planes de acción",'Calculos 2'!$A$9,"Responsable ","SUBGERENCIACORPORATIVA/DIRECCIÓNDERECURSOSTECNOLÓGICOS") -> 2 | M28: =+GETPIVOTDATA("Suma de Abiertos",'Calculos 2'!$A$9,"Responsable ","SUBGERENCIACORPORATIVA/DIRECCIÓNDERECURSOSTECNOLÓGICOS") -> 0 | N28: =+GETPIVOTDATA("Suma de Vencidos",'Calculos 2'!$A$9,"Responsable ","SUBGERENCIACORPORATIVA/DIRECCIÓNDERECURSOSTECNOLÓGICOS") -> 2 | O28: =+GETPIVOTDATA("Suma de Finalizados",'Calculos 2'!$A$9,"Responsable ","SUBGERENCIACORPORATIVA/DIRECCIÓNDERECURSOSTECNOLÓGICOS") -> 0
K29: Sub Gerencia Corporativa Dirección de Gestión Financiera Dirección de Recursos Tecnológicos | L29: =+GETPIVOTDATA("Suma de Total Planes de acción",'Calculos 2'!$A$9,"Responsable ","SUBGERENCIACORPORATIVADIRECCIÓNDEGESTIÓNFINANCIERADIRECCIÓNDERECURSOSTECNOLÓGICOS") -> 1 | M29: =+GETPIVOTDATA("Suma de Abiertos",'Calculos 2'!$A$9,"Responsable ","SUBGERENCIACORPORATIVADIRECCIÓNDEGESTIÓNFINANCIERADIRECCIÓNDERECURSOSTECNOLÓGICOS") -> 0 | N29: =+GETPIVOTDATA("Suma de Vencidos",'Calculos 2'!$A$9,"Responsable ","SUBGERENCIACORPORATIVADIRECCIÓNDEGESTIÓNFINANCIERADIRECCIÓNDERECURSOSTECNOLÓGICOS") -> 0 | O29: =+GETPIVOTDATA("Suma de Finalizados",'Calculos 2'!$A$9,"Responsable ","SUBGERENCIACORPORATIVADIRECCIÓNDEGESTIÓNFINANCIERADIRECCIÓNDERECURSOSTECNOLÓGICOS") -> 1
K30: Sub Gerencia de Planeación y Proyectos Dirección de Gestión Humana | L30: =+GETPIVOTDATA("Suma de Total Planes de acción",'Calculos 2'!$A$9,"Responsable ","SUBGERENCIADEPLANEACIÓNYPROYECTOSDIRECCIÓNDEGESTIÓNHUMANA") -> 2 | M30: =+GETPIVOTDATA("Suma de Abiertos",'Calculos 2'!$A$9,"Responsable ","SUBGERENCIADEPLANEACIÓNYPROYECTOSDIRECCIÓNDEGESTIÓNHUMANA") -> 0 | N30: =+GETPIVOTDATA("Suma de Vencidos",'Calculos 2'!$A$9,"Responsable ","SUBGERENCIADEPLANEACIÓNYPROYECTOSDIRECCIÓNDEGESTIÓNHUMANA") -> 0 | O30: =+GETPIVOTDATA("Suma de Finalizados",'Calculos 2'!$A$9,"Responsable ","SUBGERENCIADEPLANEACIÓNYPROYECTOSDIRECCIÓNDEGESTIÓNHUMANA") -> 2
K31: Sub Gerencia de Planeación y Proyectos Dirección de Recursos Físicos y Negocios | L31: =+GETPIVOTDATA("Suma de Total Planes de acción",'Calculos 2'!$A$9,"Responsable ","SUBGERENCIADEPLANEACIÓNYPROYECTOSDIRECCIÓNDERECURSOSFÍSICOSYNEGOCIOS") -> 1 | M31: =+GETPIVOTDATA("Suma de Abiertos",'Calculos 2'!$A$9,"Responsable ","SUBGERENCIADEPLANEACIÓNYPROYECTOSDIRECCIÓNDERECURSOSFÍSICOSYNEGOCIOS") -> 0 | N31: =+GETPIVOTDATA("Suma de Vencidos",'Calculos 2'!$A$9,"Responsable ","SUBGERENCIADEPLANEACIÓNYPROYECTOSDIRECCIÓNDERECURSOSFÍSICOSYNEGOCIOS") -> 0 | O31: =+GETPIVOTDATA("Suma de Finalizados",'Calculos 2'!$A$9,"Responsable ","SUBGERENCIADEPLANEACIÓNYPROYECTOSDIRECCIÓNDERECURSOSFÍSICOSYNEGOCIOS") -> 1
K32: Sub Gerencia Jurídica Dirección de Gestión Humana | L32: =+GETPIVOTDATA("Suma de Total Planes de acción",'Calculos 2'!$A$9,"Responsable ","SUBGERENCIAJURÍDICADIRECCIÓNDEGESTIÓNHUMANA") -> 1 | M32: =+GETPIVOTDATA("Suma de Abiertos",'Calculos 2'!$A$9,"Responsable ","SUBGERENCIAJURÍDICADIRECCIÓNDEGESTIÓNHUMANA") -> 0 | N32: =+GETPIVOTDATA("Suma de Vencidos",'Calculos 2'!$A$9,"Responsable ","SUBGERENCIAJURÍDICADIRECCIÓNDEGESTIÓNHUMANA") -> 0 | O32: =+GETPIVOTDATA("Suma de Finalizados",'Calculos 2'!$A$9,"Responsable ","SUBGERENCIAJURÍDICADIRECCIÓNDEGESTIÓNHUMANA") -> 1
K33: Total General | L33: =SUM(L21:L32) -> 16 | M33: =SUM(M21:M32) -> 2 | N33: =SUM(N21:N32) -> 5 | O33: =SUM(O21:O32) -> 9
K36: Tabla 3:El total de Planes de Acción es la suma de laTabla 2: Planes de Acción por Responsable y la Tabla 3: Planes de Acción por Responsable compartido
K38: Total Planes de Acción | L38: Total Planes de Acción | M38: Abierto en término | N38: Vencido | O38: Finalizado | Q38: Sin Definir
L39: =+L16+L33 -> 84 | M39: =+M16+M33 -> 11 | N39: =+N16+N33 -> 6 | O39: =+O16+O33 -> 67

Sheet Detalle
A4: VIGENCIA DE LA AUDITORÍA O VISITA | B4: CODIGO AUDITORÍA SEGÚN PAD DE LA VIGENCIA | C4: No. HALLAZGO | D4: DESCRIPCIÓN HALLAZGO | E4: DESCRIPCIÓN ACCIÓN | F4: AREA RESPONSABLE | G4: FECHA DE TERMINACIÓN | H4: ESTADO | I4: Alerta 10 | J4: Alerta 20 | K4: Alerta 30 | L4: Alerta 5
A5: 2025 | B5: 90 | C5: 3.1.1 | D5: HALLAZGO ADMINISTRATIVO CON PRESUNTA INCIDENCIA DISCIPLINARIA POR INCONSISTENCIAS EN LA ENTREGA DE INFORMACIÓN REQUERIDA POR EL ORGANISMO DE CONTROL | E5: DEFINICIÓN DE LA POLITICA CONTABLE QUE INCLUYA DIFERENCIAS DE CONCEPTO ENTRE UN ACTIVO Y EL MANEJO DE LOS PREDIOS PROPIEDAD DE TTSA | F5: DIRECCIÓNDEGESTIÓNFINANCIERA/DIRECCIÓNDERECURSOSFÍSICOSYNEGOCIOS | G5: 2026-06-30 | H5: Abierta | I5: 0 | J5: 0 | K5: 0 | L5: 0
C6: 3.2.1.1.2 | D6: HALLAZGO ADMINISTRATIVO CON PRESUNTA INCIDENCIA DISCIPLINARIA POR DEFICIENCIAS EN EL COBRO DE LOS CÁNONES DE ARRENDAMIENTO CAUSADOS DURANTE LA EJECUCIÓN DE LOS CONTRATOS DE ARRENDAMIENTO A-027-TQLL-2003; A-024-P.D.-2003; T-S.-2009 CÓDIGO A – L.3 EN Z.T.; Y TT NO. 90 DE 2015. | E6: ACTUALIZACIÓN DEL PROCEDIMIENTO DE GESTIÓN INMOBILIARIA QUE DEFINA LOS CONTROLES PARA EJERCER LAS ACCIONES DE COBRO DE CANONES DE ARRENDAMIENTO, EL PROCESO Y RESPONSABLES DE DECLARATORIA DE SINIESTRO EN LOS CASOS EN LOS QUE SE CUENTE CON GARANTÍAS DE ARRENDAMIENTO, O, LOS REQUISITOS, PROCEDIMIENTO Y RESPONSABLES PARA EL EJERCICIO DE ACCIONES DE COBRO COACTIVO | F6: DIRECCIÓNDERECURSOSFÍSICOSYNEGOCIOS/SUBGERENCIAJURÍDICA | G6: 2026-10-13 | H6: Abierta | I6: 0 | J6: 0 | K6: 0 | L6: 0
C7: 3.2.1.1.3 | D7: HALLAZGO ADMINISTRATIVO CON PRESUNTA INCIDENCIA DISCIPLINARIA POR LA GESTIÓN INEFICIENTE DE LA TERMINAL DE TRANSPORTE S.A. DURANTE DEL PROCESO DE EXPROPIACIÓN ADMINISTRATIVA ADELANTADO POR LA EMPRESA FÉRREA REGIONAL S.A.S. RESPECTO DEL PREDIO DENOMINADO “SANTA HELENA”, IDENTIFICADO CON LA MATRÍCULA INMOBILIARIA 051-191183, ASÍ COMO SU GESTIÓN INOPORTUNA EN LA DEFENSA DE LOS INTERESES DE LA ENTIDAD RESPECTO DEL COBRO DEL IMPUESTO PREDIAL | E7: CREACIÓN DE PROCEDIMIENTO PARA TRÁMITE DE EXPROPIACIONES DE LOS BIENES DE LA TTSA | F7: SUBGERENCIAJURÍDICA | G7: 2026-10-13 | H7: Abierta | I7: 0 | J7: 0 | K7: 0 | L7: 0
E8: GESTIÓN PARA LA MODIFICACIÓN DE LA RESOLUCIÓN NO. 25-75400001616-2025 EXPEDIDA POR EL MUNICIPIO DE SOACHA, CON EL FIN DE QUE SE AJUSTE EL ÁREA DEL PREDIO | F8: DIRECCIÓNDERECURSOSFÍSICOSYNEGOCIOS | G8: 2026-10-13 | H8: Abierta | I8: 0 | J8: 0 | K8: 0 | L8: 0
E9: RELIQUIDACIÓN DE IMPUESTOS CON FUNDAMENTO EN LA REDEFINICIÓN DEL ÁREA DEL PREDIO, CONFORME A LA MODIFICACIÓN DE LA RESOLUCIÓN CITADA | F9: DIRECCIÓNDEGESTIÓNFINANCIERA | G9: 2026-10-13 | H9: Abierta | I9: 0 | J9: 0 | K9: 0 | L9: 0
C10: 3.2.1.5.1 | D10: HALLAZGO ADMINISTRATIVO CON INCIDENCIA FISCAL POR LA SUMA DE CUATRO MIL OCHOCIENTOS NOVENTA Y SEIS MILLONES OCHOCIENTOS VEINTIDÓS MIL OCHOCIENTOS VEINTINUEVE PESOS M/CTE $4.896.822.829 Y PRESUNTA INCIDENCIA DISCIPLINARIA POR FALTA DE GESTIÓN OPORTUNA EN LA PRESENTACIÓN DE LAS DECLARACIONES DEL IMPUESTO PREDIAL UNIFICADO DEL INMUEBLE IDENTIFICADO CON CHIP AAA0077FYUH, VIGENCIAS 2015, 2016, 2017, 2020,2021, 2022 Y 2023 | E10: DECISIÓN DE LA DEMANDA INTERPUESTA EL 12/MARZ/2025 CON RADICADO NO. 25000234100020250038300, EN EL TRIBUNAL ADMINISTRATIVO DE CUNDINAMARCA | F10: SUBGERENCIAJURÍDICA | G10: 2026-10-13 | H10: Abierta | I10: 0 | J10: 0 | K10: 0 | L10: 0
C11: 3.4.2.2.1 | D11: HALLAZGO ADMINISTRATIVO CON INCIDENCIA FISCAL EN CUANTÍA DE SEISCIENTOS CINCO MILLONES QUINIENTOS SETENTA MIL CIENTO NOVENTA Y DOS PESOS M/CTE $605.570.192, Y PRESUNTA INCIDENCIA DISCIPLINARIA, POR EL PAGO INJUSTIFICADO DEL AIU Y PARTE DEL IVA EN EL MARCO DEL CONTRATO TT-034-2024. | E11: ANEXO AL ESTUDIO DE MERCADO DE LOS PROCESOS DE SELECCIÓN PARA LA CONTRATACIÓN DE SERVICIOS DE VIGILANCIA, QUE DETALLE LOS COSTOS E IMPUESTOS GENERADOS POR ÉSTE SERVICIO | F11: SUBGERENCIACORPORATIVA | G11: 2026-10-13 | H11: Abierta | I11: 0 | J11: 0 | K11: 0 | L11: 0 | T11: 10 a 15 de julio
E12: CONCEPTOS TÉCNICOS DE COLOMBIA COMPRA EFICIENTE Y DE LOS ENTES REGULADORES Y/O DE CONTROL SOBRE EL TRATAMIENTO DE AIU | F12: SUBGERENCIACORPORATIVA | G12: 2026-10-13 | H12: Abierta | I12: 0 | J12: 0 | K12: 0 | L12: 0
C13: 3.4.2.3.1 | D13: HALLAZGO ADMINISTRATIVO CON PRESUNTA INCIDENCIA DISCIPLINARIA POR NO APLICAR EL PRINCIPIO DE PLANEACIÓN YA QUE SE EVIDENCIA LA ACTUALIZACIÓN DE PRECIOS SEGÚN LA OFERTA COMERCIAL, PARA EL CONTRATO TT 172 DE 2024 SIN QUE EL MISMO TUVIESE FORMULA DE REAJUSTE. | E13: INCORPORACIÓN CONTRACTUAL DE CLÁUSULA DE ACTUALIZACIÓN DE PRECIOS UNITARIOS POR CAMBIO DE VIGENCIA, EN LOS CONTRATOS QUE APLIQUE | F13: DIRECCIÓNDEINFRAESTRUCTURA | G13: 2026-10-13 | H13: Abierta | I13: 0 | J13: 0 | K13: 0 | L13: 0
C14: 3.4.2.3.2 | D14: HALLAZGO ADMINISTRATIVO, POR EL INCUMPLIMIENTO EN LA OBLIGACIÓN DE LA ENTIDAD DE PUBLICAR INFORMACIÓN CONTRACTUAL EN LA PLATAFORMA SECOP II, PARA LOS CONTRATOS TT 172 Y TT 112 DE 2024. | E14: MEMORANDO DE LINEAMIENTOS EMITIDO POR LA SUB GERENCIA JURÍDICA SOBRE EL PROCEDIMIENTO DE PUBLICACIÓN EN LA PLATAFORMA SECOP, LA DEFINICIÓN DE RESPONSABLES, PLAZOS, PUBLICACIONES OBLIGATORIAS Y OPCIONALES | F14: SUBGERENCIAJURÍDICA | G14: 2026-10-13 | H14: Abierta | I14: 0 | J14: 0 | K14: 0 | L14: 0
C15: 4.2.1 | D15: HALLAZGO ADMINISTRATIVO CON PRESUNTA INCIDENCIA DISCIPLINARIA POR FALTA DE DILIGENCIA Y GESTIÓN OPORTUNA DE LOS REGISTROS “NO PAGOS” EN EL ESTACIONAMIENTO EN VÍA (ZONAS DE PARQUEO PAGO – ZPP) POR PARTE DE LA TERMINAL DE TRANSPORTE S.A. (TTSA). | E15: ACTUALIZACIÓN DEL PROCEDIMIENTO GPE-PRO2 GESTIÓN Y RECUPERACIÓN DE LOS REGISTROS SUSCEPTIBLES DE GESTIÓN DE ZPP QUE INCLUYA EL CONTROL AUTOMÁTICO DE LAS ALERTAS QUE GENERA EL APLICATIVO RESPECTO A LOS USOS DE LOS USUARIOS CUANDO PRESETAN REGISTROS "NO PAGOS" PARA QUE EL PERSONAL EN VÍA REALICE EL COBRO Ó EL USUARIO REALICE EL PAGO DEL MISMO PARA PODER HACER USO DE LAS ZONAS DE PARQUEO PAGO | F15: SUBGERENCIADESERVICIOSOPERACIONALESEINFRAESTRUCTURA | G15: 2026-06-30 | H15: Abierta | I15: 0 | J15: 0 | K15: 0 | L15: 0
A16: Total general

Sheet Vencidos
B2: VIGENCIA | C2: PAD | D2: No. HALLAZGO | E2: DESCRIPCIÓN HALLAZGO | F2: DESCRIPCIÓN ACCIÓN | G2: AREA RESPONSABLE | H2: FECHA DE TERMINACIÓN | I2: ENLACE EVIDENCIAS
B3: 2024 | C3: 90 | D3: 3.2.1.2 | E3: HALLAZGO ADMINISTRATIVA CON PRESUNTA INCIDENCIA DISCIPLINARIA Y FISCAL EN CUANTÍA DE $2.124.470, POR PAGO DE SANCIONES E INTERESES DE MORA ANTE LA SECRETARÍA DISTRITAL DE HACIENDA DURANTE LA VIGENCIA 2023 | F3: SE ESTABLECERAN INTERFACES CON LOS DIFERENTES PROGRAMAS DE MANEJO DE INGRESOS, QUE REDUZCAN PROCESOS MANUALES QUE MINIMICEN LA INTERVENCIÓN HUMANA EN EL REGISTRO DE LA INFORMACIÓN | G3: SUBGERENCIACORPORATIVA/DIRECCIÓNDERECURSOSTECNOLÓGICOS | H3: 2025-06-30 | I3: https://drive.google.com/drive/folders/1rVN9dCAaOu7HPMZfk_8Ipi4TNEITP1m_
B4: 2024 | C4: 90 | D4: 3.2.1.3 | E4: HALLAZGO ADMINISTRATIVA CON PRESUNTA INCIDENCIA DISCIPLINARIA Y FISCAL EN CUANTÍA DE $3.902.504, POR PAGO DE SANCIONES E INTERESES DE MORA ANTE LA DIRECCIÓN DE IMPUESTOS Y ADUANAS NACIONALES – DIAN | F4: SE ESTABLECERÁN INTERFACES CON LOS DIFERENTES PROGRAMAS DE MANEJO DE INGRESOS, QUE REDUZCAN PROCESOS MANUALES QUE MINIMICEN LA INTERVENCIÓN HUMANA EN EL REGISTRO DE LA INFORMACIÓN | G4: SUBGERENCIACORPORATIVA/DIRECCIÓNDERECURSOSTECNOLÓGICOS | H4: 2025-06-30 | I4: https://drive.google.com/drive/folders/1dWHLZvVx3dWrHlfG1qALbAqY-VP21Tsm
B5: 2025 | C5: 90 | D5: 3.3.1.1 | E5: HALLAZGO ADMINISTRATIVO POR EL INCUMPLIMIENTO DE ALGUNAS ACTIVIDADES DEL LINEAMIENTO PRESUPUESTAL ORDENADO EN SU MANUAL DE PRESUPUESTO. CÓDIGO: GAF-MN06 VERSIÓN 7, AGOSTO DE 2018. | F5: ACTUALIZACIÓN DEL MANUAL DEL PRESUPUESTO | G5: SUBGERENCIACORPORATIVA/DIRECCIÓNDEGESTIÓNFINANCIERA | H5: 46142 | I5: https://drive.google.com/drive/u/0/folders/14P1qKtAiC-YzKemPT5X0iBzfxnAFb5ip
B6: 2025 | C6: 90 | D6: 3.3.2.2 | E6: HALLAZGO ADMINISTRATIVO CON PRESUNTA INCIDENCIA DISCIPLINARIA, POR CUANTO LA TERMINAL DE TRANSPORTE, POSEE DOS TIPOS DE REGISTROS DE EXPEDICIÓN DE CDP Y CRP, QUE PRESENTAN INCONSISTENCIAS. | F6: ACTUALIZACIÓN DEL MANUAL DEL PRESUPUESTO | G6: SUBGERENCIACORPORATIVA/DIRECCIÓNDEGESTIÓNFINANCIERA | H6: 2026-04-30 | I6: https://drive.google.com/drive/u/0/folders/1gFWUgRMGQMoMIs5t5-wrGMmiUXXbS50u
B7: 2025 | C7: 90 | D7: 3.3.2.3.1 | E7: HALLAZGO ADMINISTRATIVO POR CUANTO LA TERMINAL PRESENTA SALDOS SIN PAGO EN LAS CXP VIGENCIA 2023 A PAGAR EN ENERO DE 2024 Y 2024 A PAGAR EN ENERO DE 2025, INCUMPLIENDO LO SEÑALADO EN SU PROCEDIMIENTO INTERNO. | F7: ACTUALIZACIÓN DEL MANUAL DEL PRESUPUESTO | G7: SUBGERENCIACORPORATIVA/DIRECCIÓNDEGESTIÓNFINANCIERA | H7: 2026-04-30 | I7: https://drive.google.com/drive/u/0/folders/1S5KdfBLYx-YHAeqUV10IyafbWn3tAV6c
B8: 2025 | C8: 90 | D8: 3.4.2.1.1 | E8: HALLAZGO ADMINISTRATIVO CON INCIDENCIA FISCAL EN CUANTÍA DE $1.482.567.858 Y PRESUNTA INCIDENCIA DISCIPLINARIA TODA VEZ QUE, EN DESARROLLO DEL CONTRATO 99 DE 2019 SUSCRITO ENTRE LA TERMINAL DE TRANSPORTE S.A. Y PROTECH INGENIERÍA S.A.S, SE PRODUJO UNA GESTIÓN FISCAL ANTIECONÓMICA, INEFICAZ, INEFICIENTE, PORQUE EL SISTEMA ADQUIRIDO NO CUMPLE CON EL OBJETO DEL CONTRATO, NO ES FUNCIONAL. | F8: PRESENTACIÓN POR PARTE DE LOS SUPERVISORES DEL CONTRATO, DE INFORME QUE DETALLE Y EXPLIQUE EL FUNCIONAMIENTO DE CADA UNO DE LOS COMPONENTES DE LA SOLUCIÓN, Y EVIDENCIA DE LAS PRUEBAS EFECTUADAS PARA EL RECIBO DE LA MISMA. ADEMÁS, DEL FUNCIONAMIENTO ACTUAL DE LA SOLUCIÓN TECNOLÓGICA Y EL ESTADO DE LAS RECLAMACIONES GESTIONADAS ANTE LA ASEGURADORA | G8: SUBGERENCIADESERVICIOSOPERACIONALESEINFRAESTRUCTURA | H8: 2025-12-31 | I8: https://drive.google.com/drive/u/0/folders/1FtPipptfNQSnRuDzBLHttv5QsFbt4_i4
B9: 2025 | C9: 90 | D9: 3.4.2.3.3 | E9: HALLAZGO ADMINISTRATIVO POR NO APLICAR EL PRINCIPIO DE PLANEACIÓN YA QUE SE EVIDENCIA EL PAGO DE LOS ÍTEMS NO PREVISTOS ANTES DE SER APROBADOS POR EL SUPERVISOR DEL CONTRATO TT 112 DE 2024, EVIDENCIANDO UN INCUMPLIMIENTO EN LAS OBLIGACIONES DE LA ENTIDAD. | F9: CAPACITACIÓN POR PARTE DE LA SUBGERENCIA JURÍDICA, SOBRE LA SUPERVISIÓN DE CONTRATOS, QUE INCLUYA ÍTEMS NO PREVISTOS Y RECONOCIMIENTO PARA EL PAGO | G9: SUBGERENCIAJURÍDICA | H9: 2026-02-28 | I9: https://drive.google.com/drive/u/0/folders/1ur2Auhsr5t-nA4bZISLNcN9eQ8lGYGY-
B10: 2025 | C10: 90 | D10: 3.4.2.4.1 | E10: HALLAZGO ADMINISTRATIVO CON PRESUNTA INCIDENCIA DISCIPLINARIA Y PENAL DEBIDO A QUE DE LOS RECURSOS INICIALMENTE ASIGNADOS AL CONTRATO 135 DE 2023 FUERON DISMINUIDOS EN LA SUMA $9.000.00 MILLONES, SIN LA EXPEDICIÓN DEL CORRESPONDIENTE ACTO ADMINISTRATIVO QUE PERMITIERA LA LIBERACIÓN DE ESTOS RECURSOS, GENERANDO LA DESFINANCIACIÓN DEL MISMO. | F10: ACTUALIZACIÓN DEL MANUAL DE PRESUPUESTO PARA LA VALIDACIÓN DE REQUISITOS PARA LA MODIFICACIÓN DE CDP | G10: DIRECCIÓNDEGESTIÓNFINANCIERA | H10: 2026-04-30 | I10: https://drive.google.com/drive/u/0/folders/16uXFDMuYgvGjkp-JJgwIwXgpK9vORInY
B11: 2025 | C11: 90 | D11: 3.4.2.4.1 | E11: HALLAZGO ADMINISTRATIVO CON PRESUNTA INCIDENCIA DISCIPLINARIA Y PENAL DEBIDO A QUE DE LOS RECURSOS INICIALMENTE ASIGNADOS AL CONTRATO 135 DE 2023 FUERON DISMINUIDOS EN LA SUMA $9.000.00 MILLONES, SIN LA EXPEDICIÓN DEL CORRESPONDIENTE ACTO ADMINISTRATIVO QUE PERMITIERA LA LIBERACIÓN DE ESTOS RECURSOS, GENERANDO LA DESFINANCIACIÓN DEL MISMO. | F11: INFORME DE LA DIRECCIÓN FINANCIERA PARA INDICAR EL MANEJO DE LOS CDP | G11: DIRECCIÓNDEGESTIÓNFINANCIERA | H11: 2026-04-30 | I11: https://drive.google.com/drive/u/0/folders/1qaiBaFOogRrmDOJAIqv0IVPFCZcfZjnf

Sheet Abiertos
B2: VIGENCIA | C2: PAD | D2: No. HALLAZGO | E2: DESCRIPCIÓN HALLAZGO | F2: DESCRIPCIÓN ACCIÓN | G2: AREA RESPONSABLE | H2: FECHA DE TERMINACIÓN | I2: ENLACE EVIDENCIAS
B3: 2025 | C3: 90 | D3: 3.1.1 | E3: HALLAZGO ADMINISTRATIVO CON PRESUNTA INCIDENCIA DISCIPLINARIA POR INCONSISTENCIAS EN LA ENTREGA DE INFORMACIÓN REQUERIDA POR EL ORGANISMO DE CONTROL | F3: DEFINICIÓN DE LA POLITICA CONTABLE QUE INCLUYA DIFERENCIAS DE CONCEPTO ENTRE UN ACTIVO Y EL MANEJO DE LOS PREDIOS PROPIEDAD DE TTSA | G3: DIRECCIÓNDEGESTIÓNFINANCIERA/DIRECCIÓNDERECURSOSFÍSICOSYNEGOCIOS | H3: 2026-06-30 | I3: https://drive.google.com/drive/u/0/folders/1bmZSYTZPlrSq234glXYiTJCO48SccgqJ
B4: 2025 | C4: 90 | D4: 3.2.1.1.2 | E4: HALLAZGO ADMINISTRATIVO CON PRESUNTA INCIDENCIA DISCIPLINARIA POR DEFICIENCIAS EN EL COBRO DE LOS CÁNONES DE ARRENDAMIENTO CAUSADOS DURANTE LA EJECUCIÓN DE LOS CONTRATOS DE ARRENDAMIENTO A-027-TQLL-2003; A-024-P.D.-2003; T-S.-2009 CÓDIGO A – L.3 EN Z.T.; Y TT NO. 90 DE 2015. | F4: ACTUALIZACIÓN DEL PROCEDIMIENTO DE GESTIÓN INMOBILIARIA QUE DEFINA LOS CONTROLES PARA EJERCER LAS ACCIONES DE COBRO DE CANONES DE ARRENDAMIENTO, EL PROCESO Y RESPONSABLES DE DECLARATORIA DE SINIESTRO EN LOS CASOS EN LOS QUE SE CUENTE CON GARANTÍAS DE ARRENDAMIENTO, O, LOS REQUISITOS, PROCEDIMIENTO Y RESPONSABLES PARA EL EJERCICIO DE ACCIONES DE COBRO COACTIVO | G4: DIRECCIÓNDERECURSOSFÍSICOSYNEGOCIOS/SUBGERENCIAJURÍDICA | H4: 2026-10-13 | I4: https://drive.google.com/drive/u/0/folders/1QT49y1L5HwPHxc-EwvXz5gLce7HGc71K
B5: 2025 | C5: 90 | D5: 3.2.1.1.3 | E5: HALLAZGO ADMINISTRATIVO CON PRESUNTA INCIDENCIA DISCIPLINARIA POR LA GESTIÓN INEFICIENTE DE LA TERMINAL DE TRANSPORTE S.A. DURANTE DEL PROCESO DE EXPROPIACIÓN ADMINISTRATIVA ADELANTADO POR LA EMPRESA FÉRREA REGIONAL S.A.S. RESPECTO DEL PREDIO DENOMINADO “SANTA HELENA”, IDENTIFICADO CON LA MATRÍCULA INMOBILIARIA 051-191183, ASÍ COMO SU GESTIÓN INOPORTUNA EN LA DEFENSA DE LOS INTERESES DE LA ENTIDAD RESPECTO DEL COBRO DEL IMPUESTO PREDIAL | F5: CREACIÓN DE PROCEDIMIENTO PARA TRÁMITE DE EXPROPIACIONES DE LOS BIENES DE LA TTSA | G5: SUBGERENCIAJURÍDICA | H5: 2026-10-13 | I5: https://drive.google.com/drive/u/0/folders/1kilX7Bb9sV8Qh-eNoVoUyX1WaRol3HVN
B6: 2025 | C6: 90 | D6: 3.2.1.1.3 | E6: HALLAZGO ADMINISTRATIVO CON PRESUNTA INCIDENCIA DISCIPLINARIA POR LA GESTIÓN INEFICIENTE DE LA TERMINAL DE TRANSPORTE S.A. DURANTE DEL PROCESO DE EXPROPIACIÓN ADMINISTRATIVA ADELANTADO POR LA EMPRESA FÉRREA REGIONAL S.A.S. RESPECTO DEL PREDIO DENOMINADO “SANTA HELENA”, IDENTIFICADO CON LA MATRÍCULA INMOBILIARIA 051-191183, ASÍ COMO SU GESTIÓN INOPORTUNA EN LA DEFENSA DE LOS INTERESES DE LA ENTIDAD RESPECTO DEL COBRO DEL IMPUESTO PREDIAL | F6: GESTIÓN PARA LA MODIFICACIÓN DE LA RESOLUCIÓN NO. 25-75400001616-2025 EXPEDIDA POR EL MUNICIPIO DE SOACHA, CON EL FIN DE QUE SE AJUSTE EL ÁREA DEL PREDIO | G6: DIRECCIÓNDERECURSOSFÍSICOSYNEGOCIOS | H6: 2026-10-13 | I6: https://drive.google.com/drive/u/0/folders/1EubnA9GmEsmbl7UFcOUTjsykCzJiqONA
B7: 2025 | C7: 90 | D7: 3.2.1.1.3 | E7: HALLAZGO ADMINISTRATIVO CON PRESUNTA INCIDENCIA DISCIPLINARIA POR LA GESTIÓN INEFICIENTE DE LA TERMINAL DE TRANSPORTE S.A. DURANTE DEL PROCESO DE EXPROPIACIÓN ADMINISTRATIVA ADELANTADO POR LA EMPRESA FÉRREA REGIONAL S.A.S. RESPECTO DEL PREDIO DENOMINADO “SANTA HELENA”, IDENTIFICADO CON LA MATRÍCULA INMOBILIARIA 051-191183, ASÍ COMO SU GESTIÓN INOPORTUNA EN LA DEFENSA DE LOS INTERESES DE LA ENTIDAD RESPECTO DEL COBRO DEL IMPUESTO PREDIAL | F7: RELIQUIDACIÓN DE IMPUESTOS CON FUNDAMENTO EN LA REDEFINICIÓN DEL ÁREA DEL PREDIO, CONFORME A LA MODIFICACIÓN DE LA RESOLUCIÓN CITADA | G7: DIRECCIÓNDEGESTIÓNFINANCIERA | H7: 2026-10-13 | I7: https://drive.google.com/drive/u/0/folders/1RljHJeJbF-CMMxCEgzMTaJzp2W7ejDiQ
B8: 2025 | C8: 90 | D8: 3.2.1.5.1 | E8: HALLAZGO ADMINISTRATIVO CON INCIDENCIA FISCAL POR LA SUMA DE CUATRO MIL OCHOCIENTOS NOVENTA Y SEIS MILLONES OCHOCIENTOS VEINTIDÓS MIL OCHOCIENTOS VEINTINUEVE PESOS M/CTE $4.896.822.829 Y PRESUNTA INCIDENCIA DISCIPLINARIA POR FALTA DE GESTIÓN OPORTUNA EN LA PRESENTACIÓN DE LAS DECLARACIONES DEL IMPUESTO PREDIAL UNIFICADO DEL INMUEBLE IDENTIFICADO CON CHIP AAA0077FYUH, VIGENCIAS 2015, 2016, 2017, 2020,2021, 2022 Y 2023 | F8: DECISIÓN DE LA DEMANDA INTERPUESTA EL 12/MARZ/2025 CON RADICADO NO. 25000234100020250038300, EN EL TRIBUNAL ADMINISTRATIVO DE CUNDINAMARCA | G8: SUBGERENCIAJURÍDICA | H8: 2026-10-13 | I8: https://drive.google.com/drive/u/0/folders/1IS9BzI07vze98OgBUC7T6wwNdSXGpNkr
B9: 2025 | C9: 90 | D9: 3.4.2.2.1 | E9: HALLAZGO ADMINISTRATIVO CON INCIDENCIA FISCAL EN CUANTÍA DE SEISCIENTOS CINCO MILLONES QUINIENTOS SETENTA MIL CIENTO NOVENTA Y DOS PESOS M/CTE $605.570.192, Y PRESUNTA INCIDENCIA DISCIPLINARIA, POR EL PAGO INJUSTIFICADO DEL AIU Y PARTE DEL IVA EN EL MARCO DEL CONTRATO TT-034-2024. | F9: ANEXO AL ESTUDIO DE MERCADO DE LOS PROCESOS DE SELECCIÓN PARA LA CONTRATACIÓN DE SERVICIOS DE VIGILANCIA, QUE DETALLE LOS COSTOS E IMPUESTOS GENERADOS POR ÉSTE SERVICIO | G9: SUBGERENCIACORPORATIVA | H9: 2026-10-13 | I9: https://drive.google.com/drive/u/0/folders/1QycXzX7KEyRWZIzCiZduAkCCQ4bGJsSg
B10: 2025 | C10: 90 | D10: 3.4.2.2.1 | E10: HALLAZGO ADMINISTRATIVO CON INCIDENCIA FISCAL EN CUANTÍA DE SEISCIENTOS CINCO MILLONES QUINIENTOS SETENTA MIL CIENTO NOVENTA Y DOS PESOS M/CTE $605.570.192, Y PRESUNTA INCIDENCIA DISCIPLINARIA, POR EL PAGO INJUSTIFICADO DEL AIU Y PARTE DEL IVA EN EL MARCO DEL CONTRATO TT-034-2024. | F10: CONCEPTOS TÉCNICOS DE COLOMBIA COMPRA EFICIENTE Y DE LOS ENTES REGULADORES Y/O DE CONTROL SOBRE EL TRATAMIENTO DE AIU | G10: SUBGERENCIACORPORATIVA | H10: 2026-10-13 | I10: https://drive.google.com/drive/u/0/folders/1tuZORUcxjX6PVP3fksW0wknXGprxA46m
B11: 2025 | C11: 90 | D11: 3.4.2.3.1 | E11: HALLAZGO ADMINISTRATIVO CON PRESUNTA INCIDENCIA DISCIPLINARIA POR NO APLICAR EL PRINCIPIO DE PLANEACIÓN YA QUE SE EVIDENCIA LA ACTUALIZACIÓN DE PRECIOS SEGÚN LA OFERTA COMERCIAL, PARA EL CONTRATO TT 172 DE 2024 SIN QUE EL MISMO TUVIESE FORMULA DE REAJUSTE. | F11: INCORPORACIÓN CONTRACTUAL DE CLÁUSULA DE ACTUALIZACIÓN DE PRECIOS UNITARIOS POR CAMBIO DE VIGENCIA, EN LOS CONTRATOS QUE APLIQUE | G11: DIRECCIÓNDEINFRAESTRUCTURA | H11: 2026-10-13 | I11: https://drive.google.com/drive/u/0/folders/1f-eEYBbHrafzNrQi8Fnv29rVPz4-XqL_
B12: 2025 | C12: 90 | D12: 3.4.2.3.2 | E12: HALLAZGO ADMINISTRATIVO, POR EL INCUMPLIMIENTO EN LA OBLIGACIÓN DE LA ENTIDAD DE PUBLICAR INFORMACIÓN CONTRACTUAL EN LA PLATAFORMA SECOP II, PARA LOS CONTRATOS TT 172 Y TT 112 DE 2024. | F12: MEMORANDO DE LINEAMIENTOS EMITIDO POR LA SUB GERENCIA JURÍDICA SOBRE EL PROCEDIMIENTO DE PUBLICACIÓN EN LA PLATAFORMA SECOP, LA DEFINICIÓN DE RESPONSABLES, PLAZOS, PUBLICACIONES OBLIGATORIAS Y OPCIONALES | G12: SUBGERENCIAJURÍDICA | H12: 2026-10-13 | I12: https://drive.google.com/drive/u/0/folders/1dsZmy5um6-qhZPvusn_XKe0f6iNeojJy
B13: 2025 | C13: 90 | D13: 4.2.1 | E13: HALLAZGO ADMINISTRATIVO CON PRESUNTA INCIDENCIA DISCIPLINARIA POR FALTA DE DILIGENCIA Y GESTIÓN OPORTUNA DE LOS REGISTROS “NO PAGOS” EN EL ESTACIONAMIENTO EN VÍA (ZONAS DE PARQUEO PAGO – ZPP) POR PARTE DE LA TERMINAL DE TRANSPORTE S.A. (TTSA). | F13: ACTUALIZACIÓN DEL PROCEDIMIENTO GPE-PRO2 GESTIÓN Y RECUPERACIÓN DE LOS REGISTROS SUSCEPTIBLES DE GESTIÓN DE ZPP QUE INCLUYA EL CONTROL AUTOMÁTICO DE LAS ALERTAS QUE GENERA EL APLICATIVO RESPECTO A LOS USOS DE LOS USUARIOS CUANDO PRESETAN REGISTROS "NO PAGOS" PARA QUE EL PERSONAL EN VÍA REALICE EL COBRO Ó EL USUARIO REALICE EL PAGO DEL MISMO PARA PODER HACER USO DE LAS ZONAS DE PARQUEO PAGO | G13: SUBGERENCIADESERVICIOSOPERACIONALESEINFRAESTRUCTURA | H13: 2026-06-30 | I13: https://drive.google.com/drive/u/0/folders/1ob0EHj5xccHYorw-3njw11UNR-cvSjI2

Sheet Hoja4
B2: VIGENCIA DE LA AUDITORÍA O VISITA | C2: CODIGO AUDITORÍA SEGÚN PAD DE LA VIGENCIA | D2: No. HALLAZGO | E2: DESCRIPCIÓN HALLAZGO | F2: DESCRIPCIÓN ACCIÓN | G2: AREA RESPONSABLE | H2: FECHA DE TERMINACIÓN
B3: 2024 | C3: 90 | D3: 3.2.1.2 | E3: HALLAZGO ADMINISTRATIVA CON PRESUNTA INCIDENCIA DISCIPLINARIA Y FISCAL EN CUANTÍA DE $2.124.470, POR PAGO DE SANCIONES E INTERESES DE MORA ANTE LA SECRETARÍA DISTRITAL DE HACIENDA DURANTE LA VIGENCIA 2023 | F3: SE ESTABLECERAN INTERFACES CON LOS DIFERENTES PROGRAMAS DE MANEJO DE INGRESOS, QUE REDUZCAN PROCESOS MANUALES QUE MINIMICEN LA INTERVENCIÓN HUMANA EN EL REGISTRO DE LA INFORMACIÓN | G3: SUBGERENCIACORPORATIVA/DIRECCIÓNDERECURSOSTECNOLÓGICOS | H3: 2025-06-30
B4: 2024 | C4: 90 | D4: 3.2.1.3 | E4: HALLAZGO ADMINISTRATIVA CON PRESUNTA INCIDENCIA DISCIPLINARIA Y FISCAL EN CUANTÍA DE $3.902.504, POR PAGO DE SANCIONES E INTERESES DE MORA ANTE LA DIRECCIÓN DE IMPUESTOS Y ADUANAS NACIONALES – DIAN | F4: SE ESTABLECERÁN INTERFACES CON LOS DIFERENTES PROGRAMAS DE MANEJO DE INGRESOS, QUE REDUZCAN PROCESOS MANUALES QUE MINIMICEN LA INTERVENCIÓN HUMANA EN EL REGISTRO DE LA INFORMACIÓN | G4: SUBGERENCIACORPORATIVA/DIRECCIÓNDERECURSOSTECNOLÓGICOS | H4: 2025-06-30
B5: 2025 | C5: 90 | D5: 3.3.1.1 | E5: HALLAZGO ADMINISTRATIVO POR EL INCUMPLIMIENTO DE ALGUNAS ACTIVIDADES DEL LINEAMIENTO PRESUPUESTAL ORDENADO EN SU MANUAL DE PRESUPUESTO. CÓDIGO: GAF-MN06 VERSIÓN 7, AGOSTO DE 2018. | F5: ACTUALIZACIÓN DEL MANUAL DEL PRESUPUESTO | G5: SUBGERENCIACORPORATIVA/DIRECCIÓNDEGESTIÓNFINANCIERA | H5: 46142
B6: 2025 | D6: 3.3.2.2 | E6: HALLAZGO ADMINISTRATIVO CON PRESUNTA INCIDENCIA DISCIPLINARIA, POR CUANTO LA TERMINAL DE TRANSPORTE, POSEE DOS TIPOS DE REGISTROS DE EXPEDICIÓN DE CDP Y CRP, QUE PRESENTAN INCONSISTENCIAS. | F6: ACTUALIZACIÓN DEL MANUAL DEL PRESUPUESTO | G6: SUBGERENCIACORPORATIVA/DIRECCIÓNDEGESTIÓNFINANCIERA | H6: 2026-04-30
B7: 2025 | D7: 3.3.2.3.1 | E7: HALLAZGO ADMINISTRATIVO POR CUANTO LA TERMINAL PRESENTA SALDOS SIN PAGO EN LAS CXP VIGENCIA 2023 A PAGAR EN ENERO DE 2024 Y 2024 A PAGAR EN ENERO DE 2025, INCUMPLIENDO LO SEÑALADO EN SU PROCEDIMIENTO INTERNO. | F7: ACTUALIZACIÓN DEL MANUAL DEL PRESUPUESTO | G7: SUBGERENCIACORPORATIVA/DIRECCIÓNDEGESTIÓNFINANCIERA | H7: 2026-04-30
B8: 2025 | D8: 3.4.2.1.1 | E8: HALLAZGO ADMINISTRATIVO CON INCIDENCIA FISCAL EN CUANTÍA DE $1.482.567.858 Y PRESUNTA INCIDENCIA DISCIPLINARIA TODA VEZ QUE, EN DESARROLLO DEL CONTRATO 99 DE 2019 SUSCRITO ENTRE LA TERMINAL DE TRANSPORTE S.A. Y PROTECH INGENIERÍA S.A.S, SE PRODUJO UNA GESTIÓN FISCAL ANTIECONÓMICA, INEFICAZ, INEFICIENTE, PORQUE EL SISTEMA ADQUIRIDO NO CUMPLE CON EL OBJETO DEL CONTRATO, NO ES FUNCIONAL. | F8: PRESENTACIÓN POR PARTE DE LOS SUPERVISORES DEL CONTRATO, DE INFORME QUE DETALLE Y EXPLIQUE EL FUNCIONAMIENTO DE CADA UNO DE LOS COMPONENTES DE LA SOLUCIÓN, Y EVIDENCIA DE LAS PRUEBAS EFECTUADAS PARA EL RECIBO DE LA MISMA. ADEMÁS, DEL FUNCIONAMIENTO ACTUAL DE LA SOLUCIÓN TECNOLÓGICA Y EL ESTADO DE LAS RECLAMACIONES GESTIONADAS ANTE LA ASEGURADORA | G8: SUBGERENCIADESERVICIOSOPERACIONALESEINFRAESTRUCTURA | H8: 2025-12-31
B9: 2025 | D9: 3.4.2.3.3 | E9: HALLAZGO ADMINISTRATIVO POR NO APLICAR EL PRINCIPIO DE PLANEACIÓN YA QUE SE EVIDENCIA EL PAGO DE LOS ÍTEMS NO PREVISTOS ANTES DE SER APROBADOS POR EL SUPERVISOR DEL CONTRATO TT 112 DE 2024, EVIDENCIANDO UN INCUMPLIMIENTO EN LAS OBLIGACIONES DE LA ENTIDAD. | F9: CAPACITACIÓN POR PARTE DE LA SUBGERENCIA JURÍDICA, SOBRE LA SUPERVISIÓN DE CONTRATOS, QUE INCLUYA ÍTEMS NO PREVISTOS Y RECONOCIMIENTO PARA EL PAGO | G9: SUBGERENCIAJURÍDICA | H9: 2026-02-28
B10: 2025 | D10: 3.4.2.4.1 | E10: HALLAZGO ADMINISTRATIVO CON PRESUNTA INCIDENCIA DISCIPLINARIA Y PENAL DEBIDO A QUE DE LOS RECURSOS INICIALMENTE ASIGNADOS AL CONTRATO 135 DE 2023 FUERON DISMINUIDOS EN LA SUMA $9.000.00 MILLONES, SIN LA EXPEDICIÓN DEL CORRESPONDIENTE ACTO ADMINISTRATIVO QUE PERMITIERA LA LIBERACIÓN DE ESTOS RECURSOS, GENERANDO LA DESFINANCIACIÓN DEL MISMO. | F10: ACTUALIZACIÓN DEL MANUAL DE PRESUPUESTO PARA LA VALIDACIÓN DE REQUISITOS PARA LA MODIFICACIÓN DE CDP | G10: DIRECCIÓNDEGESTIÓNFINANCIERA | H10: 2026-04-30
B11: 2025 | D11: 3.4.2.4.1 | F11: INFORME DE LA DIRECCIÓN FINANCIERA PARA INDICAR EL MANEJO DE LOS CDP | G11: DIRECCIÓNDEGESTIÓNFINANCIERA | H11: 2026-04-30

Sheet Resumen
C3: Vigencia | D3: Auditoría | E3: No. Hallazgo | F3: Responsable | G3: Total hallazgos | H3: Total Planes de acción | I3: Abiertos | J3: Vencidos | K3: Finalizados | L3: Alerta 10 | M3: Alerta 20 | N3: Alerta 30 | O3: Alerta 5 | P3: Ene | Q3: Feb | R3: Marzo | S3: Abr | T3: May | U3: Jun
C4: 2025 | D4: 90 | E4: 3.1.1 | F4: DIRECCIÓNDEGESTIÓNFINANCIERA/DIRECCIÓNDERECURSOSFÍSICOSYNEGOCIOS | G4: =IF(COUNTIFS($C$4:C4, C4, $D$4:D4, D4, $E$4:E4, E4)=1, 1, 0) -> 1 | H4: {=SUMPRODUCT((TRIM(CLEAN('Base de Datos'!$F$2:$F$3000))&""=TRIM(CLEAN(C4))&"")*(TRIM(CLEAN('Base de Datos'!$G$2:$G$3000))&""=TRIM(CLEAN(D4))&"")*(TRIM(CLEAN('Base de Datos'!$H$2:$H$3000))&""=TRIM(CLEAN(E4))&"")*(TRIM(CLEAN('Base de Datos'!$U$2:$U$3000))&""=TRIM(CLEAN(F4))&""))} -> 0 | I4: =COUNTIFS('Base de Datos'!$F:$F,$C4,'Base de Datos'!$G:$G,$D4,'Base de Datos'!$H:$H,$E4,'Base de Datos'!$U:$U,$F4,'Base de Datos'!$AA:$AA,"Abierta") -> 0 | J4: =COUNTIFS('Base de Datos'!$F:$F,$C4,'Base de Datos'!$G:$G,$D4,'Base de Datos'!$H:$H,$E4,'Base de Datos'!$U:$U,$F4,'Base de Datos'!$AA:$AA,"Vencida") -> 0 | K4: =COUNTIFS('Base de Datos'!$F:$F,$C4,'Base de Datos'!$G:$G,$D4,'Base de Datos'!$H:$H,$E4,'Base de Datos'!$U:$U,$F4,'Base de Datos'!$AA:$AA,"Finalizada") -> 0 | L4: =COUNTIFS('Base de Datos'!$F:$F,$C4,'Base de Datos'!$G:$G,$D4,'Base de Datos'!$H:$H,$E4,'Base de Datos'!$U:$U,$F4,'Base de Datos'!$AA:$AA,"Abierta",'Base de Datos'!$AC:$AC,"<=10",'Base de Datos'!$AC:$AC,">0") -> 0 | M4: =COUNTIFS('Base de Datos'!$F:$F,$C4,'Base de Datos'!$G:$G,$D4,'Base de Datos'!$H:$H,$E4,'Base de Datos'!$U:$U,$F4,'Base de Datos'!$AA:$AA,"Abierta",'Base de Datos'!$AC:$AC,"<=20",'Base de Datos'!$AC:$AC,">10") -> 0 | N4: =COUNTIFS('Base de Datos'!$F:$F,$C4,'Base de Datos'!$G:$G,$D4,'Base de Datos'!$H:$H,$E4,'Base de Datos'!$U:$U,$F4,'Base de Datos'!$AA:$AA,"Abierta",'Base de Datos'!$AC:$AC,"<=30",'Base de Datos'!$AC:$AC,">20") -> 0 | O4: =COUNTIFS('Base de Datos'!$F:$F,$C4,'Base de Datos'!$G:$G,$D4,'Base de Datos'!$H:$H,$E4,'Base de Datos'!$U:$U,$F4,'Base de Datos'!$AA:$AA,"Abierta",'Base de Datos'!$AG:$AG,1) -> 0 | P4: =COUNTIFS('Base de Datos'!$F:$F, $C4, 'Base de Datos'!$H:$H, $E4, 'Base de Datos'!$U:$U, $F4, 'Base de Datos'!$AA:$AA, "Finalizada", 'Base de Datos'!#REF!, ">=01/01/2026", 'Base de Datos'!#REF!, "<=31/01/2026") -> #REF! | Q4: =COUNTIFS('Base de Datos'!$F:$F, $C4, 'Base de Datos'!$H:$H, $E4, 'Base de Datos'!$U:$U, $F4, 'Base de Datos'!$AA:$AA, "Finalizada", 'Base de Datos'!#REF!, ">=01/02/2026", 'Base de Datos'!#REF!, "<=28/02/2026") -> #REF! | R4: =COUNTIFS('Base de Datos'!$F:$F, $C4, 'Base de Datos'!$H:$H, $E4, 'Base de Datos'!$U:$U, $F4, 'Base de Datos'!$AA:$AA, "Finalizada", 'Base de Datos'!#REF!, ">=01/03/2026", 'Base de Datos'!#REF!, "<=31/03/2026") -> #REF! | S4: =COUNTIFS('Base de Datos'!$F:$F, $C4, 'Base de Datos'!$H:$H, $E4, 'Base de Datos'!$U:$U, $F4, 'Base de Datos'!$AA:$AA, "Finalizada", 'Base de Datos'!#REF!, ">=01/04/2026", 'Base de Datos'!#REF!, "<=30/04/2026") -> #REF! | T4: =COUNTIFS('Base de Datos'!$F:$F, $C4, 'Base de Datos'!$H:$H, $E4, 'Base de Datos'!$U:$U, $F4, 'Base de Datos'!$AA:$AA, "Finalizada", 'Base de Datos'!#REF!, ">=01/05/2026", 'Base de Datos'!#REF!, "<=31/05/2026") -> #REF! | U4: =COUNTIFS('Base de Datos'!$F:$F, $C4, 'Base de Datos'!$H:$H, $E4, 'Base de Datos'!$U:$U, $F4, 'Base de Datos'!$AA:$AA, "Finalizada", 'Base de Datos'!#REF!, ">=01/06/2026", 'Base de Datos'!#REF!, "<=30/06/2026") -> #REF!
C5: 2025 | D5: 90 | E5: 3.1.1 | F5: DIRECCIÓNDEGESTIÓNFINANCIERA | G5: =IF(COUNTIFS($C$4:C5, C5, $D$4:D5, D5, $E$4:E5, E5)=1, 1, 0) -> 0 | H5: {=SUMPRODUCT((TRIM(CLEAN('Base de Datos'!$F$2:$F$3000))&""=TRIM(CLEAN(C5))&"")*(TRIM(CLEAN('Base de Datos'!$G$2:$G$3000))&""=TRIM(CLEAN(D5))&"")*(TRIM(CLEAN('Base de Datos'!$H$2:$H$3000))&""=TRIM(CLEAN(E5))&"")*(TRIM(CLEAN('Base de Datos'!$U$2:$U$3000))&""=TRIM(CLEAN(F5))&""))} -> 0 | I5: =COUNTIFS('Base de Datos'!$F:$F,$C5,'Base de Datos'!$G:$G,$D5,'Base de Datos'!$H:$H,$E5,'Base de Datos'!$U:$U,$F5,'Base de Datos'!$AA:$AA,"Abierta") -> 0 | J5: =COUNTIFS('Base de Datos'!$F:$F,$C5,'Base de Datos'!$G:$G,$D5,'Base de Datos'!$H:$H,$E5,'Base de Datos'!$U:$U,$F5,'Base de Datos'!$AA:$AA,"Vencida") -> 0 | K5: =COUNTIFS('Base de Datos'!$F:$F,$C5,'Base de Datos'!$G:$G,$D5,'Base de Datos'!$H:$H,$E5,'Base de Datos'!$U:$U,$F5,'Base de Datos'!$AA:$AA,"Finalizada") -> 0 | L5: =COUNTIFS('Base de Datos'!$F:$F,$C5,'Base de Datos'!$G:$G,$D5,'Base de Datos'!$H:$H,$E5,'Base de Datos'!$U:$U,$F5,'Base de Datos'!$AA:$AA,"Abierta",'Base de Datos'!$AC:$AC,"<=10",'Base de Datos'!$AC:$AC,">0") -> 0 | M5: =COUNTIFS('Base de Datos'!$F:$F,$C5,'Base de Datos'!$G:$G,$D5,'Base de Datos'!$H:$H,$E5,'Base de Datos'!$U:$U,$F5,'Base de Datos'!$AA:$AA,"Abierta",'Base de Datos'!$AC:$AC,"<=20",'Base de Datos'!$AC:$AC,">10") -> 0 | N5: =COUNTIFS('Base de Datos'!$F:$F,$C5,'Base de Datos'!$G:$G,$D5,'Base de Datos'!$H:$H,$E5,'Base de Datos'!$U:$U,$F5,'Base de Datos'!$AA:$AA,"Abierta",'Base de Datos'!$AC:$AC,"<=30",'Base de Datos'!$AC:$AC,">20") -> 0 | O5: =COUNTIFS('Base de Datos'!$F:$F,$C5,'Base de Datos'!$G:$G,$D5,'Base de Datos'!$H:$H,$E5,'Base de Datos'!$U:$U,$F5,'Base de Datos'!$AA:$AA,"Abierta",'Base de Datos'!$AG:$AG,1) -> 0 | P5: =COUNTIFS('Base de Datos'!$F:$F, $C5, 'Base de Datos'!$H:$H, $E5, 'Base de Datos'!$U:$U, $F5, 'Base de Datos'!$AA:$AA, "Finalizada", 'Base de Datos'!#REF!, ">=01/01/2026", 'Base de Datos'!#REF!, "<=31/01/2026") -> #REF! | Q5: =COUNTIFS('Base de Datos'!$F:$F, $C5, 'Base de Datos'!$H:$H, $E5, 'Base de Datos'!$U:$U, $F5, 'Base de Datos'!$AA:$AA, "Finalizada", 'Base de Datos'!#REF!, ">=01/02/2026", 'Base de Datos'!#REF!, "<=28/02/2026") -> #REF! | R5: =COUNTIFS('Base de Datos'!$F:$F, $C5, 'Base de Datos'!$H:$H, $E5, 'Base de Datos'!$U:$U, $F5, 'Base de Datos'!$AA:$AA, "Finalizada", 'Base de Datos'!#REF!, ">=01/03/2026", 'Base de Datos'!#REF!, "<=31/03/2026") -> #REF! | S5: =COUNTIFS('Base de Datos'!$F:$F, $C5, 'Base de Datos'!$H:$H, $E5, 'Base de Datos'!$U:$U, $F5, 'Base de Datos'!$AA:$AA, "Finalizada", 'Base de Datos'!#REF!, ">=01/04/2026", 'Base de Datos'!#REF!, "<=30/04/2026") -> #REF! | T5: =COUNTIFS('Base de Datos'!$F:$F, $C5, 'Base de Datos'!$H:$H, $E5, 'Base de Datos'!$U:$U, $F5, 'Base de Datos'!$AA:$AA, "Finalizada", 'Base de Datos'!#REF!, ">=01/05/2026", 'Base de Datos'!#REF!, "<=31/05/2026") -> #REF! | U5: =COUNTIFS('Base de Datos'!$F:$F, $C5, 'Base de Datos'!$H:$H, $E5, 'Base de Datos'!$U:$U, $F5, 'Base de Datos'!$AA:$AA, "Finalizada", 'Base de Datos'!#REF!, ">=01/06/2026", 'Base de Datos'!#REF!, "<=30/06/2026") -> #REF!
C6: 2025 | D6: 90 | E6: 3.1.2 | F6: DIRECCIÓNDERECURSOSFÍSICOSYNEGOCIOS | G6: =IF(COUNTIFS($C$4:C6, C6, $D$4:D6, D6, $E$4:E6, E6)=1, 1, 0) -> 1 | H6: {=SUMPRODUCT((TRIM(CLEAN('Base de Datos'!$F$2:$F$3000))&""=TRIM(CLEAN(C6))&"")*(TRIM(CLEAN('Base de Datos'!$G$2:$G$3000))&""=TRIM(CLEAN(D6))&"")*(TRIM(CLEAN('Base de Datos'!$H$2:$H$3000))&""=TRIM(CLEAN(E6))&"")*(TRIM(CLEAN('Base de Datos'!$U$2:$U$3000))&""=TRIM(CLEAN(F6))&""))} -> 0 | I6: =COUNTIFS('Base de Datos'!$F:$F,$C6,'Base de Datos'!$G:$G,$D6,'Base de Datos'!$H:$H,$E6,'Base de Datos'!$U:$U,$F6,'Base de Datos'!$AA:$AA,"Abierta") -> 0 | J6: =COUNTIFS('Base de Datos'!$F:$F,$C6,'Base de Datos'!$G:$G,$D6,'Base de Datos'!$H:$H,$E6,'Base de Datos'!$U:$U,$F6,'Base de Datos'!$AA:$AA,"Vencida") -> 0 | K6: =COUNTIFS('Base de Datos'!$F:$F,$C6,'Base de Datos'!$G:$G,$D6,'Base de Datos'!$H:$H,$E6,'Base de Datos'!$U:$U,$F6,'Base de Datos'!$AA:$AA,"Finalizada") -> 0 | L6: =COUNTIFS('Base de Datos'!$F:$F,$C6,'Base de Datos'!$G:$G,$D6,'Base de Datos'!$H:$H,$E6,'Base de Datos'!$U:$U,$F6,'Base de Datos'!$AA:$AA,"Abierta",'Base de Datos'!$AC:$AC,"<=10",'Base de Datos'!$AC:$AC,">0") -> 0 | M6: =COUNTIFS('Base de Datos'!$F:$F,$C6,'Base de Datos'!$G:$G,$D6,'Base de Datos'!$H:$H,$E6,'Base de Datos'!$U:$U,$F6,'Base de Datos'!$AA:$AA,"Abierta",'Base de Datos'!$AC:$AC,"<=20",'Base de Datos'!$AC:$AC,">10") -> 0 | N6: =COUNTIFS('Base de Datos'!$F:$F,$C6,'Base de Datos'!$G:$G,$D6,'Base de Datos'!$H:$H,$E6,'Base de Datos'!$U:$U,$F6,'Base de Datos'!$AA:$AA,"Abierta",'Base de Datos'!$AC:$AC,"<=30",'Base de Datos'!$AC:$AC,">20") -> 0 | O6: =COUNTIFS('Base de Datos'!$F:$F,$C6,'Base de Datos'!$G:$G,$D6,'Base de Datos'!$H:$H,$E6,'Base de Datos'!$U:$U,$F6,'Base de Datos'!$AA:$AA,"Abierta",'Base de Datos'!$AG:$AG,1) -> 0 | P6: =COUNTIFS('Base de Datos'!$F:$F, $C6, 'Base de Datos'!$H:$H, $E6, 'Base de Datos'!$U:$U, $F6, 'Base de Datos'!$AA:$AA, "Finalizada", 'Base de Datos'!#REF!, ">=01/01/2026", 'Base de Datos'!#REF!, "<=31/01/2026") -> #REF! | Q6: =COUNTIFS('Base de Datos'!$F:$F, $C6, 'Base de Datos'!$H:$H, $E6, 'Base de Datos'!$U:$U, $F6, 'Base de Datos'!$AA:$AA, "Finalizada", 'Base de Datos'!#REF!, ">=01/02/2026", 'Base de Datos'!#REF!, "<=28/02/2026") -> #REF! | R6: =COUNTIFS('Base de Datos'!$F:$F, $C6, 'Base de Datos'!$H:$H, $E6, 'Base de Datos'!$U:$U, $F6, 'Base de Datos'!$AA:$AA, "Finalizada", 'Base de Datos'!#REF!, ">=01/03/2026", 'Base de Datos'!#REF!, "<=31/03/2026") -> #REF! | S6: =COUNTIFS('Base de Datos'!$F:$F, $C6, 'Base de Datos'!$H:$H, $E6, 'Base de Datos'!$U:$U, $F6, 'Base de Datos'!$AA:$AA, "Finalizada", 'Base de Datos'!#REF!, ">=01/04/2026", 'Base de Datos'!#REF!, "<=30/04/2026") -> #REF! | T6: =COUNTIFS('Base de Datos'!$F:$F, $C6, 'Base de Datos'!$H:$H, $E6, 'Base de Datos'!$U:$U, $F6, 'Base de Datos'!$AA:$AA, "Finalizada", 'Base de Datos'!#REF!, ">=01/05/2026", 'Base de Datos'!#REF!, "<=31/05/2026") -> #REF! | U6: =COUNTIFS('Base de Datos'!$F:$F, $C6, 'Base de Datos'!$H:$H, $E6, 'Base de Datos'!$U:$U, $F6, 'Base de Datos'!$AA:$AA, "Finalizada", 'Base de Datos'!#REF!, ">=01/06/2026", 'Base de Datos'!#REF!, "<=30/06/2026") -> #REF!
C7: 2025 | D7: 90 | E7: 3.2.1.1.1 | F7: DIRECCIÓNDEGESTIÓNHUMANA | G7: =IF(COUNTIFS($C$4:C7, C7, $D$4:D7, D7, $E$4:E7, E7)=1, 1, 0) -> 1 | H7: {=SUMPRODUCT((TRIM(CLEAN('Base de Datos'!$F$2:$F$3000))&""=TRIM(CLEAN(C7))&"")*(TRIM(CLEAN('Base de Datos'!$G$2:$G$3000))&""=TRIM(CLEAN(D7))&"")*(TRIM(CLEAN('Base de Datos'!$H$2:$H$3000))&""=TRIM(CLEAN(E7))&"")*(TRIM(CLEAN('Base de Datos'!$U$2:$U$3000))&""=TRIM(CLEAN(F7))&""))} -> 0 | I7: =COUNTIFS('Base de Datos'!$F:$F,$C7,'Base de Datos'!$G:$G,$D7,'Base de Datos'!$H:$H,$E7,'Base de Datos'!$U:$U,$F7,'Base de Datos'!$AA:$AA,"Abierta") -> 0 | J7: =COUNTIFS('Base de Datos'!$F:$F,$C7,'Base de Datos'!$G:$G,$D7,'Base de Datos'!$H:$H,$E7,'Base de Datos'!$U:$U,$F7,'Base de Datos'!$AA:$AA,"Vencida") -> 0 | K7: =COUNTIFS('Base de Datos'!$F:$F,$C7,'Base de Datos'!$G:$G,$D7,'Base de Datos'!$H:$H,$E7,'Base de Datos'!$U:$U,$F7,'Base de Datos'!$AA:$AA,"Finalizada") -> 0 | L7: =COUNTIFS('Base de Datos'!$F:$F,$C7,'Base de Datos'!$G:$G,$D7,'Base de Datos'!$H:$H,$E7,'Base de Datos'!$U:$U,$F7,'Base de Datos'!$AA:$AA,"Abierta",'Base de Datos'!$AC:$AC,"<=10",'Base de Datos'!$AC:$AC,">0") -> 0 | M7: =COUNTIFS('Base de Datos'!$F:$F,$C7,'Base de Datos'!$G:$G,$D7,'Base de Datos'!$H:$H,$E7,'Base de Datos'!$U:$U,$F7,'Base de Datos'!$AA:$AA,"Abierta",'Base de Datos'!$AC:$AC,"<=20",'Base de Datos'!$AC:$AC,">10") -> 0 | N7: =COUNTIFS('Base de Datos'!$F:$F,$C7,'Base de Datos'!$G:$G,$D7,'Base de Datos'!$H:$H,$E7,'Base de Datos'!$U:$U,$F7,'Base de Datos'!$AA:$AA,"Abierta",'Base de Datos'!$AC:$AC,"<=30",'Base de Datos'!$AC:$AC,">20") -> 0 | O7: =COUNTIFS('Base de Datos'!$F:$F,$C7,'Base de Datos'!$G:$G,$D7,'Base de Datos'!$H:$H,$E7,'Base de Datos'!$U:$U,$F7,'Base de Datos'!$AA:$AA,"Abierta",'Base de Datos'!$AG:$AG,1) -> 0 | P7: =COUNTIFS('Base de Datos'!$F:$F, $C7, 'Base de Datos'!$H:$H, $E7, 'Base de Datos'!$U:$U, $F7, 'Base de Datos'!$AA:$AA, "Finalizada", 'Base de Datos'!#REF!, ">=01/01/2026", 'Base de Datos'!#REF!, "<=31/01/2026") -> #REF! | Q7: =COUNTIFS('Base de Datos'!$F:$F, $C7, 'Base de Datos'!$H:$H, $E7, 'Base de Datos'!$U:$U, $F7, 'Base de Datos'!$AA:$AA, "Finalizada", 'Base de Datos'!#REF!, ">=01/02/2026", 'Base de Datos'!#REF!, "<=28/02/2026") -> #REF! | R7: =COUNTIFS('Base de Datos'!$F:$F, $C7, 'Base de Datos'!$H:$H, $E7, 'Base de Datos'!$U:$U, $F7, 'Base de Datos'!$AA:$AA, "Finalizada", 'Base de Datos'!#REF!, ">=01/03/2026", 'Base de Datos'!#REF!, "<=31/03/2026") -> #REF! | S7: =COUNTIFS('Base de Datos'!$F:$F, $C7, 'Base de Datos'!$H:$H, $E7, 'Base de Datos'!$U:$U, $F7, 'Base de Datos'!$AA:$AA, "Finalizada", 'Base de Datos'!#REF!, ">=01/04/2026", 'Base de Datos'!#REF!, "<=30/04/2026") -> #REF! | T7: =COUNTIFS('Base de Datos'!$F:$F, $C7, 'Base de Datos'!$H:$H, $E7, 'Base de Datos'!$U:$U, $F7, 'Base de Datos'!$AA:$AA, "Finalizada", 'Base de Datos'!#REF!, ">=01/05/2026", 'Base de Datos'!#REF!, "<=31/05/2026") -> #REF! | U7: =COUNTIFS('Base de Datos'!$F:$F, $C7, 'Base de Datos'!$H:$H, $E7, 'Base de Datos'!$U:$U, $F7, 'Base de Datos'!$AA:$AA, "Finalizada", 'Base de Datos'!#REF!, ">=01/06/2026", 'Base de Datos'!#REF!, "<=30/06/2026") -> #REF!
C8: 2025 | D8: 90 | E8: 3.2.1.1.2 | F8: DIRECCIÓNDERECURSOSFÍSICOSYNEGOCIOS/SUBGERENCIAJURÍDICA | G8: =IF(COUNTIFS($C$4:C8, C8, $D$4:D8, D8, $E$4:E8, E8)=1, 1, 0) -> 1 | H8: {=SUMPRODUCT((TRIM(CLEAN('Base de Datos'!$F$2:$F$3000))&""=TRIM(CLEAN(C8))&"")*(TRIM(CLEAN('Base de Datos'!$G$2:$G$3000))&""=TRIM(CLEAN(D8))&"")*(TRIM(CLEAN('Base de Datos'!$H$2:$H$3000))&""=TRIM(CLEAN(E8))&"")*(TRIM(CLEAN('Base de Datos'!$U$2:$U$3000))&""=TRIM(CLEAN(F8))&""))} -> 0 | I8: =COUNTIFS('Base de Datos'!$F:$F,$C8,'Base de Datos'!$G:$G,$D8,'Base de Datos'!$H:$H,$E8,'Base de Datos'!$U:$U,$F8,'Base de Datos'!$AA:$AA,"Abierta") -> 0 | J8: =COUNTIFS('Base de Datos'!$F:$F,$C8,'Base de Datos'!$G:$G,$D8,'Base de Datos'!$H:$H,$E8,'Base de Datos'!$U:$U,$F8,'Base de Datos'!$AA:$AA,"Vencida") -> 0 | K8: =COUNTIFS('Base de Datos'!$F:$F,$C8,'Base de Datos'!$G:$G,$D8,'Base de Datos'!$H:$H,$E8,'Base de Datos'!$U:$U,$F8,'Base de Datos'!$AA:$AA,"Finalizada") -> 0 | L8: =COUNTIFS('Base de Datos'!$F:$F,$C8,'Base de Datos'!$G:$G,$D8,'Base de Datos'!$H:$H,$E8,'Base de Datos'!$U:$U,$F8,'Base de Datos'!$AA:$AA,"Abierta",'Base de Datos'!$AC:$AC,"<=10",'Base de Datos'!$AC:$AC,">0") -> 0 | M8: =COUNTIFS('Base de Datos'!$F:$F,$C8,'Base de Datos'!$G:$G,$D8,'Base de Datos'!$H:$H,$E8,'Base de Datos'!$U:$U,$F8,'Base de Datos'!$AA:$AA,"Abierta",'Base de Datos'!$AC:$AC,"<=20",'Base de Datos'!$AC:$AC,">10") -> 0 | N8: =COUNTIFS('Base de Datos'!$F:$F,$C8,'Base de Datos'!$G:$G,$D8,'Base de Datos'!$H:$H,$E8,'Base de Datos'!$U:$U,$F8,'Base de Datos'!$AA:$AA,"Abierta",'Base de Datos'!$AC:$AC,"<=30",'Base de Datos'!$AC:$AC,">20") -> 0 | O8: =COUNTIFS('Base de Datos'!$F:$F,$C8,'Base de Datos'!$G:$G,$D8,'Base de Datos'!$H:$H,$E8,'Base de Datos'!$U:$U,$F8,'Base de Datos'!$AA:$AA,"Abierta",'Base de Datos'!$AG:$AG,1) -> 0 | P8: =COUNTIFS('Base de Datos'!$F:$F, $C8, 'Base de Datos'!$H:$H, $E8, 'Base de Datos'!$U:$U, $F8, 'Base de Datos'!$AA:$AA, "Finalizada", 'Base de Datos'!#REF!, ">=01/01/2026", 'Base de Datos'!#REF!, "<=31/01/2026") -> #REF! | Q8: =COUNTIFS('Base de Datos'!$F:$F, $C8, 'Base de Datos'!$H:$H, $E8, 'Base de Datos'!$U:$U, $F8, 'Base de Datos'!$AA:$AA, "Finalizada", 'Base de Datos'!#REF!, ">=01/02/2026", 'Base de Datos'!#REF!, "<=28/02/2026") -> #REF! | R8: =COUNTIFS('Base de Datos'!$F:$F, $C8, 'Base de Datos'!$H:$H, $E8, 'Base de Datos'!$U:$U, $F8, 'Base de Datos'!$AA:$AA, "Finalizada", 'Base de Datos'!#REF!, ">=01/03/2026", 'Base de Datos'!#REF!, "<=31/03/2026") -> #REF! | S8: =COUNTIFS('Base de Datos'!$F:$F, $C8, 'Base de Datos'!$H:$H, $E8, 'Base de Datos'!$U:$U, $F8, 'Base de Datos'!$AA:$AA, "Finalizada", 'Base de Datos'!#REF!, ">=01/04/2026", 'Base de Datos'!#REF!, "<=30/04/2026") -> #REF! | T8: =COUNTIFS('Base de Datos'!$F:$F, $C8, 'Base de Datos'!$H:$H, $E8, 'Base de Datos'!$U:$U, $F8, 'Base de Datos'!$AA:$AA, "Finalizada", 'Base de Datos'!#REF!, ">=01/05/2026", 'Base de Datos'!#REF!, "<=31/05/2026") -> #REF! | U8: =COUNTIFS('Base de Datos'!$F:$F, $C8, 'Base de Datos'!$H:$H, $E8, 'Base de Datos'!$U:$U, $F8, 'Base de Datos'!$AA:$AA, "Finalizada", 'Base de Datos'!#REF!, ">=01/06/2026", 'Base de Datos'!#REF!, "<=30/06/2026") -> #REF!
C9: 2025 | D9: 90 | E9: 3.2.1.1.3 | F9: DIRECCIÓNDERECURSOSFÍSICOSYNEGOCIOS | G9: =IF(COUNTIFS($C$4:C9, C9, $D$4:D9, D9, $E$4:E9, E9)=1, 1, 0) -> 1 | H9: {=SUMPRODUCT((TRIM(CLEAN('Base de Datos'!$F$2:$F$3000))&""=TRIM(CLEAN(C9))&"")*(TRIM(CLEAN('Base de Datos'!$G$2:$G$3000))&""=TRIM(CLEAN(D9))&"")*(TRIM(CLEAN('Base de Datos'!$H$2:$H$3000))&""=TRIM(CLEAN(E9))&"")*(TRIM(CLEAN('Base de Datos'!$U$2:$U$3000))&""=TRIM(CLEAN(F9))&""))} -> 0 | I9: =COUNTIFS('Base de Datos'!$F:$F,$C9,'Base de Datos'!$G:$G,$D9,'Base de Datos'!$H:$H,$E9,'Base de Datos'!$U:$U,$F9,'Base de Datos'!$AA:$AA,"Abierta") -> 0 | J9: =COUNTIFS('Base de Datos'!$F:$F,$C9,'Base de Datos'!$G:$G,$D9,'Base de Datos'!$H:$H,$E9,'Base de Datos'!$U:$U,$F9,'Base de Datos'!$AA:$AA,"Vencida") -> 0 | K9: =COUNTIFS('Base de Datos'!$F:$F,$C9,'Base de Datos'!$G:$G,$D9,'Base de Datos'!$H:$H,$E9,'Base de Datos'!$U:$U,$F9,'Base de Datos'!$AA:$AA,"Finalizada") -> 0 | L9: =COUNTIFS('Base de Datos'!$F:$F,$C9,'Base de Datos'!$G:$G,$D9,'Base de Datos'!$H:$H,$E9,'Base de Datos'!$U:$U,$F9,'Base de Datos'!$AA:$AA,"Abierta",'Base de Datos'!$AC:$AC,"<=10",'Base de Datos'!$AC:$AC,">0") -> 0 | M9: =COUNTIFS('Base de Datos'!$F:$F,$C9,'Base de Datos'!$G:$G,$D9,'Base de Datos'!$H:$H,$E9,'Base de Datos'!$U:$U,$F9,'Base de Datos'!$AA:$AA,"Abierta",'Base de Datos'!$AC:$AC,"<=20",'Base de Datos'!$AC:$AC,">10") -> 0 | N9: =COUNTIFS('Base de Datos'!$F:$F,$C9,'Base de Datos'!$G:$G,$D9,'Base de Datos'!$H:$H,$E9,'Base de Datos'!$U:$U,$F9,'Base de Datos'!$AA:$AA,"Abierta",'Base de Datos'!$AC:$AC,"<=30",'Base de Datos'!$AC:$AC,">20") -> 0 | O9: =COUNTIFS('Base de Datos'!$F:$F,$C9,'Base de Datos'!$G:$G,$D9,'Base de Datos'!$H:$H,$E9,'Base de Datos'!$U:$U,$F9,'Base de Datos'!$AA:$AA,"Abierta",'Base de Datos'!$AG:$AG,1) -> 0 | P9: =COUNTIFS('Base de Datos'!$F:$F, $C9, 'Base de Datos'!$H:$H, $E9, 'Base de Datos'!$U:$U, $F9, 'Base de Datos'!$AA:$AA, "Finalizada", 'Base de Datos'!#REF!, ">=01/01/2026", 'Base de Datos'!#REF!, "<=31/01/2026") -> #REF! | Q9: =COUNTIFS('Base de Datos'!$F:$F, $C9, 'Base de Datos'!$H:$H, $E9, 'Base de Datos'!$U:$U, $F9, 'Base de Datos'!$AA:$AA, "Finalizada", 'Base de Datos'!#REF!, ">=01/02/2026", 'Base de Datos'!#REF!, "<=28/02/2026") -> #REF! | R9: =COUNTIFS('Base de Datos'!$F:$F, $C9, 'Base de Datos'!$H:$H, $E9, 'Base de Datos'!$U:$U, $F9, 'Base de Datos'!$AA:$AA, "Finalizada", 'Base de Datos'!#REF!, ">=01/03/2026", 'Base de Datos'!#REF!, "<=31/03/2026") -> #REF! | S9: =COUNTIFS('Base de Datos'!$F:$F, $C9, 'Base de Datos'!$H:$H, $E9, 'Base de Datos'!$U:$U, $F9, 'Base de Datos'!$AA:$AA, "Finalizada", 'Base de Datos'!#REF!, ">=01/04/2026", 'Base de Datos'!#REF!, "<=30/04/2026") -> #REF! | T9: =COUNTIFS('Base de Datos'!$F:$F, $C9, 'Base de Datos'!$H:$H, $E9, 'Base de Datos'!$U:$U, $F9, 'Base de Datos'!$AA:$AA, "Finalizada", 'Base de Datos'!#REF!, ">=01/05/2026", 'Base de Datos'!#REF!, "<=31/05/2026") -> #REF! | U9: =COUNTIFS('Base de Datos'!$F:$F, $C9, 'Base de Datos'!$H:$H, $E9, 'Base de Datos'!$U:$U, $F9, 'Base de Datos'!$AA:$AA, "Finalizada", 'Base de Datos'!#REF!, ">=01/06/2026", 'Base de Datos'!#REF!, "<=30/06/2026") -> #REF!
C10: 2025 | D10: 90 | E10: 3.2.1.1.3 | F10: DIRECCIÓNDEGESTIÓNFINANCIERA | G10: =IF(COUNTIFS($C$4:C10, C10, $D$4:D10, D10, $E$4:E10, E10)=1, 1, 0) -> 0 | H10: {=SUMPRODUCT((TRIM(CLEAN('Base de Datos'!$F$2:$F$3000))&""=TRIM(CLEAN(C10))&"")*(TRIM(CLEAN('Base de Datos'!$G$2:$G$3000))&""=TRIM(CLEAN(D10))&"")*(TRIM(CLEAN('Base de Datos'!$H$2:$H$3000))&""=TRIM(CLEAN(E10))&"")*(TRIM(CLEAN('Base de Datos'!$U$2:$U$3000))&""=TRIM(CLEAN(F10))&""))} -> 0 | I10: =COUNTIFS('Base de Datos'!$F:$F,$C10,'Base de Datos'!$G:$G,$D10,'Base de Datos'!$H:$H,$E10,'Base de Datos'!$U:$U,$F10,'Base de Datos'!$AA:$AA,"Abierta") -> 0 | J10: =COUNTIFS('Base de Datos'!$F:$F,$C10,'Base de Datos'!$G:$G,$D10,'Base de Datos'!$H:$H,$E10,'Base de Datos'!$U:$U,$F10,'Base de Datos'!$AA:$AA,"Vencida") -> 0 | K10: =COUNTIFS('Base de Datos'!$F:$F,$C10,'Base de Datos'!$G:$G,$D10,'Base de Datos'!$H:$H,$E10,'Base de Datos'!$U:$U,$F10,'Base de Datos'!$AA:$AA,"Finalizada") -> 0 | L10: =COUNTIFS('Base de Datos'!$F:$F,$C10,'Base de Datos'!$G:$G,$D10,'Base de Datos'!$H:$H,$E10,'Base de Datos'!$U:$U,$F10,'Base de Datos'!$AA:$AA,"Abierta",'Base de Datos'!$AC:$AC,"<=10",'Base de Datos'!$AC:$AC,">0") -> 0 | M10: =COUNTIFS('Base de Datos'!$F:$F,$C10,'Base de Datos'!$G:$G,$D10,'Base de Datos'!$H:$H,$E10,'Base de Datos'!$U:$U,$F10,'Base de Datos'!$AA:$AA,"Abierta",'Base de Datos'!$AC:$AC,"<=20",'Base de Datos'!$AC:$AC,">10") -> 0 | N10: =COUNTIFS('Base de Datos'!$F:$F,$C10,'Base de Datos'!$G:$G,$D10,'Base de Datos'!$H:$H,$E10,'Base de Datos'!$U:$U,$F10,'Base de Datos'!$AA:$AA,"Abierta",'Base de Datos'!$AC:$AC,"<=30",'Base de Datos'!$AC:$AC,">20") -> 0 | O10: =COUNTIFS('Base de Datos'!$F:$F,$C10,'Base de Datos'!$G:$G,$D10,'Base de Datos'!$H:$H,$E10,'Base de Datos'!$U:$U,$F10,'Base de Datos'!$AA:$AA,"Abierta",'Base de Datos'!$AG:$AG,1) -> 0 | P10: =COUNTIFS('Base de Datos'!$F:$F, $C10, 'Base de Datos'!$H:$H, $E10, 'Base de Datos'!$U:$U, $F10, 'Base de Datos'!$AA:$AA, "Finalizada", 'Base de Datos'!#REF!, ">=01/01/2026", 'Base de Datos'!#REF!, "<=31/01/2026") -> #REF! | Q10: =COUNTIFS('Base de Datos'!$F:$F, $C10, 'Base de Datos'!$H:$H, $E10, 'Base de Datos'!$U:$U, $F10, 'Base de Datos'!$AA:$AA, "Finalizada", 'Base de Datos'!#REF!, ">=01/02/2026", 'Base de Datos'!#REF!, "<=28/02/2026") -> #REF! | R10: =COUNTIFS('Base de Datos'!$F:$F, $C10, 'Base de Datos'!$H:$H, $E10, 'Base de Datos'!$U:$U, $F10, 'Base de Datos'!$AA:$AA, "Finalizada", 'Base de Datos'!#REF!, ">=01/03/2026", 'Base de Datos'!#REF!, "<=31/03/2026") -> #REF! | S10: =COUNTIFS('Base de Datos'!$F:$F, $C10, 'Base de Datos'!$H:$H, $E10, 'Base de Datos'!$U:$U, $F10, 'Base de Datos'!$AA:$AA, "Finalizada", 'Base de Datos'!#REF!, ">=01/04/2026", 'Base de Datos'!#REF!, "<=30/04/2026") -> #REF! | T10: =COUNTIFS('Base de Datos'!$F:$F, $C10, 'Base de Datos'!$H:$H, $E10, 'Base de Datos'!$U:$U, $F10, 'Base de Datos'!$AA:$AA, "Finalizada", 'Base de Datos'!#REF!, ">=01/05/2026", 'Base de Datos'!#REF!, "<=31/05/2026") -> #REF! | U10: =COUNTIFS('Base de Datos'!$F:$F, $C10, 'Base de Datos'!$H:$H, $E10, 'Base de Datos'!$U:$U, $F10, 'Base de Datos'!$AA:$AA, "Finalizada", 'Base de Datos'!#REF!, ">=01/06/2026", 'Base de Datos'!#REF!, "<=30/06/2026") -> #REF!
C11: 2025 | D11: 90 | E11: 3.2.1.1.3 | F11: SUBGERENCIAJURÍDICA | G11: =IF(COUNTIFS($C$4:C11, C11, $D$4:D11, D11, $E$4:E11, E11)=1, 1, 0) -> 0 | H11: {=SUMPRODUCT((TRIM(CLEAN('Base de Datos'!$F$2:$F$3000))&""=TRIM(CLEAN(C11))&"")*(TRIM(CLEAN('Base de Datos'!$G$2:$G$3000))&""=TRIM(CLEAN(D11))&"")*(TRIM(CLEAN('Base de Datos'!$H$2:$H$3000))&""=TRIM(CLEAN(E11))&"")*(TRIM(CLEAN('Base de Datos'!$U$2:$U$3000))&""=TRIM(CLEAN(F11))&""))} -> 0 | I11: =COUNTIFS('Base de Datos'!$F:$F,$C11,'Base de Datos'!$G:$G,$D11,'Base de Datos'!$H:$H,$E11,'Base de Datos'!$U:$U,$F11,'Base de Datos'!$AA:$AA,"Abierta") -> 0 | J11: =COUNTIFS('Base de Datos'!$F:$F,$C11,'Base de Datos'!$G:$G,$D11,'Base de Datos'!$H:$H,$E11,'Base de Datos'!$U:$U,$F11,'Base de Datos'!$AA:$AA,"Vencida") -> 0 | K11: =COUNTIFS('Base de Datos'!$F:$F,$C11,'Base de Datos'!$G:$G,$D11,'Base de Datos'!$H:$H,$E11,'Base de Datos'!$U:$U,$F11,'Base de Datos'!$AA:$AA,"Finalizada") -> 0 | L11: =COUNTIFS('Base de Datos'!$F:$F,$C11,'Base de Datos'!$G:$G,$D11,'Base de Datos'!$H:$H,$E11,'Base de Datos'!$U:$U,$F11,'Base de Datos'!$AA:$AA,"Abierta",'Base de Datos'!$AC:$AC,"<=10",'Base de Datos'!$AC:$AC,">0") -> 0 | M11: =COUNTIFS('Base de Datos'!$F:$F,$C11,'Base de Datos'!$G:$G,$D11,'Base de Datos'!$H:$H,$E11,'Base de Datos'!$U:$U,$F11,'Base de Datos'!$AA:$AA,"Abierta",'Base de Datos'!$AC:$AC,"<=20",'Base de Datos'!$AC:$AC,">10") -> 0 | N11: =COUNTIFS('Base de Datos'!$F:$F,$C11,'Base de Datos'!$G:$G,$D11,'Base de Datos'!$H:$H,$E11,'Base de Datos'!$U:$U,$F11,'Base de Datos'!$AA:$AA,"Abierta",'Base de Datos'!$AC:$AC,"<=30",'Base de Datos'!$AC:$AC,">20") -> 0 | O11: =COUNTIFS('Base de Datos'!$F:$F,$C11,'Base de Datos'!$G:$G,$D11,'Base de Datos'!$H:$H,$E11,'Base de Datos'!$U:$U,$F11,'Base de Datos'!$AA:$AA,"Abierta",'Base de Datos'!$AG:$AG,1) -> 0 | P11: =COUNTIFS('Base de Datos'!$F:$F, $C11, 'Base de Datos'!$H:$H, $E11, 'Base de Datos'!$U:$U, $F11, 'Base de Datos'!$AA:$AA, "Finalizada", 'Base de Datos'!#REF!, ">=01/01/2026", 'Base de Datos'!#REF!, "<=31/01/2026") -> #REF! | Q11: =COUNTIFS('Base de Datos'!$F:$F, $C11, 'Base de Datos'!$H:$H, $E11, 'Base de Datos'!$U:$U, $F11, 'Base de Datos'!$AA:$AA, "Finalizada", 'Base de Datos'!#REF!, ">=01/02/2026", 'Base de Datos'!#REF!, "<=28/02/2026") -> #REF! | R11: =COUNTIFS('Base de Datos'!$F:$F, $C11, 'Base de Datos'!$H:$H, $E11, 'Base de Datos'!$U:$U, $F11, 'Base de Datos'!$AA:$AA, "Finalizada", 'Base de Datos'!#REF!, ">=01/03/2026", 'Base de Datos'!#REF!, "<=31/03/2026") -> #REF! | S11: =COUNTIFS('Base de Datos'!$F:$F, $C11, 'Base de Datos'!$H:$H, $E11, 'Base de Datos'!$U:$U, $F11, 'Base de Datos'!$AA:$AA, "Finalizada", 'Base de Datos'!#REF!, ">=01/04/2026", 'Base de Datos'!#REF!, "<=30/04/2026") -> #REF! | T11: =COUNTIFS('Base de Datos'!$F:$F, $C11, 'Base de Datos'!$H:$H, $E11, 'Base de Datos'!$U:$U, $F11, 'Base de Datos'!$AA:$AA, "Finalizada", 'Base de Datos'!#REF!, ">=01/05/2026", 'Base de Datos'!#REF!, "<=31/05/2026") -> #REF! | U11: =COUNTIFS('Base de Datos'!$F:$F, $C11, 'Base de Datos'!$H:$H, $E11, 'Base de Datos'!$U:$U, $F11, 'Base de Datos'!$AA:$AA, "Finalizada", 'Base de Datos'!#REF!, ">=01/06/2026", 'Base de Datos'!#REF!, "<=30/06/2026") -> #REF!
C12: 2025 | D12: 90 | E12: 3.2.1.1.4 | F12: DIRECCIÓNDERECURSOSFÍSICOSYNEGOCIOS | G12: =IF(COUNTIFS($C$4:C12, C12, $D$4:D12, D12, $E$4:E12, E12)=1, 1, 0) -> 1 | H12: {=SUMPRODUCT((TRIM(CLEAN('Base de Datos'!$F$2:$F$3000))&""=TRIM(CLEAN(C12))&"")*(TRIM(CLEAN('Base de Datos'!$G$2:$G$3000))&""=TRIM(CLEAN(D12))&"")*(TRIM(CLEAN('Base de Datos'!$H$2:$H$3000))&""=TRIM(CLEAN(E12))&"")*(TRIM(CLEAN('Base de Datos'!$U$2:$U$3000))&""=TRIM(CLEAN(F12))&""))} -> 0 | I12: =COUNTIFS('Base de Datos'!$F:$F,$C12,'Base de Datos'!$G:$G,$D12,'Base de Datos'!$H:$H,$E12,'Base de Datos'!$U:$U,$F12,'Base de Datos'!$AA:$AA,"Abierta") -> 0 | J12: =COUNTIFS('Base de Datos'!$F:$F,$C12,'Base de Datos'!$G:$G,$D12,'Base de Datos'!$H:$H,$E12,'Base de Datos'!$U:$U,$F12,'Base de Datos'!$AA:$AA,"Vencida") -> 0 | K12: =COUNTIFS('Base de Datos'!$F:$F,$C12,'Base de Datos'!$G:$G,$D12,'Base de Datos'!$H:$H,$E12,'Base de Datos'!$U:$U,$F12,'Base de Datos'!$AA:$AA,"Finalizada") -> 0 | L12: =COUNTIFS('Base de Datos'!$F:$F,$C12,'Base de Datos'!$G:$G,$D12,'Base de Datos'!$H:$H,$E12,'Base de Datos'!$U:$U,$F12,'Base de Datos'!$AA:$AA,"Abierta",'Base de Datos'!$AC:$AC,"<=10",'Base de Datos'!$AC:$AC,">0") -> 0 | M12: =COUNTIFS('Base de Datos'!$F:$F,$C12,'Base de Datos'!$G:$G,$D12,'Base de Datos'!$H:$H,$E12,'Base de Datos'!$U:$U,$F12,'Base de Datos'!$AA:$AA,"Abierta",'Base de Datos'!$AC:$AC,"<=20",'Base de Datos'!$AC:$AC,">10") -> 0 | N12: =COUNTIFS('Base de Datos'!$F:$F,$C12,'Base de Datos'!$G:$G,$D12,'Base de Datos'!$H:$H,$E12,'Base de Datos'!$U:$U,$F12,'Base de Datos'!$AA:$AA,"Abierta",'Base de Datos'!$AC:$AC,"<=30",'Base de Datos'!$AC:$AC,">20") -> 0 | O12: =COUNTIFS('Base de Datos'!$F:$F,$C12,'Base de Datos'!$G:$G,$D12,'Base de Datos'!$H:$H,$E12,'Base de Datos'!$U:$U,$F12,'Base de Datos'!$AA:$AA,"Abierta",'Base de Datos'!$AG:$AG,1) -> 0 | P12: =COUNTIFS('Base de Datos'!$F:$F, $C12, 'Base de Datos'!$H:$H, $E12, 'Base de Datos'!$U:$U, $F12, 'Base de Datos'!$AA:$AA, "Finalizada", 'Base de Datos'!#REF!, ">=01/01/2026", 'Base de Datos'!#REF!, "<=31/01/2026") -> #REF! | Q12: =COUNTIFS('Base de Datos'!$F:$F, $C12, 'Base de Datos'!$H:$H, $E12, 'Base de Datos'!$U:$U, $F12, 'Base de Datos'!$AA:$AA, "Finalizada", 'Base de Datos'!#REF!, ">=01/02/2026", 'Base de Datos'!#REF!, "<=28/02/2026") -> #REF! | R12: =COUNTIFS('Base de Datos'!$F:$F, $C12, 'Base de Datos'!$H:$H, $E12, 'Base de Datos'!$U:$U, $F12, 'Base de Datos'!$AA:$AA, "Finalizada", 'Base de Datos'!#REF!, ">=01/03/2026", 'Base de Datos'!#REF!, "<=31/03/2026") -> #REF! | S12: =COUNTIFS('Base de Datos'!$F:$F, $C12, 'Base de Datos'!$H:$H, $E12, 'Base de Datos'!$U:$U, $F12, 'Base de Datos'!$AA:$AA, "Finalizada", 'Base de Datos'!#REF!, ">=01/04/2026", 'Base de Datos'!#REF!, "<=30/04/2026") -> #REF! | T12: =COUNTIFS('Base de Datos'!$F:$F, $C12, 'Base de Datos'!$H:$H, $E12, 'Base de Datos'!$U:$U, $F12, 'Base de Datos'!$AA:$AA, "Finalizada", 'Base de Datos'!#REF!, ">=01/05/2026", 'Base de Datos'!#REF!, "<=31/05/2026") -> #REF! | U12: =COUNTIFS('Base de Datos'!$F:$F, $C12, 'Base de Datos'!$H:$H, $E12, 'Base de Datos'!$U:$U, $F12, 'Base de Datos'!$AA:$AA, "Finalizada", 'Base de Datos'!#REF!, ">=01/06/2026", 'Base de Datos'!#REF!, "<=30/06/2026") -> #REF!
C13: 2025 | D13: 90 | E13: 3.2.1.1.4 | F13: DIRECCIÓNDEGESTIÓNFINANCIERA | G13: =IF(COUNTIFS($C$4:C13, C13, $D$4:D13, D13, $E$4:E13, E13)=1, 1, 0) -> 0 | H13: {=SUMPRODUCT((TRIM(CLEAN('Base de Datos'!$F$2:$F$3000))&""=TRIM(CLEAN(C13))&"")*(TRIM(CLEAN('Base de Datos'!$G$2:$G$3000))&""=TRIM(CLEAN(D13))&"")*(TRIM(CLEAN('Base de Datos'!$H$2:$H$3000))&""=TRIM(CLEAN(E13))&"")*(TRIM(CLEAN('Base de Datos'!$U$2:$U$3000))&""=TRIM(CLEAN(F13))&""))} -> 0 | I13: =COUNTIFS('Base de Datos'!$F:$F,$C13,'Base de Datos'!$G:$G,$D13,'Base de Datos'!$H:$H,$E13,'Base de Datos'!$U:$U,$F13,'Base de Datos'!$AA:$AA,"Abierta") -> 0 | J13: =COUNTIFS('Base de Datos'!$F:$F,$C13,'Base de Datos'!$G:$G,$D13,'Base de Datos'!$H:$H,$E13,'Base de Datos'!$U:$U,$F13,'Base de Datos'!$AA:$AA,"Vencida") -> 0 | K13: =COUNTIFS('Base de Datos'!$F:$F,$C13,'Base de Datos'!$G:$G,$D13,'Base de Datos'!$H:$H,$E13,'Base de Datos'!$U:$U,$F13,'Base de Datos'!$AA:$AA,"Finalizada") -> 0 | L13: =COUNTIFS('Base de Datos'!$F:$F,$C13,'Base de Datos'!$G:$G,$D13,'Base de Datos'!$H:$H,$E13,'Base de Datos'!$U:$U,$F13,'Base de Datos'!$AA:$AA,"Abierta",'Base de Datos'!$AC:$AC,"<=10",'Base de Datos'!$AC:$AC,">0") -> 0 | M13: =COUNTIFS('Base de Datos'!$F:$F,$C13,'Base de Datos'!$G:$G,$D13,'Base de Datos'!$H:$H,$E13,'Base de Datos'!$U:$U,$F13,'Base de Datos'!$AA:$AA,"Abierta",'Base de Datos'!$AC:$AC,"<=20",'Base de Datos'!$AC:$AC,">10") -> 0 | N13: =COUNTIFS('Base de Datos'!$F:$F,$C13,'Base de Datos'!$G:$G,$D13,'Base de Datos'!$H:$H,$E13,'Base de Datos'!$U:$U,$F13,'Base de Datos'!$AA:$AA,"Abierta",'Base de Datos'!$AC:$AC,"<=30",'Base de Datos'!$AC:$AC,">20") -> 0 | O13: =COUNTIFS('Base de Datos'!$F:$F,$C13,'Base de Datos'!$G:$G,$D13,'Base de Datos'!$H:$H,$E13,'Base de Datos'!$U:$U,$F13,'Base de Datos'!$AA:$AA,"Abierta",'Base de Datos'!$AG:$AG,1) -> 0 | P13: =COUNTIFS('Base de Datos'!$F:$F, $C13, 'Base de Datos'!$H:$H, $E13, 'Base de Datos'!$U:$U, $F13, 'Base de Datos'!$AA:$AA, "Finalizada", 'Base de Datos'!#REF!, ">=01/01/2026", 'Base de Datos'!#REF!, "<=31/01/2026") -> #REF! | Q13: =COUNTIFS('Base de Datos'!$F:$F, $C13, 'Base de Datos'!$H:$H, $E13, 'Base de Datos'!$U:$U, $F13, 'Base de Datos'!$AA:$AA, "Finalizada", 'Base de Datos'!#REF!, ">=01/02/2026", 'Base de Datos'!#REF!, "<=28/02/2026") -> #REF! | R13: =COUNTIFS('Base de Datos'!$F:$F, $C13, 'Base de Datos'!$H:$H, $E13, 'Base de Datos'!$U:$U, $F13, 'Base de Datos'!$AA:$AA, "Finalizada", 'Base de Datos'!#REF!, ">=01/03/2026", 'Base de Datos'!#REF!, "<=31/03/2026") -> #REF! | S13: =COUNTIFS('Base de Datos'!$F:$F, $C13, 'Base de Datos'!$H:$H, $E13, 'Base de Datos'!$U:$U, $F13, 'Base de Datos'!$AA:$AA, "Finalizada", 'Base de Datos'!#REF!, ">=01/04/2026", 'Base de Datos'!#REF!, "<=30/04/2026") -> #REF! | T13: =COUNTIFS('Base de Datos'!$F:$F, $C13, 'Base de Datos'!$H:$H, $E13, 'Base de Datos'!$U:$U, $F13, 'Base de Datos'!$AA:$AA, "Finalizada", 'Base de Datos'!#REF!, ">=01/05/2026", 'Base de Datos'!#REF!, "<=31/05/2026") -> #REF! | U13: =COUNTIFS('Base de Datos'!$F:$F, $C13, 'Base de Datos'!$H:$H, $E13, 'Base de Datos'!$U:$U, $F13, 'Base de Datos'!$AA:$AA, "Finalizada", 'Base de Datos'!#REF!, ">=01/06/2026", 'Base de Datos'!#REF!, "<=30/06/2026") -> #REF!
C14: 2025 | D14: 90 | E14: 3.2.1.5.1 | F14: DIRECCIÓNDEGESTIÓNFINANCIERA | G14: =IF(COUNTIFS($C$4:C14, C14, $D$4:D14, D14, $E$4:E14, E14)=1, 1, 0) -> 1 | H14: {=SUMPRODUCT((TRIM(CLEAN('Base de Datos'!$F$2:$F$3000))&""=TRIM(CLEAN(C14))&"")*(TRIM(CLEAN('Base de Datos'!$G$2:$G$3000))&""=TRIM(CLEAN(D14))&"")*(TRIM(CLEAN('Base de Datos'!$H$2:$H$3000))&""=TRIM(CLEAN(E14))&"")*(TRIM(CLEAN('Base de Datos'!$U$2:$U$3000))&""=TRIM(CLEAN(F14))&""))} -> 0 | I14: =COUNTIFS('Base de Datos'!$F:$F,$C14,'Base de Datos'!$G:$G,$D14,'Base de Datos'!$H:$H,$E14,'Base de Datos'!$U:$U,$F14,'Base de Datos'!$AA:$AA,"Abierta") -> 0 | J14: =COUNTIFS('Base de Datos'!$F:$F,$C14,'Base de Datos'!$G:$G,$D14,'Base de Datos'!$H:$H,$E14,'Base de Datos'!$U:$U,$F14,'Base de Datos'!$AA:$AA,"Vencida") -> 0 | K14: =COUNTIFS('Base de Datos'!$F:$F,$C14,'Base de Datos'!$G:$G,$D14,'Base de Datos'!$H:$H,$E14,'Base de Datos'!$U:$U,$F14,'Base de Datos'!$AA:$AA,"Finalizada") -> 0 | L14: =COUNTIFS('Base de Datos'!$F:$F,$C14,'Base de Datos'!$G:$G,$D14,'Base de Datos'!$H:$H,$E14,'Base de Datos'!$U:$U,$F14,'Base de Datos'!$AA:$AA,"Abierta",'Base de Datos'!$AC:$AC,"<=10",'Base de Datos'!$AC:$AC,">0") -> 0 | M14: =COUNTIFS('Base de Datos'!$F:$F,$C14,'Base de Datos'!$G:$G,$D14,'Base de Datos'!$H:$H,$E14,'Base de Datos'!$U:$U,$F14,'Base de Datos'!$AA:$AA,"Abierta",'Base de Datos'!$AC:$AC,"<=20",'Base de Datos'!$AC:$AC,">10") -> 0 | N14: =COUNTIFS('Base de Datos'!$F:$F,$C14,'Base de Datos'!$G:$G,$D14,'Base de Datos'!$H:$H,$E14,'Base de Datos'!$U:$U,$F14,'Base de Datos'!$AA:$AA,"Abierta",'Base de Datos'!$AC:$AC,"<=30",'Base de Datos'!$AC:$AC,">20") -> 0 | O14: =COUNTIFS('Base de Datos'!$F:$F,$C14,'Base de Datos'!$G:$G,$D14,'Base de Datos'!$H:$H,$E14,'Base de Datos'!$U:$U,$F14,'Base de Datos'!$AA:$AA,"Abierta",'Base de Datos'!$AG:$AG,1) -> 0 | P14: =COUNTIFS('Base de Datos'!$F:$F, $C14, 'Base de Datos'!$H:$H, $E14, 'Base de Datos'!$U:$U, $F14, 'Base de Datos'!$AA:$AA, "Finalizada", 'Base de Datos'!#REF!, ">=01/01/2026", 'Base de Datos'!#REF!, "<=31/01/2026") -> #REF! | Q14: =COUNTIFS('Base de Datos'!$F:$F, $C14, 'Base de Datos'!$H:$H, $E14, 'Base de Datos'!$U:$U, $F14, 'Base de Datos'!$AA:$AA, "Finalizada", 'Base de Datos'!#REF!, ">=01/02/2026", 'Base de Datos'!#REF!, "<=28/02/2026") -> #REF! | R14: =COUNTIFS('Base de Datos'!$F:$F, $C14, 'Base de Datos'!$H:$H, $E14, 'Base de Datos'!$U:$U, $F14, 'Base de Datos'!$AA:$AA, "Finalizada", 'Base de Datos'!#REF!, ">=01/03/2026", 'Base de Datos'!#REF!, "<=31/03/2026") -> #REF! | S14: =COUNTIFS('Base de Datos'!$F:$F, $C14, 'Base de Datos'!$H:$H, $E14, 'Base de Datos'!$U:$U, $F14, 'Base de Datos'!$AA:$AA, "Finalizada", 'Base de Datos'!#REF!, ">=01/04/2026", 'Base de Datos'!#REF!, "<=30/04/2026") -> #REF! | T14: =COUNTIFS('Base de Datos'!$F:$F, $C14, 'Base de Datos'!$H:$H, $E14, 'Base de Datos'!$U:$U, $F14, 'Base de Datos'!$AA:$AA, "Finalizada", 'Base de Datos'!#REF!, ">=01/05/2026", 'Base de Datos'!#REF!, "<=31/05/2026") -> #REF! | U14: =COUNTIFS('Base de Datos'!$F:$F, $C14, 'Base de Datos'!$H:$H, $E14, 'Base de Datos'!$U:$U, $F14, 'Base de Datos'!$AA:$AA, "Finalizada", 'Base de Datos'!#REF!, ">=01/06/2026", 'Base de Datos'!#REF!, "<=30/06/2026") -> #REF!
C15: 2025 | D15: 90 | E15: 3.2.1.5.1 | F15: SUBGERENCIAJURÍDICA | G15: =IF(COUNTIFS($C$4:C15, C15, $D$4:D15, D15, $E$4:E15, E15)=1, 1, 0) -> 0 | H15: {=SUMPRODUCT((TRIM(CLEAN('Base de Datos'!$F$2:$F$3000))&""=TRIM(CLEAN(C15))&"")*(TRIM(CLEAN('Base de Datos'!$G$2:$G$3000))&""=TRIM(CLEAN(D15))&"")*(TRIM(CLEAN('Base de Datos'!$H$2:$H$3000))&""=TRIM(CLEAN(E15))&"")*(TRIM(CLEAN('Base de Datos'!$U$2:$U$3000))&""=TRIM(CLEAN(F15))&""))} -> 0 | I15: =COUNTIFS('Base de Datos'!$F:$F,$C15,'Base de Datos'!$G:$G,$D15,'Base de Datos'!$H:$H,$E15,'Base de Datos'!$U:$U,$F15,'Base de Datos'!$AA:$AA,"Abierta") -> 0 | J15: =COUNTIFS('Base de Datos'!$F:$F,$C15,'Base de Datos'!$G:$G,$D15,'Base de Datos'!$H:$H,$E15,'Base de Datos'!$U:$U,$F15,'Base de Datos'!$AA:$AA,"Vencida") -> 0 | K15: =COUNTIFS('Base de Datos'!$F:$F,$C15,'Base de Datos'!$G:$G,$D15,'Base de Datos'!$H:$H,$E15,'Base de Datos'!$U:$U,$F15,'Base de Datos'!$AA:$AA,"Finalizada") -> 0 | L15: =COUNTIFS('Base de Datos'!$F:$F,$C15,'Base de Datos'!$G:$G,$D15,'Base de Datos'!$H:$H,$E15,'Base de Datos'!$U:$U,$F15,'Base de Datos'!$AA:$AA,"Abierta",'Base de Datos'!$AC:$AC,"<=10",'Base de Datos'!$AC:$AC,">0") -> 0 | M15: =COUNTIFS('Base de Datos'!$F:$F,$C15,'Base de Datos'!$G:$G,$D15,'Base de Datos'!$H:$H,$E15,'Base de Datos'!$U:$U,$F15,'Base de Datos'!$AA:$AA,"Abierta",'Base de Datos'!$AC:$AC,"<=20",'Base de Datos'!$AC:$AC,">10") -> 0 | N15: =COUNTIFS('Base de Datos'!$F:$F,$C15,'Base de Datos'!$G:$G,$D15,'Base de Datos'!$H:$H,$E15,'Base de Datos'!$U:$U,$F15,'Base de Datos'!$AA:$AA,"Abierta",'Base de Datos'!$AC:$AC,"<=30",'Base de Datos'!$AC:$AC,">20") -> 0 | O15: =COUNTIFS('Base de Datos'!$F:$F,$C15,'Base de Datos'!$G:$G,$D15,'Base de Datos'!$H:$H,$E15,'Base de Datos'!$U:$U,$F15,'Base de Datos'!$AA:$AA,"Abierta",'Base de Datos'!$AG:$AG,1) -> 0 | P15: =COUNTIFS('Base de Datos'!$F:$F, $C15, 'Base de Datos'!$H:$H, $E15, 'Base de Datos'!$U:$U, $F15, 'Base de Datos'!$AA:$AA, "Finalizada", 'Base de Datos'!#REF!, ">=01/01/2026", 'Base de Datos'!#REF!, "<=31/01/2026") -> #REF! | Q15: =COUNTIFS('Base de Datos'!$F:$F, $C15, 'Base de Datos'!$H:$H, $E15, 'Base de Datos'!$U:$U, $F15, 'Base de Datos'!$AA:$AA, "Finalizada", 'Base de Datos'!#REF!, ">=01/02/2026", 'Base de Datos'!#REF!, "<=28/02/2026") -> #REF! | R15: =COUNTIFS('Base de Datos'!$F:$F, $C15, 'Base de Datos'!$H:$H, $E15, 'Base de Datos'!$U:$U, $F15, 'Base de Datos'!$AA:$AA, "Finalizada", 'Base de Datos'!#REF!, ">=01/03/2026", 'Base de Datos'!#REF!, "<=31/03/2026") -> #REF! | S15: =COUNTIFS('Base de Datos'!$F:$F, $C15, 'Base de Datos'!$H:$H, $E15, 'Base de Datos'!$U:$U, $F15, 'Base de Datos'!$AA:$AA, "Finalizada", 'Base de Datos'!#REF!, ">=01/04/2026", 'Base de Datos'!#REF!, "<=30/04/2026") -> #REF! | T15: =COUNTIFS('Base de Datos'!$F:$F, $C15, 'Base de Datos'!$H:$H, $E15, 'Base de Datos'!$U:$U, $F15, 'Base de Datos'!$AA:$AA, "Finalizada", 'Base de Datos'!#REF!, ">=01/05/2026", 'Base de Datos'!#REF!, "<=31/05/2026") -> #REF! | U15: =COUNTIFS('Base de Datos'!$F:$F, $C15, 'Base de Datos'!$H:$H, $E15, 'Base de Datos'!$U:$U, $F15, 'Base de Datos'!$AA:$AA, "Finalizada", 'Base de Datos'!#REF!, ">=01/06/2026", 'Base de Datos'!#REF!, "<=30/06/2026") -> #REF!
... C24: 2025 | D24: 90 | E24: 3.4.2.1.1 | F24: DIRECCIÓNDESERVICIOALTRANSPORTADOR/DIRECCIÓNDERECURSOSTECNOLÓGICOS | G24: =IF(COUNTIFS($C$4:C24, C24, $D$4:D24, D24, $E$4:E24, E24)=1, 1, 0) -> 0 | H24: {=SUMPRODUCT((TRIM(CLEAN('Base de Datos'!$F$2:$F$3000))&""=TRIM(CLEAN(C24))&"")*(TRIM(CLEAN('Base de Datos'!$G$2:$G$3000))&""=TRIM(CLEAN(D24))&"")*(TRIM(CLEAN('Base de Datos'!$H$2:$H$3000))&""=TRIM(CLEAN(E24))&"")*(TRIM(CLEAN('Base de Datos'!$U$2:$U$3000))&""=TRIM(CLEAN(F24))&""))} -> 0 | I24: =COUNTIFS('Base de Datos'!$F:$F,$C24,'Base de Datos'!$G:$G,$D24,'Base de Datos'!$H:$H,$E24,'Base de Datos'!$U:$U,$F24,'Base de Datos'!$AA:$AA,"Abierta") -> 0 | J24: =COUNTIFS('Base de Datos'!$F:$F,$C24,'Base de Datos'!$G:$G,$D24,'Base de Datos'!$H:$H,$E24,'Base de Datos'!$U:$U,$F24,'Base de Datos'!$AA:$AA,"Vencida") -> 0 | K24: =COUNTIFS('Base de Datos'!$F:$F,$C24,'Base de Datos'!$G:$G,$D24,'Base de Datos'!$H:$H,$E24,'Base de Datos'!$U:$U,$F24,'Base de Datos'!$AA:$AA,"Finalizada") -> 0 | L24: =COUNTIFS('Base de Datos'!$F:$F,$C24,'Base de Datos'!$G:$G,$D24,'Base de Datos'!$H:$H,$E24,'Base de Datos'!$U:$U,$F24,'Base de Datos'!$AA:$AA,"Abierta",'Base de Datos'!$AC:$AC,"<=10",'Base de Datos'!$AC:$AC,">0") -> 0 | M24: =COUNTIFS('Base de Datos'!$F:$F,$C24,'Base de Datos'!$G:$G,$D24,'Base de Datos'!$H:$H,$E24,'Base de Datos'!$U:$U,$F24,'Base de Datos'!$AA:$AA,"Abierta",'Base de Datos'!$AC:$AC,"<=20",'Base de Datos'!$AC:$AC,">10") -> 0 | N24: =COUNTIFS('Base de Datos'!$F:$F,$C24,'Base de Datos'!$G:$G,$D24,'Base de Datos'!$H:$H,$E24,'Base de Datos'!$U:$U,$F24,'Base de Datos'!$AA:$AA,"Abierta",'Base de Datos'!$AC:$AC,"<=30",'Base de Datos'!$AC:$AC,">20") -> 0 | O24: =COUNTIFS('Base de Datos'!$F:$F,$C24,'Base de Datos'!$G:$G,$D24,'Base de Datos'!$H:$H,$E24,'Base de Datos'!$U:$U,$F24,'Base de Datos'!$AA:$AA,"Abierta",'Base de Datos'!$AG:$AG,1) -> 0 | P24: =COUNTIFS('Base de Datos'!$F:$F, $C24, 'Base de Datos'!$H:$H, $E24, 'Base de Datos'!$U:$U, $F24, 'Base de Datos'!$AA:$AA, "Finalizada", 'Base de Datos'!#REF!, ">=01/01/2026", 'Base de Datos'!#REF!, "<=31/01/2026") -> #REF! | Q24: =COUNTIFS('Base de Datos'!$F:$F, $C24, 'Base de Datos'!$H:$H, $E24, 'Base de Datos'!$U:$U, $F24, 'Base de Datos'!$AA:$AA, "Finalizada", 'Base de Datos'!#REF!, ">=01/02/2026", 'Base de Datos'!#REF!, "<=28/02/2026") -> #REF! | R24: =COUNTIFS('Base de Datos'!$F:$F, $C24, 'Base de Datos'!$H:$H, $E24, 'Base de Datos'!$U:$U, $F24, 'Base de Datos'!$AA:$AA, "Finalizada", 'Base de Datos'!#REF!, ">=01/03/2026", 'Base de Datos'!#REF!, "<=31/03/2026") -> #REF! | S24: =COUNTIFS('Base de Datos'!$F:$F, $C24, 'Base de Datos'!$H:$H, $E24, 'Base de Datos'!$U:$U, $F24, 'Base de Datos'!$AA:$AA, "Finalizada", 'Base de Datos'!#REF!, ">=01/04/2026", 'Base de Datos'!#REF!, "<=30/04/2026") -> #REF! | T24: =COUNTIFS('Base de Datos'!$F:$F, $C24, 'Base de Datos'!$H:$H, $E24, 'Base de Datos'!$U:$U, $F24, 'Base de Datos'!$AA:$AA, "Finalizada", 'Base de Datos'!#REF!, ">=01/05/2026", 'Base de Datos'!#REF!, "<=31/05/2026") -> #REF! | U24: =COUNTIFS('Base de Datos'!$F:$F, $C24, 'Base de Datos'!$H:$H, $E24, 'Base de Datos'!$U:$U, $F24, 'Base de Datos'!$AA:$AA, "Finalizada", 'Base de Datos'!#REF!, ">=01/06/2026", 'Base de Datos'!#REF!, "<=30/06/2026") -> #REF!
C25: 2025 | D25: 90 | E25: 3.4.2.2.1 | F25: SUBGERENCIACORPORATIVA | G25: =IF(COUNTIFS($C$4:C25, C25, $D$4:D25, D25, $E$4:E25, E25)=1, 1, 0) -> 1 | H25: {=SUMPRODUCT((TRIM(CLEAN('Base de Datos'!$F$2:$F$3000))&""=TRIM(CLEAN(C25))&"")*(TRIM(CLEAN('Base de Datos'!$G$2:$G$3000))&""=TRIM(CLEAN(D25))&"")*(TRIM(CLEAN('Base de Datos'!$H$2:$H$3000))&""=TRIM(CLEAN(E25))&"")*(TRIM(CLEAN('Base de Datos'!$U$2:$U$3000))&""=TRIM(CLEAN(F25))&""))} -> 0 | I25: =COUNTIFS('Base de Datos'!$F:$F,$C25,'Base de Datos'!$G:$G,$D25,'Base de Datos'!$H:$H,$E25,'Base de Datos'!$U:$U,$F25,'Base de Datos'!$AA:$AA,"Abierta") -> 0 | J25: =COUNTIFS('Base de Datos'!$F:$F,$C25,'Base de Datos'!$G:$G,$D25,'Base de Datos'!$H:$H,$E25,'Base de Datos'!$U:$U,$F25,'Base de Datos'!$AA:$AA,"Vencida") -> 0 | K25: =COUNTIFS('Base de Datos'!$F:$F,$C25,'Base de Datos'!$G:$G,$D25,'Base de Datos'!$H:$H,$E25,'Base de Datos'!$U:$U,$F25,'Base de Datos'!$AA:$AA,"Finalizada") -> 0 | L25: =COUNTIFS('Base de Datos'!$F:$F,$C25,'Base de Datos'!$G:$G,$D25,'Base de Datos'!$H:$H,$E25,'Base de Datos'!$U:$U,$F25,'Base de Datos'!$AA:$AA,"Abierta",'Base de Datos'!$AC:$AC,"<=10",'Base de Datos'!$AC:$AC,">0") -> 0 | M25: =COUNTIFS('Base de Datos'!$F:$F,$C25,'Base de Datos'!$G:$G,$D25,'Base de Datos'!$H:$H,$E25,'Base de Datos'!$U:$U,$F25,'Base de Datos'!$AA:$AA,"Abierta",'Base de Datos'!$AC:$AC,"<=20",'Base de Datos'!$AC:$AC,">10") -> 0 | N25: =COUNTIFS('Base de Datos'!$F:$F,$C25,'Base de Datos'!$G:$G,$D25,'Base de Datos'!$H:$H,$E25,'Base de Datos'!$U:$U,$F25,'Base de Datos'!$AA:$AA,"Abierta",'Base de Datos'!$AC:$AC,"<=30",'Base de Datos'!$AC:$AC,">20") -> 0 | O25: =COUNTIFS('Base de Datos'!$F:$F,$C25,'Base de Datos'!$G:$G,$D25,'Base de Datos'!$H:$H,$E25,'Base de Datos'!$U:$U,$F25,'Base de Datos'!$AA:$AA,"Abierta",'Base de Datos'!$AG:$AG,1) -> 0 | P25: =COUNTIFS('Base de Datos'!$F:$F, $C25, 'Base de Datos'!$H:$H, $E25, 'Base de Datos'!$U:$U, $F25, 'Base de Datos'!$AA:$AA, "Finalizada", 'Base de Datos'!#REF!, ">=01/01/2026", 'Base de Datos'!#REF!, "<=31/01/2026") -> #REF! | Q25: =COUNTIFS('Base de Datos'!$F:$F, $C25, 'Base de Datos'!$H:$H, $E25, 'Base de Datos'!$U:$U, $F25, 'Base de Datos'!$AA:$AA, "Finalizada", 'Base de Datos'!#REF!, ">=01/02/2026", 'Base de Datos'!#REF!, "<=28/02/2026") -> #REF! | R25: =COUNTIFS('Base de Datos'!$F:$F, $C25, 'Base de Datos'!$H:$H, $E25, 'Base de Datos'!$U:$U, $F25, 'Base de Datos'!$AA:$AA, "Finalizada", 'Base de Datos'!#REF!, ">=01/03/2026", 'Base de Datos'!#REF!, "<=31/03/2026") -> #REF! | S25: =COUNTIFS('Base de Datos'!$F:$F, $C25, 'Base de Datos'!$H:$H, $E25, 'Base de Datos'!$U:$U, $F25, 'Base de Datos'!$AA:$AA, "Finalizada", 'Base de Datos'!#REF!, ">=01/04/2026", 'Base de Datos'!#REF!, "<=30/04/2026") -> #REF! | T25: =COUNTIFS('Base de Datos'!$F:$F, $C25, 'Base de Datos'!$H:$H, $E25, 'Base de Datos'!$U:$U, $F25, 'Base de Datos'!$AA:$AA, "Finalizada", 'Base de Datos'!#REF!, ">=01/05/2026", 'Base de Datos'!#REF!, "<=31/05/2026") -> #REF! | U25: =COUNTIFS('Base de Datos'!$F:$F, $C25, 'Base de Datos'!$H:$H, $E25, 'Base de Datos'!$U:$U, $F25, 'Base de Datos'!$AA:$AA, "Finalizada", 'Base de Datos'!#REF!, ">=01/06/2026", 'Base de Datos'!#REF!, "<=30/06/2026") -> #REF! | X25: =COUNTIFS('[1]Base de datos'!$A:$A, $A27, '[1]Base de datos'!$B:$B, $B27, '[1]Base de datos'!$G:$G, $C27, '[1]Base de datos'!$S:$S, ">=01/06/2026", '[1]Base de datos'!$S:$S, "<=30/06/2026") -> #VALUE!
C26: 2025 | D26: 90 | E26: 3.4.2.3.1 | F26: DIRECCIÓNDEINFRAESTRUCTURA | G26: =IF(COUNTIFS($C$4:C26, C26, $D$4:D26, D26, $E$4:E26, E26)=1, 1, 0) -> 1 | H26: {=SUMPRODUCT((TRIM(CLEAN('Base de Datos'!$F$2:$F$3000))&""=TRIM(CLEAN(C26))&"")*(TRIM(CLEAN('Base de Datos'!$G$2:$G$3000))&""=TRIM(CLEAN(D26))&"")*(TRIM(CLEAN('Base de Datos'!$H$2:$H$3000))&""=TRIM(CLEAN(E26))&"")*(TRIM(CLEAN('Base de Datos'!$U$2:$U$3000))&""=TRIM(CLEAN(F26))&""))} -> 0 | I26: =COUNTIFS('Base de Datos'!$F:$F,$C26,'Base de Datos'!$G:$G,$D26,'Base de Datos'!$H:$H,$E26,'Base de Datos'!$U:$U,$F26,'Base de Datos'!$AA:$AA,"Abierta") -> 0 | J26: =COUNTIFS('Base de Datos'!$F:$F,$C26,'Base de Datos'!$G:$G,$D26,'Base de Datos'!$H:$H,$E26,'Base de Datos'!$U:$U,$F26,'Base de Datos'!$AA:$AA,"Vencida") -> 0 | K26: =COUNTIFS('Base de Datos'!$F:$F,$C26,'Base de Datos'!$G:$G,$D26,'Base de Datos'!$H:$H,$E26,'Base de Datos'!$U:$U,$F26,'Base de Datos'!$AA:$AA,"Finalizada") -> 0 | L26: =COUNTIFS('Base de Datos'!$F:$F,$C26,'Base de Datos'!$G:$G,$D26,'Base de Datos'!$H:$H,$E26,'Base de Datos'!$U:$U,$F26,'Base de Datos'!$AA:$AA,"Abierta",'Base de Datos'!$AC:$AC,"<=10",'Base de Datos'!$AC:$AC,">0") -> 0 | M26: =COUNTIFS('Base de Datos'!$F:$F,$C26,'Base de Datos'!$G:$G,$D26,'Base de Datos'!$H:$H,$E26,'Base de Datos'!$U:$U,$F26,'Base de Datos'!$AA:$AA,"Abierta",'Base de Datos'!$AC:$AC,"<=20",'Base de Datos'!$AC:$AC,">10") -> 0 | N26: =COUNTIFS('Base de Datos'!$F:$F,$C26,'Base de Datos'!$G:$G,$D26,'Base de Datos'!$H:$H,$E26,'Base de Datos'!$U:$U,$F26,'Base de Datos'!$AA:$AA,"Abierta",'Base de Datos'!$AC:$AC,"<=30",'Base de Datos'!$AC:$AC,">20") -> 0 | O26: =COUNTIFS('Base de Datos'!$F:$F,$C26,'Base de Datos'!$G:$G,$D26,'Base de Datos'!$H:$H,$E26,'Base de Datos'!$U:$U,$F26,'Base de Datos'!$AA:$AA,"Abierta",'Base de Datos'!$AG:$AG,1) -> 0 | P26: =COUNTIFS('Base de Datos'!$F:$F, $C26, 'Base de Datos'!$H:$H, $E26, 'Base de Datos'!$U:$U, $F26, 'Base de Datos'!$AA:$AA, "Finalizada", 'Base de Datos'!#REF!, ">=01/01/2026", 'Base de Datos'!#REF!, "<=31/01/2026") -> #REF! | Q26: =COUNTIFS('Base de Datos'!$F:$F, $C26, 'Base de Datos'!$H:$H, $E26, 'Base de Datos'!$U:$U, $F26, 'Base de Datos'!$AA:$AA, "Finalizada", 'Base de Datos'!#REF!, ">=01/02/2026", 'Base de Datos'!#REF!, "<=28/02/2026") -> #REF! | R26: =COUNTIFS('Base de Datos'!$F:$F, $C26, 'Base de Datos'!$H:$H, $E26, 'Base de Datos'!$U:$U, $F26, 'Base de Datos'!$AA:$AA, "Finalizada", 'Base de Datos'!#REF!, ">=01/03/2026", 'Base de Datos'!#REF!, "<=31/03/2026") -> #REF! | S26: =COUNTIFS('Base de Datos'!$F:$F, $C26, 'Base de Datos'!$H:$H, $E26, 'Base de Datos'!$U:$U, $F26, 'Base de Datos'!$AA:$AA, "Finalizada", 'Base de Datos'!#REF!, ">=01/04/2026", 'Base de Datos'!#REF!, "<=30/04/2026") -> #REF! | T26: =COUNTIFS('Base de Datos'!$F:$F, $C26, 'Base de Datos'!$H:$H, $E26, 'Base de Datos'!$U:$U, $F26, 'Base de Datos'!$AA:$AA, "Finalizada", 'Base de Datos'!#REF!, ">=01/05/2026", 'Base de Datos'!#REF!, "<=31/05/2026") -> #REF! | U26: =COUNTIFS('Base de Datos'!$F:$F, $C26, 'Base de Datos'!$H:$H, $E26, 'Base de Datos'!$U:$U, $F26, 'Base de Datos'!$AA:$AA, "Finalizada", 'Base de Datos'!#REF!, ">=01/06/2026", 'Base de Datos'!#REF!, "<=30/06/2026") -> #REF!
C27: 2025 | D27: 90 | E27: 3.4.2.3.2 | F27: SUBGERENCIAJURÍDICA | G27: =IF(COUNTIFS($C$4:C27, C27, $D$4:D27, D27, $E$4:E27, E27)=1, 1, 0) -> 1 | H27: {=SUMPRODUCT((TRIM(CLEAN('Base de Datos'!$F$2:$F$3000))&""=TRIM(CLEAN(C27))&"")*(TRIM(CLEAN('Base de Datos'!$G$2:$G$3000))&""=TRIM(CLEAN(D27))&"")*(TRIM(CLEAN('Base de Datos'!$H$2:$H$3000))&""=TRIM(CLEAN(E27))&"")*(TRIM(CLEAN('Base de Datos'!$U$2:$U$3000))&""=TRIM(CLEAN(F27))&""))} -> 0 | I27: =COUNTIFS('Base de Datos'!$F:$F,$C27,'Base de Datos'!$G:$G,$D27,'Base de Datos'!$H:$H,$E27,'Base de Datos'!$U:$U,$F27,'Base de Datos'!$AA:$AA,"Abierta") -> 0 | J27: =COUNTIFS('Base de Datos'!$F:$F,$C27,'Base de Datos'!$G:$G,$D27,'Base de Datos'!$H:$H,$E27,'Base de Datos'!$U:$U,$F27,'Base de Datos'!$AA:$AA,"Vencida") -> 0 | K27: =COUNTIFS('Base de Datos'!$F:$F,$C27,'Base de Datos'!$G:$G,$D27,'Base de Datos'!$H:$H,$E27,'Base de Datos'!$U:$U,$F27,'Base de Datos'!$AA:$AA,"Finalizada") -> 0 | L27: =COUNTIFS('Base de Datos'!$F:$F,$C27,'Base de Datos'!$G:$G,$D27,'Base de Datos'!$H:$H,$E27,'Base de Datos'!$U:$U,$F27,'Base de Datos'!$AA:$AA,"Abierta",'Base de Datos'!$AC:$AC,"<=10",'Base de Datos'!$AC:$AC,">0") -> 0 | M27: =COUNTIFS('Base de Datos'!$F:$F,$C27,'Base de Datos'!$G:$G,$D27,'Base de Datos'!$H:$H,$E27,'Base de Datos'!$U:$U,$F27,'Base de Datos'!$AA:$AA,"Abierta",'Base de Datos'!$AC:$AC,"<=20",'Base de Datos'!$AC:$AC,">10") -> 0 | N27: =COUNTIFS('Base de Datos'!$F:$F,$C27,'Base de Datos'!$G:$G,$D27,'Base de Datos'!$H:$H,$E27,'Base de Datos'!$U:$U,$F27,'Base de Datos'!$AA:$AA,"Abierta",'Base de Datos'!$AC:$AC,"<=30",'Base de Datos'!$AC:$AC,">20") -> 0 | O27: =COUNTIFS('Base de Datos'!$F:$F,$C27,'Base de Datos'!$G:$G,$D27,'Base de Datos'!$H:$H,$E27,'Base de Datos'!$U:$U,$F27,'Base de Datos'!$AA:$AA,"Abierta",'Base de Datos'!$AG:$AG,1) -> 0 | P27: =COUNTIFS('Base de Datos'!$F:$F, $C27, 'Base de Datos'!$H:$H, $E27, 'Base de Datos'!$U:$U, $F27, 'Base de Datos'!$AA:$AA, "Finalizada", 'Base de Datos'!#REF!, ">=01/01/2026", 'Base de Datos'!#REF!, "<=31/01/2026") -> #REF! | Q27: =COUNTIFS('Base de Datos'!$F:$F, $C27, 'Base de Datos'!$H:$H, $E27, 'Base de Datos'!$U:$U, $F27, 'Base de Datos'!$AA:$AA, "Finalizada", 'Base de Datos'!#REF!, ">=01/02/2026", 'Base de Datos'!#REF!, "<=28/02/2026") -> #REF! | R27: =COUNTIFS('Base de Datos'!$F:$F, $C27, 'Base de Datos'!$H:$H, $E27, 'Base de Datos'!$U:$U, $F27, 'Base de Datos'!$AA:$AA, "Finalizada", 'Base de Datos'!#REF!, ">=01/03/2026", 'Base de Datos'!#REF!, "<=31/03/2026") -> #REF! | S27: =COUNTIFS('Base de Datos'!$F:$F, $C27, 'Base de Datos'!$H:$H, $E27, 'Base de Datos'!$U:$U, $F27, 'Base de Datos'!$AA:$AA, "Finalizada", 'Base de Datos'!#REF!, ">=01/04/2026", 'Base de Datos'!#REF!, "<=30/04/2026") -> #REF! | T27: =COUNTIFS('Base de Datos'!$F:$F, $C27, 'Base de Datos'!$H:$H, $E27, 'Base de Datos'!$U:$U, $F27, 'Base de Datos'!$AA:$AA, "Finalizada", 'Base de Datos'!#REF!, ">=01/05/2026", 'Base de Datos'!#REF!, "<=31/05/2026") -> #REF! | U27: =COUNTIFS('Base de Datos'!$F:$F, $C27, 'Base de Datos'!$H:$H, $E27, 'Base de Datos'!$U:$U, $F27, 'Base de Datos'!$AA:$AA, "Finalizada", 'Base de Datos'!#REF!, ">=01/06/2026", 'Base de Datos'!#REF!, "<=30/06/2026") -> #REF!
C28: 2025 | D28: 90 | E28: 3.4.2.3.3 | F28: DIRECCIÓNDEINFRAESTRUCTURA | G28: =IF(COUNTIFS($C$4:C28, C28, $D$4:D28, D28, $E$4:E28, E28)=1, 1, 0) -> 1 | H28: {=SUMPRODUCT((TRIM(CLEAN('Base de Datos'!$F$2:$F$3000))&""=TRIM(CLEAN(C28))&"")*(TRIM(CLEAN('Base de Datos'!$G$2:$G$3000))&""=TRIM(CLEAN(D28))&"")*(TRIM(CLEAN('Base de Datos'!$H$2:$H$3000))&""=TRIM(CLEAN(E28))&"")*(TRIM(CLEAN('Base de Datos'!$U$2:$U$3000))&""=TRIM(CLEAN(F28))&""))} -> 0 | I28: =COUNTIFS('Base de Datos'!$F:$F,$C28,'Base de Datos'!$G:$G,$D28,'Base de Datos'!$H:$H,$E28,'Base de Datos'!$U:$U,$F28,'Base de Datos'!$AA:$AA,"Abierta") -> 0 | J28: =COUNTIFS('Base de Datos'!$F:$F,$C28,'Base de Datos'!$G:$G,$D28,'Base de Datos'!$H:$H,$E28,'Base de Datos'!$U:$U,$F28,'Base de Datos'!$AA:$AA,"Vencida") -> 0 | K28: =COUNTIFS('Base de Datos'!$F:$F,$C28,'Base de Datos'!$G:$G,$D28,'Base de Datos'!$H:$H,$E28,'Base de Datos'!$U:$U,$F28,'Base de Datos'!$AA:$AA,"Finalizada") -> 0 | L28: =COUNTIFS('Base de Datos'!$F:$F,$C28,'Base de Datos'!$G:$G,$D28,'Base de Datos'!$H:$H,$E28,'Base de Datos'!$U:$U,$F28,'Base de Datos'!$AA:$AA,"Abierta",'Base de Datos'!$AC:$AC,"<=10",'Base de Datos'!$AC:$AC,">0") -> 0 | M28: =COUNTIFS('Base de Datos'!$F:$F,$C28,'Base de Datos'!$G:$G,$D28,'Base de Datos'!$H:$H,$E28,'Base de Datos'!$U:$U,$F28,'Base de Datos'!$AA:$AA,"Abierta",'Base de Datos'!$AC:$AC,"<=20",'Base de Datos'!$AC:$AC,">10") -> 0 | N28: =COUNTIFS('Base de Datos'!$F:$F,$C28,'Base de Datos'!$G:$G,$D28,'Base de Datos'!$H:$H,$E28,'Base de Datos'!$U:$U,$F28,'Base de Datos'!$AA:$AA,"Abierta",'Base de Datos'!$AC:$AC,"<=30",'Base de Datos'!$AC:$AC,">20") -> 0 | O28: =COUNTIFS('Base de Datos'!$F:$F,$C28,'Base de Datos'!$G:$G,$D28,'Base de Datos'!$H:$H,$E28,'Base de Datos'!$U:$U,$F28,'Base de Datos'!$AA:$AA,"Abierta",'Base de Datos'!$AG:$AG,1) -> 0 | P28: =COUNTIFS('Base de Datos'!$F:$F, $C28, 'Base de Datos'!$H:$H, $E28, 'Base de Datos'!$U:$U, $F28, 'Base de Datos'!$AA:$AA, "Finalizada", 'Base de Datos'!#REF!, ">=01/01/2026", 'Base de Datos'!#REF!, "<=31/01/2026") -> #REF! | Q28: =COUNTIFS('Base de Datos'!$F:$F, $C28, 'Base de Datos'!$H:$H, $E28, 'Base de Datos'!$U:$U, $F28, 'Base de Datos'!$AA:$AA, "Finalizada", 'Base de Datos'!#REF!, ">=01/02/2026", 'Base de Datos'!#REF!, "<=28/02/2026") -> #REF! | R28: =COUNTIFS('Base de Datos'!$F:$F, $C28, 'Base de Datos'!$H:$H, $E28, 'Base de Datos'!$U:$U, $F28, 'Base de Datos'!$AA:$AA, "Finalizada", 'Base de Datos'!#REF!, ">=01/03/2026", 'Base de Datos'!#REF!, "<=31/03/2026") -> #REF! | S28: =COUNTIFS('Base de Datos'!$F:$F, $C28, 'Base de Datos'!$H:$H, $E28, 'Base de Datos'!$U:$U, $F28, 'Base de Datos'!$AA:$AA, "Finalizada", 'Base de Datos'!#REF!, ">=01/04/2026", 'Base de Datos'!#REF!, "<=30/04/2026") -> #REF! | T28: =COUNTIFS('Base de Datos'!$F:$F, $C28, 'Base de Datos'!$H:$H, $E28, 'Base de Datos'!$U:$U, $F28, 'Base de Datos'!$AA:$AA, "Finalizada", 'Base de Datos'!#REF!, ">=01/05/2026", 'Base de Datos'!#REF!, "<=31/05/2026") -> #REF! | U28: =COUNTIFS('Base de Datos'!$F:$F, $C28, 'Base de Datos'!$H:$H, $E28, 'Base de Datos'!$U:$U, $F28, 'Base de Datos'!$AA:$AA, "Finalizada", 'Base de Datos'!#REF!, ">=01/06/2026", 'Base de Datos'!#REF!, "<=30/06/2026") -> #REF!
C29: 2025 | D29: 90 | E29: 3.4.2.3.3 | F29: SUBGERENCIAJURÍDICA | G29: =IF(COUNTIFS($C$4:C29, C29, $D$4:D29, D29, $E$4:E29, E29)=1, 1, 0) -> 0 | H29: {=SUMPRODUCT((TRIM(CLEAN('Base de Datos'!$F$2:$F$3000))&""=TRIM(CLEAN(C29))&"")*(TRIM(CLEAN('Base de Datos'!$G$2:$G$3000))&""=TRIM(CLEAN(D29))&"")*(TRIM(CLEAN('Base de Datos'!$H$2:$H$3000))&""=TRIM(CLEAN(E29))&"")*(TRIM(CLEAN('Base de Datos'!$U$2:$U$3000))&""=TRIM(CLEAN(F29))&""))} -> 0 | I29: =COUNTIFS('Base de Datos'!$F:$F,$C29,'Base de Datos'!$G:$G,$D29,'Base de Datos'!$H:$H,$E29,'Base de Datos'!$U:$U,$F29,'Base de Datos'!$AA:$AA,"Abierta") -> 0 | J29: =COUNTIFS('Base de Datos'!$F:$F,$C29,'Base de Datos'!$G:$G,$D29,'Base de Datos'!$H:$H,$E29,'Base de Datos'!$U:$U,$F29,'Base de Datos'!$AA:$AA,"Vencida") -> 0 | K29: =COUNTIFS('Base de Datos'!$F:$F,$C29,'Base de Datos'!$G:$G,$D29,'Base de Datos'!$H:$H,$E29,'Base de Datos'!$U:$U,$F29,'Base de Datos'!$AA:$AA,"Finalizada") -> 0 | L29: =COUNTIFS('Base de Datos'!$F:$F,$C29,'Base de Datos'!$G:$G,$D29,'Base de Datos'!$H:$H,$E29,'Base de Datos'!$U:$U,$F29,'Base de Datos'!$AA:$AA,"Abierta",'Base de Datos'!$AC:$AC,"<=10",'Base de Datos'!$AC:$AC,">0") -> 0 | M29: =COUNTIFS('Base de Datos'!$F:$F,$C29,'Base de Datos'!$G:$G,$D29,'Base de Datos'!$H:$H,$E29,'Base de Datos'!$U:$U,$F29,'Base de Datos'!$AA:$AA,"Abierta",'Base de Datos'!$AC:$AC,"<=20",'Base de Datos'!$AC:$AC,">10") -> 0 | N29: =COUNTIFS('Base de Datos'!$F:$F,$C29,'Base de Datos'!$G:$G,$D29,'Base de Datos'!$H:$H,$E29,'Base de Datos'!$U:$U,$F29,'Base de Datos'!$AA:$AA,"Abierta",'Base de Datos'!$AC:$AC,"<=30",'Base de Datos'!$AC:$AC,">20") -> 0 | O29: =COUNTIFS('Base de Datos'!$F:$F,$C29,'Base de Datos'!$G:$G,$D29,'Base de Datos'!$H:$H,$E29,'Base de Datos'!$U:$U,$F29,'Base de Datos'!$AA:$AA,"Abierta",'Base de Datos'!$AG:$AG,1) -> 0 | P29: =COUNTIFS('Base de Datos'!$F:$F, $C29, 'Base de Datos'!$H:$H, $E29, 'Base de Datos'!$U:$U, $F29, 'Base de Datos'!$AA:$AA, "Finalizada", 'Base de Datos'!#REF!, ">=01/01/2026", 'Base de Datos'!#REF!, "<=31/01/2026") -> #REF! | Q29: =COUNTIFS('Base de Datos'!$F:$F, $C29, 'Base de Datos'!$H:$H, $E29, 'Base de Datos'!$U:$U, $F29, 'Base de Datos'!$AA:$AA, "Finalizada", 'Base de Datos'!#REF!, ">=01/02/2026", 'Base de Datos'!#REF!, "<=28/02/2026") -> #REF! | R29: =COUNTIFS('Base de Datos'!$F:$F, $C29, 'Base de Datos'!$H:$H, $E29, 'Base de Datos'!$U:$U, $F29, 'Base de Datos'!$AA:$AA, "Finalizada", 'Base de Datos'!#REF!, ">=01/03/2026", 'Base de Datos'!#REF!, "<=31/03/2026") -> #REF! | S29: =COUNTIFS('Base de Datos'!$F:$F, $C29, 'Base de Datos'!$H:$H, $E29, 'Base de Datos'!$U:$U, $F29, 'Base de Datos'!$AA:$AA, "Finalizada", 'Base de Datos'!#REF!, ">=01/04/2026", 'Base de Datos'!#REF!, "<=30/04/2026") -> #REF! | T29: =COUNTIFS('Base de Datos'!$F:$F, $C29, 'Base de Datos'!$H:$H, $E29, 'Base de Datos'!$U:$U, $F29, 'Base de Datos'!$AA:$AA, "Finalizada", 'Base de Datos'!#REF!, ">=01/05/2026", 'Base de Datos'!#REF!, "<=31/05/2026") -> #REF! | U29: =COUNTIFS('Base de Datos'!$F:$F, $C29, 'Base de Datos'!$H:$H, $E29, 'Base de Datos'!$U:$U, $F29, 'Base de Datos'!$AA:$AA, "Finalizada", 'Base de Datos'!#REF!, ">=01/06/2026", 'Base de Datos'!#REF!, "<=30/06/2026") -> #REF!
C30: 2025 | D30: 90 | E30: 3.4.2.4.1 | F30: DIRECCIÓNDEGESTIÓNFINANCIERA | G30: =IF(COUNTIFS($C$4:C30, C30, $D$4:D30, D30, $E$4:E30, E30)=1, 1, 0) -> 1 | H30: {=SUMPRODUCT((TRIM(CLEAN('Base de Datos'!$F$2:$F$3000))&""=TRIM(CLEAN(C30))&"")*(TRIM(CLEAN('Base de Datos'!$G$2:$G$3000))&""=TRIM(CLEAN(D30))&"")*(TRIM(CLEAN('Base de Datos'!$H$2:$H$3000))&""=TRIM(CLEAN(E30))&"")*(TRIM(CLEAN('Base de Datos'!$U$2:$U$3000))&""=TRIM(CLEAN(F30))&""))} -> 0 | I30: =COUNTIFS('Base de Datos'!$F:$F,$C30,'Base de Datos'!$G:$G,$D30,'Base de Datos'!$H:$H,$E30,'Base de Datos'!$U:$U,$F30,'Base de Datos'!$AA:$AA,"Abierta") -> 0 | J30: =COUNTIFS('Base de Datos'!$F:$F,$C30,'Base de Datos'!$G:$G,$D30,'Base de Datos'!$H:$H,$E30,'Base de Datos'!$U:$U,$F30,'Base de Datos'!$AA:$AA,"Vencida") -> 0 | K30: =COUNTIFS('Base de Datos'!$F:$F,$C30,'Base de Datos'!$G:$G,$D30,'Base de Datos'!$H:$H,$E30,'Base de Datos'!$U:$U,$F30,'Base de Datos'!$AA:$AA,"Finalizada") -> 0 | L30: =COUNTIFS('Base de Datos'!$F:$F,$C30,'Base de Datos'!$G:$G,$D30,'Base de Datos'!$H:$H,$E30,'Base de Datos'!$U:$U,$F30,'Base de Datos'!$AA:$AA,"Abierta",'Base de Datos'!$AC:$AC,"<=10",'Base de Datos'!$AC:$AC,">0") -> 0 | M30: =COUNTIFS('Base de Datos'!$F:$F,$C30,'Base de Datos'!$G:$G,$D30,'Base de Datos'!$H:$H,$E30,'Base de Datos'!$U:$U,$F30,'Base de Datos'!$AA:$AA,"Abierta",'Base de Datos'!$AC:$AC,"<=20",'Base de Datos'!$AC:$AC,">10") -> 0 | N30: =COUNTIFS('Base de Datos'!$F:$F,$C30,'Base de Datos'!$G:$G,$D30,'Base de Datos'!$H:$H,$E30,'Base de Datos'!$U:$U,$F30,'Base de Datos'!$AA:$AA,"Abierta",'Base de Datos'!$AC:$AC,"<=30",'Base de Datos'!$AC:$AC,">20") -> 0 | O30: =COUNTIFS('Base de Datos'!$F:$F,$C30,'Base de Datos'!$G:$G,$D30,'Base de Datos'!$H:$H,$E30,'Base de Datos'!$U:$U,$F30,'Base de Datos'!$AA:$AA,"Abierta",'Base de Datos'!$AG:$AG,1) -> 0 | P30: =COUNTIFS('Base de Datos'!$F:$F, $C30, 'Base de Datos'!$H:$H, $E30, 'Base de Datos'!$U:$U, $F30, 'Base de Datos'!$AA:$AA, "Finalizada", 'Base de Datos'!#REF!, ">=01/01/2026", 'Base de Datos'!#REF!, "<=31/01/2026") -> #REF! | Q30: =COUNTIFS('Base de Datos'!$F:$F, $C30, 'Base de Datos'!$H:$H, $E30, 'Base de Datos'!$U:$U, $F30, 'Base de Datos'!$AA:$AA, "Finalizada", 'Base de Datos'!#REF!, ">=01/02/2026", 'Base de Datos'!#REF!, "<=28/02/2026") -> #REF! | R30: =COUNTIFS('Base de Datos'!$F:$F, $C30, 'Base de Datos'!$H:$H, $E30, 'Base de Datos'!$U:$U, $F30, 'Base de Datos'!$AA:$AA, "Finalizada", 'Base de Datos'!#REF!, ">=01/03/2026", 'Base de Datos'!#REF!, "<=31/03/2026") -> #REF! | S30: =COUNTIFS('Base de Datos'!$F:$F, $C30, 'Base de Datos'!$H:$H, $E30, 'Base de Datos'!$U:$U, $F30, 'Base de Datos'!$AA:$AA, "Finalizada", 'Base de Datos'!#REF!, ">=01/04/2026", 'Base de Datos'!#REF!, "<=30/04/2026") -> #REF! | T30: =COUNTIFS('Base de Datos'!$F:$F, $C30, 'Base de Datos'!$H:$H, $E30, 'Base de Datos'!$U:$U, $F30, 'Base de Datos'!$AA:$AA, "Finalizada", 'Base de Datos'!#REF!, ">=01/05/2026", 'Base de Datos'!#REF!, "<=31/05/2026") -> #REF! | U30: =COUNTIFS('Base de Datos'!$F:$F, $C30, 'Base de Datos'!$H:$H, $E30, 'Base de Datos'!$U:$U, $F30, 'Base de Datos'!$AA:$AA, "Finalizada", 'Base de Datos'!#REF!, ">=01/06/2026", 'Base de Datos'!#REF!, "<=30/06/2026") -> #REF!
C31: 2025 | D31: 90 | E31: 3.4.2.4.1 | F31: DIRECCIÓNDEGESTIÓNHUMANA | G31: =IF(COUNTIFS($C$4:C31, C31, $D$4:D31, D31, $E$4:E31, E31)=1, 1, 0) -> 0 | H31: {=SUMPRODUCT((TRIM(CLEAN('Base de Datos'!$F$2:$F$3000))&""=TRIM(CLEAN(C31))&"")*(TRIM(CLEAN('Base de Datos'!$G$2:$G$3000))&""=TRIM(CLEAN(D31))&"")*(TRIM(CLEAN('Base de Datos'!$H$2:$H$3000))&""=TRIM(CLEAN(E31))&"")*(TRIM(CLEAN('Base de Datos'!$U$2:$U$3000))&""=TRIM(CLEAN(F31))&""))} -> 0 | I31: =COUNTIFS('Base de Datos'!$F:$F,$C31,'Base de Datos'!$G:$G,$D31,'Base de Datos'!$H:$H,$E31,'Base de Datos'!$U:$U,$F31,'Base de Datos'!$AA:$AA,"Abierta") -> 0 | J31: =COUNTIFS('Base de Datos'!$F:$F,$C31,'Base de Datos'!$G:$G,$D31,'Base de Datos'!$H:$H,$E31,'Base de Datos'!$U:$U,$F31,'Base de Datos'!$AA:$AA,"Vencida") -> 0 | K31: =COUNTIFS('Base de Datos'!$F:$F,$C31,'Base de Datos'!$G:$G,$D31,'Base de Datos'!$H:$H,$E31,'Base de Datos'!$U:$U,$F31,'Base de Datos'!$AA:$AA,"Finalizada") -> 0 | L31: =COUNTIFS('Base de Datos'!$F:$F,$C31,'Base de Datos'!$G:$G,$D31,'Base de Datos'!$H:$H,$E31,'Base de Datos'!$U:$U,$F31,'Base de Datos'!$AA:$AA,"Abierta",'Base de Datos'!$AC:$AC,"<=10",'Base de Datos'!$AC:$AC,">0") -> 0 | M31: =COUNTIFS('Base de Datos'!$F:$F,$C31,'Base de Datos'!$G:$G,$D31,'Base de Datos'!$H:$H,$E31,'Base de Datos'!$U:$U,$F31,'Base de Datos'!$AA:$AA,"Abierta",'Base de Datos'!$AC:$AC,"<=20",'Base de Datos'!$AC:$AC,">10") -> 0 | N31: =COUNTIFS('Base de Datos'!$F:$F,$C31,'Base de Datos'!$G:$G,$D31,'Base de Datos'!$H:$H,$E31,'Base de Datos'!$U:$U,$F31,'Base de Datos'!$AA:$AA,"Abierta",'Base de Datos'!$AC:$AC,"<=30",'Base de Datos'!$AC:$AC,">20") -> 0 | O31: =COUNTIFS('Base de Datos'!$F:$F,$C31,'Base de Datos'!$G:$G,$D31,'Base de Datos'!$H:$H,$E31,'Base de Datos'!$U:$U,$F31,'Base de Datos'!$AA:$AA,"Abierta",'Base de Datos'!$AG:$AG,1) -> 0 | P31: =COUNTIFS('Base de Datos'!$F:$F, $C31, 'Base de Datos'!$H:$H, $E31, 'Base de Datos'!$U:$U, $F31, 'Base de Datos'!$AA:$AA, "Finalizada", 'Base de Datos'!#REF!, ">=01/01/2026", 'Base de Datos'!#REF!, "<=31/01/2026") -> #REF! | Q31: =COUNTIFS('Base de Datos'!$F:$F, $C31, 'Base de Datos'!$H:$H, $E31, 'Base de Datos'!$U:$U, $F31, 'Base de Datos'!$AA:$AA, "Finalizada", 'Base de Datos'!#REF!, ">=01/02/2026", 'Base de Datos'!#REF!, "<=28/02/2026") -> #REF! | R31: =COUNTIFS('Base de Datos'!$F:$F, $C31, 'Base de Datos'!$H:$H, $E31, 'Base de Datos'!$U:$U, $F31, 'Base de Datos'!$AA:$AA, "Finalizada", 'Base de Datos'!#REF!, ">=01/03/2026", 'Base de Datos'!#REF!, "<=31/03/2026") -> #REF! | S31: =COUNTIFS('Base de Datos'!$F:$F, $C31, 'Base de Datos'!$H:$H, $E31, 'Base de Datos'!$U:$U, $F31, 'Base de Datos'!$AA:$AA, "Finalizada", 'Base de Datos'!#REF!, ">=01/04/2026", 'Base de Datos'!#REF!, "<=30/04/2026") -> #REF! | T31: =COUNTIFS('Base de Datos'!$F:$F, $C31, 'Base de Datos'!$H:$H, $E31, 'Base de Datos'!$U:$U, $F31, 'Base de Datos'!$AA:$AA, "Finalizada", 'Base de Datos'!#REF!, ">=01/05/2026", 'Base de Datos'!#REF!, "<=31/05/2026") -> #REF! | U31: =COUNTIFS('Base de Datos'!$F:$F, $C31, 'Base de Datos'!$H:$H, $E31, 'Base de Datos'!$U:$U, $F31, 'Base de Datos'!$AA:$AA, "Finalizada", 'Base de Datos'!#REF!, ">=01/06/2026", 'Base de Datos'!#REF!, "<=30/06/2026") -> #REF!
C32: 2025 | D32: 90 | E32: 4.2.1 | F32: SUBGERENCIADESERVICIOSOPERACIONALESEINFRAESTRUCTURA | G32: =IF(COUNTIFS($C$4:C32, C32, $D$4:D32, D32, $E$4:E32, E32)=1, 1, 0) -> 1 | H32: {=SUMPRODUCT((TRIM(CLEAN('Base de Datos'!$F$2:$F$3000))&""=TRIM(CLEAN(C32))&"")*(TRIM(CLEAN('Base de Datos'!$G$2:$G$3000))&""=TRIM(CLEAN(D32))&"")*(TRIM(CLEAN('Base de Datos'!$H$2:$H$3000))&""=TRIM(CLEAN(E32))&"")*(TRIM(CLEAN('Base de Datos'!$U$2:$U$3000))&""=TRIM(CLEAN(F32))&""))} -> 0 | I32: =COUNTIFS('Base de Datos'!$F:$F,$C32,'Base de Datos'!$G:$G,$D32,'Base de Datos'!$H:$H,$E32,'Base de Datos'!$U:$U,$F32,'Base de Datos'!$AA:$AA,"Abierta") -> 0 | J32: =COUNTIFS('Base de Datos'!$F:$F,$C32,'Base de Datos'!$G:$G,$D32,'Base de Datos'!$H:$H,$E32,'Base de Datos'!$U:$U,$F32,'Base de Datos'!$AA:$AA,"Vencida") -> 0 | K32: =COUNTIFS('Base de Datos'!$F:$F,$C32,'Base de Datos'!$G:$G,$D32,'Base de Datos'!$H:$H,$E32,'Base de Datos'!$U:$U,$F32,'Base de Datos'!$AA:$AA,"Finalizada") -> 0 | L32: =COUNTIFS('Base de Datos'!$F:$F,$C32,'Base de Datos'!$G:$G,$D32,'Base de Datos'!$H:$H,$E32,'Base de Datos'!$U:$U,$F32,'Base de Datos'!$AA:$AA,"Abierta",'Base de Datos'!$AC:$AC,"<=10",'Base de Datos'!$AC:$AC,">0") -> 0 | M32: =COUNTIFS('Base de Datos'!$F:$F,$C32,'Base de Datos'!$G:$G,$D32,'Base de Datos'!$H:$H,$E32,'Base de Datos'!$U:$U,$F32,'Base de Datos'!$AA:$AA,"Abierta",'Base de Datos'!$AC:$AC,"<=20",'Base de Datos'!$AC:$AC,">10") -> 0 | N32: =COUNTIFS('Base de Datos'!$F:$F,$C32,'Base de Datos'!$G:$G,$D32,'Base de Datos'!$H:$H,$E32,'Base de Datos'!$U:$U,$F32,'Base de Datos'!$AA:$AA,"Abierta",'Base de Datos'!$AC:$AC,"<=30",'Base de Datos'!$AC:$AC,">20") -> 0 | O32: =COUNTIFS('Base de Datos'!$F:$F,$C32,'Base de Datos'!$G:$G,$D32,'Base de Datos'!$H:$H,$E32,'Base de Datos'!$U:$U,$F32,'Base de Datos'!$AA:$AA,"Abierta",'Base de Datos'!$AG:$AG,1) -> 0 | P32: =COUNTIFS('Base de Datos'!$F:$F, $C32, 'Base de Datos'!$H:$H, $E32, 'Base de Datos'!$U:$U, $F32, 'Base de Datos'!$AA:$AA, "Finalizada", 'Base de Datos'!#REF!, ">=01/01/2026", 'Base de Datos'!#REF!, "<=31/01/2026") -> #REF! | Q32: =COUNTIFS('Base de Datos'!$F:$F, $C32, 'Base de Datos'!$H:$H, $E32, 'Base de Datos'!$U:$U, $F32, 'Base de Datos'!$AA:$AA, "Finalizada", 'Base de Datos'!#REF!, ">=01/02/2026", 'Base de Datos'!#REF!, "<=28/02/2026") -> #REF! | R32: =COUNTIFS('Base de Datos'!$F:$F, $C32, 'Base de Datos'!$H:$H, $E32, 'Base de Datos'!$U:$U, $F32, 'Base de Datos'!$AA:$AA, "Finalizada", 'Base de Datos'!#REF!, ">=01/03/2026", 'Base de Datos'!#REF!, "<=31/03/2026") -> #REF! | S32: =COUNTIFS('Base de Datos'!$F:$F, $C32, 'Base de Datos'!$H:$H, $E32, 'Base de Datos'!$U:$U, $F32, 'Base de Datos'!$AA:$AA, "Finalizada", 'Base de Datos'!#REF!, ">=01/04/2026", 'Base de Datos'!#REF!, "<=30/04/2026") -> #REF! | T32: =COUNTIFS('Base de Datos'!$F:$F, $C32, 'Base de Datos'!$H:$H, $E32, 'Base de Datos'!$U:$U, $F32, 'Base de Datos'!$AA:$AA, "Finalizada", 'Base de Datos'!#REF!, ">=01/05/2026", 'Base de Datos'!#REF!, "<=31/05/2026") -> #REF! | U32: =COUNTIFS('Base de Datos'!$F:$F, $C32, 'Base de Datos'!$H:$H, $E32, 'Base de Datos'!$U:$U, $F32, 'Base de Datos'!$AA:$AA, "Finalizada", 'Base de Datos'!#REF!, ">=01/06/2026", 'Base de Datos'!#REF!, "<=30/06/2026") -> #REF!
C33: 2024 | D33: 90 | E33: 3.2.1.1 | F33: DIRECCIÓNDEGESTIÓNFINANCIERA | G33: =IF(COUNTIFS($C$4:C33, C33, $D$4:D33, D33, $E$4:E33, E33)=1, 1, 0) -> 1 | H33: {=SUMPRODUCT((TRIM(CLEAN('Base de Datos'!$F$2:$F$3000))&""=TRIM(CLEAN(C33))&"")*(TRIM(CLEAN('Base de Datos'!$G$2:$G$3000))&""=TRIM(CLEAN(D33))&"")*(TRIM(CLEAN('Base de Datos'!$H$2:$H$3000))&""=TRIM(CLEAN(E33))&"")*(TRIM(CLEAN('Base de Datos'!$U$2:$U$3000))&""=TRIM(CLEAN(F33))&""))} -> 0 | I33: =COUNTIFS('Base de Datos'!$F:$F,$C33,'Base de Datos'!$G:$G,$D33,'Base de Datos'!$H:$H,$E33,'Base de Datos'!$U:$U,$F33,'Base de Datos'!$AA:$AA,"Abierta") -> 0 | J33: =COUNTIFS('Base de Datos'!$F:$F,$C33,'Base de Datos'!$G:$G,$D33,'Base de Datos'!$H:$H,$E33,'Base de Datos'!$U:$U,$F33,'Base de Datos'!$AA:$AA,"Vencida") -> 0 | K33: =COUNTIFS('Base de Datos'!$F:$F,$C33,'Base de Datos'!$G:$G,$D33,'Base de Datos'!$H:$H,$E33,'Base de Datos'!$U:$U,$F33,'Base de Datos'!$AA:$AA,"Finalizada") -> 0 | L33: =COUNTIFS('Base de Datos'!$F:$F,$C33,'Base de Datos'!$G:$G,$D33,'Base de Datos'!$H:$H,$E33,'Base de Datos'!$U:$U,$F33,'Base de Datos'!$AA:$AA,"Abierta",'Base de Datos'!$AC:$AC,"<=10",'Base de Datos'!$AC:$AC,">0") -> 0 | M33: =COUNTIFS('Base de Datos'!$F:$F,$C33,'Base de Datos'!$G:$G,$D33,'Base de Datos'!$H:$H,$E33,'Base de Datos'!$U:$U,$F33,'Base de Datos'!$AA:$AA,"Abierta",'Base de Datos'!$AC:$AC,"<=20",'Base de Datos'!$AC:$AC,">10") -> 0 | N33: =COUNTIFS('Base de Datos'!$F:$F,$C33,'Base de Datos'!$G:$G,$D33,'Base de Datos'!$H:$H,$E33,'Base de Datos'!$U:$U,$F33,'Base de Datos'!$AA:$AA,"Abierta",'Base de Datos'!$AC:$AC,"<=30",'Base de Datos'!$AC:$AC,">20") -> 0 | O33: =COUNTIFS('Base de Datos'!$F:$F,$C33,'Base de Datos'!$G:$G,$D33,'Base de Datos'!$H:$H,$E33,'Base de Datos'!$U:$U,$F33,'Base de Datos'!$AA:$AA,"Abierta",'Base de Datos'!$AG:$AG,1) -> 0 | P33: =COUNTIFS('Base de Datos'!$F:$F, $C33, 'Base de Datos'!$H:$H, $E33, 'Base de Datos'!$U:$U, $F33, 'Base de Datos'!$AA:$AA, "Finalizada", 'Base de Datos'!#REF!, ">=01/01/2026", 'Base de Datos'!#REF!, "<=31/01/2026") -> #REF! | Q33: =COUNTIFS('Base de Datos'!$F:$F, $C33, 'Base de Datos'!$H:$H, $E33, 'Base de Datos'!$U:$U, $F33, 'Base de Datos'!$AA:$AA, "Finalizada", 'Base de Datos'!#REF!, ">=01/02/2026", 'Base de Datos'!#REF!, "<=28/02/2026") -> #REF! | R33: =COUNTIFS('Base de Datos'!$F:$F, $C33, 'Base de Datos'!$H:$H, $E33, 'Base de Datos'!$U:$U, $F33, 'Base de Datos'!$AA:$AA, "Finalizada", 'Base de Datos'!#REF!, ">=01/03/2026", 'Base de Datos'!#REF!, "<=31/03/2026") -> #REF! | S33: =COUNTIFS('Base de Datos'!$F:$F, $C33, 'Base de Datos'!$H:$H, $E33, 'Base de Datos'!$U:$U, $F33, 'Base de Datos'!$AA:$AA, "Finalizada", 'Base de Datos'!#REF!, ">=01/04/2026", 'Base de Datos'!#REF!, "<=30/04/2026") -> #REF! | T33: =COUNTIFS('Base de Datos'!$F:$F, $C33, 'Base de Datos'!$H:$H, $E33, 'Base de Datos'!$U:$U, $F33, 'Base de Datos'!$AA:$AA, "Finalizada", 'Base de Datos'!#REF!, ">=01/05/2026", 'Base de Datos'!#REF!, "<=31/05/2026") -> #REF! | U33: =COUNTIFS('Base de Datos'!$F:$F, $C33, 'Base de Datos'!$H:$H, $E33, 'Base de Datos'!$U:$U, $F33, 'Base de Datos'!$AA:$AA, "Finalizada", 'Base de Datos'!#REF!, ">=01/06/2026", 'Base de Datos'!#REF!, "<=30/06/2026") -> #REF!
C34: 2024 | D34: 90 | E34: 3.2.1.1 | F34: DIRECCIÓNDERECURSOSTECNOLÓGICOS DIRECCIÓNDEGESTIÓNFINANCIERA | G34: =IF(COUNTIFS($C$4:C34, C34, $D$4:D34, D34, $E$4:E34, E34)=1, 1, 0) -> 0 | H34: {=SUMPRODUCT((TRIM(CLEAN('Base de Datos'!$F$2:$F$3000))&""=TRIM(CLEAN(C34))&"")*(TRIM(CLEAN('Base de Datos'!$G$2:$G$3000))&""=TRIM(CLEAN(D34))&"")*(TRIM(CLEAN('Base de Datos'!$H$2:$H$3000))&""=TRIM(CLEAN(E34))&"")*(TRIM(CLEAN('Base de Datos'!$U$2:$U$3000))&""=TRIM(CLEAN(F34))&""))} -> 0 | I34: =COUNTIFS('Base de Datos'!$F:$F,$C34,'Base de Datos'!$G:$G,$D34,'Base de Datos'!$H:$H,$E34,'Base de Datos'!$U:$U,$F34,'Base de Datos'!$AA:$AA,"Abierta") -> 0 | J34: =COUNTIFS('Base de Datos'!$F:$F,$C34,'Base de Datos'!$G:$G,$D34,'Base de Datos'!$H:$H,$E34,'Base de Datos'!$U:$U,$F34,'Base de Datos'!$AA:$AA,"Vencida") -> 0 | K34: =COUNTIFS('Base de Datos'!$F:$F,$C34,'Base de Datos'!$G:$G,$D34,'Base de Datos'!$H:$H,$E34,'Base de Datos'!$U:$U,$F34,'Base de Datos'!$AA:$AA,"Finalizada") -> 0 | L34: =COUNTIFS('Base de Datos'!$F:$F,$C34,'Base de Datos'!$G:$G,$D34,'Base de Datos'!$H:$H,$E34,'Base de Datos'!$U:$U,$F34,'Base de Datos'!$AA:$AA,"Abierta",'Base de Datos'!$AC:$AC,"<=10",'Base de Datos'!$AC:$AC,">0") -> 0 | M34: =COUNTIFS('Base de Datos'!$F:$F,$C34,'Base de Datos'!$G:$G,$D34,'Base de Datos'!$H:$H,$E34,'Base de Datos'!$U:$U,$F34,'Base de Datos'!$AA:$AA,"Abierta",'Base de Datos'!$AC:$AC,"<=20",'Base de Datos'!$AC:$AC,">10") -> 0 | N34: =COUNTIFS('Base de Datos'!$F:$F,$C34,'Base de Datos'!$G:$G,$D34,'Base de Datos'!$H:$H,$E34,'Base de Datos'!$U:$U,$F34,'Base de Datos'!$AA:$AA,"Abierta",'Base de Datos'!$AC:$AC,"<=30",'Base de Datos'!$AC:$AC,">20") -> 0 | O34: =COUNTIFS('Base de Datos'!$F:$F,$C34,'Base de Datos'!$G:$G,$D34,'Base de Datos'!$H:$H,$E34,'Base de Datos'!$U:$U,$F34,'Base de Datos'!$AA:$AA,"Abierta",'Base de Datos'!$AG:$AG,1) -> 0 | P34: =COUNTIFS('Base de Datos'!$F:$F, $C34, 'Base de Datos'!$H:$H, $E34, 'Base de Datos'!$U:$U, $F34, 'Base de Datos'!$AA:$AA, "Finalizada", 'Base de Datos'!#REF!, ">=01/01/2026", 'Base de Datos'!#REF!, "<=31/01/2026") -> #REF! | Q34: =COUNTIFS('Base de Datos'!$F:$F, $C34, 'Base de Datos'!$H:$H, $E34, 'Base de Datos'!$U:$U, $F34, 'Base de Datos'!$AA:$AA, "Finalizada", 'Base de Datos'!#REF!, ">=01/02/2026", 'Base de Datos'!#REF!, "<=28/02/2026") -> #REF! | R34: =COUNTIFS('Base de Datos'!$F:$F, $C34, 'Base de Datos'!$H:$H, $E34, 'Base de Datos'!$U:$U, $F34, 'Base de Datos'!$AA:$AA, "Finalizada", 'Base de Datos'!#REF!, ">=01/03/2026", 'Base de Datos'!#REF!, "<=31/03/2026") -> #REF! | S34: =COUNTIFS('Base de Datos'!$F:$F, $C34, 'Base de Datos'!$H:$H, $E34, 'Base de Datos'!$U:$U, $F34, 'Base de Datos'!$AA:$AA, "Finalizada", 'Base de Datos'!#REF!, ">=01/04/2026", 'Base de Datos'!#REF!, "<=30/04/2026") -> #REF! | T34: =COUNTIFS('Base de Datos'!$F:$F, $C34, 'Base de Datos'!$H:$H, $E34, 'Base de Datos'!$U:$U, $F34, 'Base de Datos'!$AA:$AA, "Finalizada", 'Base de Datos'!#REF!, ">=01/05/2026", 'Base de Datos'!#REF!, "<=31/05/2026") -> #REF! | U34: =COUNTIFS('Base de Datos'!$F:$F, $C34, 'Base de Datos'!$H:$H, $E34, 'Base de Datos'!$U:$U, $F34, 'Base de Datos'!$AA:$AA, "Finalizada", 'Base de Datos'!#REF!, ">=01/06/2026", 'Base de Datos'!#REF!, "<=30/06/2026") -> #REF!
C35: 2024 | D35: 90 | E35: 3.2.1.1 | F35: SUBGERENCIACORPORATIVA | G35: =IF(COUNTIFS($C$4:C35, C35, $D$4:D35, D35, $E$4:E35, E35)=1, 1, 0) -> 0 | H35: {=SUMPRODUCT((TRIM(CLEAN('Base de Datos'!$F$2:$F$3000))&""=TRIM(CLEAN(C35))&"")*(TRIM(CLEAN('Base de Datos'!$G$2:$G$3000))&""=TRIM(CLEAN(D35))&"")*(TRIM(CLEAN('Base de Datos'!$H$2:$H$3000))&""=TRIM(CLEAN(E35))&"")*(TRIM(CLEAN('Base de Datos'!$U$2:$U$3000))&""=TRIM(CLEAN(F35))&""))} -> 0 | I35: =COUNTIFS('Base de Datos'!$F:$F,$C35,'Base de Datos'!$G:$G,$D35,'Base de Datos'!$H:$H,$E35,'Base de Datos'!$U:$U,$F35,'Base de Datos'!$AA:$AA,"Abierta") -> 0 | J35: =COUNTIFS('Base de Datos'!$F:$F,$C35,'Base de Datos'!$G:$G,$D35,'Base de Datos'!$H:$H,$E35,'Base de Datos'!$U:$U,$F35,'Base de Datos'!$AA:$AA,"Vencida") -> 0 | K35: =COUNTIFS('Base de Datos'!$F:$F,$C35,'Base de Datos'!$G:$G,$D35,'Base de Datos'!$H:$H,$E35,'Base de Datos'!$U:$U,$F35,'Base de Datos'!$AA:$AA,"Finalizada") -> 0 | L35: =COUNTIFS('Base de Datos'!$F:$F,$C35,'Base de Datos'!$G:$G,$D35,'Base de Datos'!$H:$H,$E35,'Base de Datos'!$U:$U,$F35,'Base de Datos'!$AA:$AA,"Abierta",'Base de Datos'!$AC:$AC,"<=10",'Base de Datos'!$AC:$AC,">0") -> 0 | M35: =COUNTIFS('Base de Datos'!$F:$F,$C35,'Base de Datos'!$G:$G,$D35,'Base de Datos'!$H:$H,$E35,'Base de Datos'!$U:$U,$F35,'Base de Datos'!$AA:$AA,"Abierta",'Base de Datos'!$AC:$AC,"<=20",'Base de Datos'!$AC:$AC,">10") -> 0 | N35: =COUNTIFS('Base de Datos'!$F:$F,$C35,'Base de Datos'!$G:$G,$D35,'Base de Datos'!$H:$H,$E35,'Base de Datos'!$U:$U,$F35,'Base de Datos'!$AA:$AA,"Abierta",'Base de Datos'!$AC:$AC,"<=30",'Base de Datos'!$AC:$AC,">20") -> 0 | O35: =COUNTIFS('Base de Datos'!$F:$F,$C35,'Base de Datos'!$G:$G,$D35,'Base de Datos'!$H:$H,$E35,'Base de Datos'!$U:$U,$F35,'Base de Datos'!$AA:$AA,"Abierta",'Base de Datos'!$AG:$AG,1) -> 0 | P35: =COUNTIFS('Base de Datos'!$F:$F, $C35, 'Base de Datos'!$H:$H, $E35, 'Base de Datos'!$U:$U, $F35, 'Base de Datos'!$AA:$AA, "Finalizada", 'Base de Datos'!#REF!, ">=01/01/2026", 'Base de Datos'!#REF!, "<=31/01/2026") -> #REF! | Q35: =COUNTIFS('Base de Datos'!$F:$F, $C35, 'Base de Datos'!$H:$H, $E35, 'Base de Datos'!$U:$U, $F35, 'Base de Datos'!$AA:$AA, "Finalizada", 'Base de Datos'!#REF!, ">=01/02/2026", 'Base de Datos'!#REF!, "<=28/02/2026") -> #REF! | R35: =COUNTIFS('Base de Datos'!$F:$F, $C35, 'Base de Datos'!$H:$H, $E35, 'Base de Datos'!$U:$U, $F35, 'Base de Datos'!$AA:$AA, "Finalizada", 'Base de Datos'!#REF!, ">=01/03/2026", 'Base de Datos'!#REF!, "<=31/03/2026") -> #REF! | S35: =COUNTIFS('Base de Datos'!$F:$F, $C35, 'Base de Datos'!$H:$H, $E35, 'Base de Datos'!$U:$U, $F35, 'Base de Datos'!$AA:$AA, "Finalizada", 'Base de Datos'!#REF!, ">=01/04/2026", 'Base de Datos'!#REF!, "<=30/04/2026") -> #REF! | T35: =COUNTIFS('Base de Datos'!$F:$F, $C35, 'Base de Datos'!$H:$H, $E35, 'Base de Datos'!$U:$U, $F35, 'Base de Datos'!$AA:$AA, "Finalizada", 'Base de Datos'!#REF!, ">=01/05/2026", 'Base de Datos'!#REF!, "<=31/05/2026") -> #REF! | U35: =COUNTIFS('Base de Datos'!$F:$F, $C35, 'Base de Datos'!$H:$H, $E35, 'Base de Datos'!$U:$U, $F35, 'Base de Datos'!$AA:$AA, "Finalizada", 'Base de Datos'!#REF!, ">=01/06/2026", 'Base de Datos'!#REF!, "<=30/06/2026") -> #REF!
C36: 2024 | D36: 90 | E36: 3.2.1.2 | F36: SUBGERENCIACORPORATIVA/DIRECCIÓNDERECURSOSTECNOLÓGICOS | G36: =IF(COUNTIFS($C$4:C36, C36, $D$4:D36, D36, $E$4:E36, E36)=1, 1, 0) -> 1 | H36: {=SUMPRODUCT((TRIM(CLEAN('Base de Datos'!$F$2:$F$3000))&""=TRIM(CLEAN(C36))&"")*(TRIM(CLEAN('Base de Datos'!$G$2:$G$3000))&""=TRIM(CLEAN(D36))&"")*(TRIM(CLEAN('Base de Datos'!$H$2:$H$3000))&""=TRIM(CLEAN(E36))&"")*(TRIM(CLEAN('Base de Datos'!$U$2:$U$3000))&""=TRIM(CLEAN(F36))&""))} -> 0 | I36: =COUNTIFS('Base de Datos'!$F:$F,$C36,'Base de Datos'!$G:$G,$D36,'Base de Datos'!$H:$H,$E36,'Base de Datos'!$U:$U,$F36,'Base de Datos'!$AA:$AA,"Abierta") -> 0 | J36: =COUNTIFS('Base de Datos'!$F:$F,$C36,'Base de Datos'!$G:$G,$D36,'Base de Datos'!$H:$H,$E36,'Base de Datos'!$U:$U,$F36,'Base de Datos'!$AA:$AA,"Vencida") -> 0 | K36: =COUNTIFS('Base de Datos'!$F:$F,$C36,'Base de Datos'!$G:$G,$D36,'Base de Datos'!$H:$H,$E36,'Base de Datos'!$U:$U,$F36,'Base de Datos'!$AA:$AA,"Finalizada") -> 0 | L36: =COUNTIFS('Base de Datos'!$F:$F,$C36,'Base de Datos'!$G:$G,$D36,'Base de Datos'!$H:$H,$E36,'Base de Datos'!$U:$U,$F36,'Base de Datos'!$AA:$AA,"Abierta",'Base de Datos'!$AC:$AC,"<=10",'Base de Datos'!$AC:$AC,">0") -> 0 | M36: =COUNTIFS('Base de Datos'!$F:$F,$C36,'Base de Datos'!$G:$G,$D36,'Base de Datos'!$H:$H,$E36,'Base de Datos'!$U:$U,$F36,'Base de Datos'!$AA:$AA,"Abierta",'Base de Datos'!$AC:$AC,"<=20",'Base de Datos'!$AC:$AC,">10") -> 0 | N36: =COUNTIFS('Base de Datos'!$F:$F,$C36,'Base de Datos'!$G:$G,$D36,'Base de Datos'!$H:$H,$E36,'Base de Datos'!$U:$U,$F36,'Base de Datos'!$AA:$AA,"Abierta",'Base de Datos'!$AC:$AC,"<=30",'Base de Datos'!$AC:$AC,">20") -> 0 | O36: =COUNTIFS('Base de Datos'!$F:$F,$C36,'Base de Datos'!$G:$G,$D36,'Base de Datos'!$H:$H,$E36,'Base de Datos'!$U:$U,$F36,'Base de Datos'!$AA:$AA,"Abierta",'Base de Datos'!$AG:$AG,1) -> 0 | P36: =COUNTIFS('Base de Datos'!$F:$F, $C36, 'Base de Datos'!$H:$H, $E36, 'Base de Datos'!$U:$U, $F36, 'Base de Datos'!$AA:$AA, "Finalizada", 'Base de Datos'!#REF!, ">=01/01/2026", 'Base de Datos'!#REF!, "<=31/01/2026") -> #REF! | Q36: =COUNTIFS('Base de Datos'!$F:$F, $C36, 'Base de Datos'!$H:$H, $E36, 'Base de Datos'!$U:$U, $F36, 'Base de Datos'!$AA:$AA, "Finalizada", 'Base de Datos'!#REF!, ">=01/02/2026", 'Base de Datos'!#REF!, "<=28/02/2026") -> #REF! | R36: =COUNTIFS('Base de Datos'!$F:$F, $C36, 'Base de Datos'!$H:$H, $E36, 'Base de Datos'!$U:$U, $F36, 'Base de Datos'!$AA:$AA, "Finalizada", 'Base de Datos'!#REF!, ">=01/03/2026", 'Base de Datos'!#REF!, "<=31/03/2026") -> #REF! | S36: =COUNTIFS('Base de Datos'!$F:$F, $C36, 'Base de Datos'!$H:$H, $E36, 'Base de Datos'!$U:$U, $F36, 'Base de Datos'!$AA:$AA, "Finalizada", 'Base de Datos'!#REF!, ">=01/04/2026", 'Base de Datos'!#REF!, "<=30/04/2026") -> #REF! | T36: =COUNTIFS('Base de Datos'!$F:$F, $C36, 'Base de Datos'!$H:$H, $E36, 'Base de Datos'!$U:$U, $F36, 'Base de Datos'!$AA:$AA, "Finalizada", 'Base de Datos'!#REF!, ">=01/05/2026", 'Base de Datos'!#REF!, "<=31/05/2026") -> #REF! | U36: =COUNTIFS('Base de Datos'!$F:$F, $C36, 'Base de Datos'!$H:$H, $E36, 'Base de Datos'!$U:$U, $F36, 'Base de Datos'!$AA:$AA, "Finalizada", 'Base de Datos'!#REF!, ">=01/06/2026", 'Base de Datos'!#REF!, "<=30/06/2026") -> #REF!
C37: 2024 | D37: 90 | E37: 3.2.1.2 | F37: SUBGERENCIADEPLANEACIÓNYPROYECTOS | G37: =IF(COUNTIFS($C$4:C37, C37, $D$4:D37, D37, $E$4:E37, E37)=1, 1, 0) -> 0 | H37: {=SUMPRODUCT((TRIM(CLEAN('Base de Datos'!$F$2:$F$3000))&""=TRIM(CLEAN(C37))&"")*(TRIM(CLEAN('Base de Datos'!$G$2:$G$3000))&""=TRIM(CLEAN(D37))&"")*(TRIM(CLEAN('Base de Datos'!$H$2:$H$3000))&""=TRIM(CLEAN(E37))&"")*(TRIM(CLEAN('Base de Datos'!$U$2:$U$3000))&""=TRIM(CLEAN(F37))&""))} -> 0 | I37: =COUNTIFS('Base de Datos'!$F:$F,$C37,'Base de Datos'!$G:$G,$D37,'Base de Datos'!$H:$H,$E37,'Base de Datos'!$U:$U,$F37,'Base de Datos'!$AA:$AA,"Abierta") -> 0 | J37: =COUNTIFS('Base de Datos'!$F:$F,$C37,'Base de Datos'!$G:$G,$D37,'Base de Datos'!$H:$H,$E37,'Base de Datos'!$U:$U,$F37,'Base de Datos'!$AA:$AA,"Vencida") -> 0 | K37: =COUNTIFS('Base de Datos'!$F:$F,$C37,'Base de Datos'!$G:$G,$D37,'Base de Datos'!$H:$H,$E37,'Base de Datos'!$U:$U,$F37,'Base de Datos'!$AA:$AA,"Finalizada") -> 0 | L37: =COUNTIFS('Base de Datos'!$F:$F,$C37,'Base de Datos'!$G:$G,$D37,'Base de Datos'!$H:$H,$E37,'Base de Datos'!$U:$U,$F37,'Base de Datos'!$AA:$AA,"Abierta",'Base de Datos'!$AC:$AC,"<=10",'Base de Datos'!$AC:$AC,">0") -> 0 | M37: =COUNTIFS('Base de Datos'!$F:$F,$C37,'Base de Datos'!$G:$G,$D37,'Base de Datos'!$H:$H,$E37,'Base de Datos'!$U:$U,$F37,'Base de Datos'!$AA:$AA,"Abierta",'Base de Datos'!$AC:$AC,"<=20",'Base de Datos'!$AC:$AC,">10") -> 0 | N37: =COUNTIFS('Base de Datos'!$F:$F,$C37,'Base de Datos'!$G:$G,$D37,'Base de Datos'!$H:$H,$E37,'Base de Datos'!$U:$U,$F37,'Base de Datos'!$AA:$AA,"Abierta",'Base de Datos'!$AC:$AC,"<=30",'Base de Datos'!$AC:$AC,">20") -> 0 | O37: =COUNTIFS('Base de Datos'!$F:$F,$C37,'Base de Datos'!$G:$G,$D37,'Base de Datos'!$H:$H,$E37,'Base de Datos'!$U:$U,$F37,'Base de Datos'!$AA:$AA,"Abierta",'Base de Datos'!$AG:$AG,1) -> 0 | P37: =COUNTIFS('Base de Datos'!$F:$F, $C37, 'Base de Datos'!$H:$H, $E37, 'Base de Datos'!$U:$U, $F37, 'Base de Datos'!$AA:$AA, "Finalizada", 'Base de Datos'!#REF!, ">=01/01/2026", 'Base de Datos'!#REF!, "<=31/01/2026") -> #REF! | Q37: =COUNTIFS('Base de Datos'!$F:$F, $C37, 'Base de Datos'!$H:$H, $E37, 'Base de Datos'!$U:$U, $F37, 'Base de Datos'!$AA:$AA, "Finalizada", 'Base de Datos'!#REF!, ">=01/02/2026", 'Base de Datos'!#REF!, "<=28/02/2026") -> #REF! | R37: =COUNTIFS('Base de Datos'!$F:$F, $C37, 'Base de Datos'!$H:$H, $E37, 'Base de Datos'!$U:$U, $F37, 'Base de Datos'!$AA:$AA, "Finalizada", 'Base de Datos'!#REF!, ">=01/03/2026", 'Base de Datos'!#REF!, "<=31/03/2026") -> #REF! | S37: =COUNTIFS('Base de Datos'!$F:$F, $C37, 'Base de Datos'!$H:$H, $E37, 'Base de Datos'!$U:$U, $F37, 'Base de Datos'!$AA:$AA, "Finalizada", 'Base de Datos'!#REF!, ">=01/04/2026", 'Base de Datos'!#REF!, "<=30/04/2026") -> #REF! | T37: =COUNTIFS('Base de Datos'!$F:$F, $C37, 'Base de Datos'!$H:$H, $E37, 'Base de Datos'!$U:$U, $F37, 'Base de Datos'!$AA:$AA, "Finalizada", 'Base de Datos'!#REF!, ">=01/05/2026", 'Base de Datos'!#REF!, "<=31/05/2026") -> #REF! | U37: =COUNTIFS('Base de Datos'!$F:$F, $C37, 'Base de Datos'!$H:$H, $E37, 'Base de Datos'!$U:$U, $F37, 'Base de Datos'!$AA:$AA, "Finalizada", 'Base de Datos'!#REF!, ">=01/06/2026", 'Base de Datos'!#REF!, "<=30/06/2026") -> #REF!
... C57: 2023 | D57: 88 | E57: 3.2.1.1.3 | F57: DIRECCIÓNDEGESTIÓNFINANCIERA | G57: =IF(COUNTIFS($C$4:C57, C57, $D$4:D57, D57, $E$4:E57, E57)=1, 1, 0) -> 1 | H57: {=SUMPRODUCT((TRIM(CLEAN('Base de Datos'!$F$2:$F$3000))&""=TRIM(CLEAN(C57))&"")*(TRIM(CLEAN('Base de Datos'!$G$2:$G$3000))&""=TRIM(CLEAN(D57))&"")*(TRIM(CLEAN('Base de Datos'!$H$2:$H$3000))&""=TRIM(CLEAN(E57))&"")*(TRIM(CLEAN('Base de Datos'!$U$2:$U$3000))&""=TRIM(CLEAN(F57))&""))} -> 0 | I57: =COUNTIFS('Base de Datos'!$F:$F,$C57,'Base de Datos'!$G:$G,$D57,'Base de Datos'!$H:$H,$E57,'Base de Datos'!$U:$U,$F57,'Base de Datos'!$AA:$AA,"Abierta") -> 0 | J57: =COUNTIFS('Base de Datos'!$F:$F,$C57,'Base de Datos'!$G:$G,$D57,'Base de Datos'!$H:$H,$E57,'Base de Datos'!$U:$U,$F57,'Base de Datos'!$AA:$AA,"Vencida") -> 0 | K57: =COUNTIFS('Base de Datos'!$F:$F,$C57,'Base de Datos'!$G:$G,$D57,'Base de Datos'!$H:$H,$E57,'Base de Datos'!$U:$U,$F57,'Base de Datos'!$AA:$AA,"Finalizada") -> 0 | L57: =COUNTIFS('Base de Datos'!$F:$F,$C57,'Base de Datos'!$G:$G,$D57,'Base de Datos'!$H:$H,$E57,'Base de Datos'!$U:$U,$F57,'Base de Datos'!$AA:$AA,"Abierta",'Base de Datos'!$AC:$AC,"<=10",'Base de Datos'!$AC:$AC,">0") -> 0 | M57: =COUNTIFS('Base de Datos'!$F:$F,$C57,'Base de Datos'!$G:$G,$D57,'Base de Datos'!$H:$H,$E57,'Base de Datos'!$U:$U,$F57,'Base de Datos'!$AA:$AA,"Abierta",'Base de Datos'!$AC:$AC,"<=20",'Base de Datos'!$AC:$AC,">10") -> 0 | N57: =COUNTIFS('Base de Datos'!$F:$F,$C57,'Base de Datos'!$G:$G,$D57,'Base de Datos'!$H:$H,$E57,'Base de Datos'!$U:$U,$F57,'Base de Datos'!$AA:$AA,"Abierta",'Base de Datos'!$AC:$AC,"<=30",'Base de Datos'!$AC:$AC,">20") -> 0 | O57: =COUNTIFS('Base de Datos'!$F:$F,$C57,'Base de Datos'!$G:$G,$D57,'Base de Datos'!$H:$H,$E57,'Base de Datos'!$U:$U,$F57,'Base de Datos'!$AA:$AA,"Abierta",'Base de Datos'!$AG:$AG,1) -> 0 | P57: =COUNTIFS('Base de Datos'!$F:$F, $C57, 'Base de Datos'!$H:$H, $E57, 'Base de Datos'!$U:$U, $F57, 'Base de Datos'!$AA:$AA, "Finalizada", 'Base de Datos'!#REF!, ">=01/01/2026", 'Base de Datos'!#REF!, "<=31/01/2026") -> #REF! | Q57: =COUNTIFS('Base de Datos'!$F:$F, $C57, 'Base de Datos'!$H:$H, $E57, 'Base de Datos'!$U:$U, $F57, 'Base de Datos'!$AA:$AA, "Finalizada", 'Base de Datos'!#REF!, ">=01/02/2026", 'Base de Datos'!#REF!, "<=28/02/2026") -> #REF! | R57: =COUNTIFS('Base de Datos'!$F:$F, $C57, 'Base de Datos'!$H:$H, $E57, 'Base de Datos'!$U:$U, $F57, 'Base de Datos'!$AA:$AA, "Finalizada", 'Base de Datos'!#REF!, ">=01/03/2026", 'Base de Datos'!#REF!, "<=31/03/2026") -> #REF! | S57: =COUNTIFS('Base de Datos'!$F:$F, $C57, 'Base de Datos'!$H:$H, $E57, 'Base de Datos'!$U:$U, $F57, 'Base de Datos'!$AA:$AA, "Finalizada", 'Base de Datos'!#REF!, ">=01/04/2026", 'Base de Datos'!#REF!, "<=30/04/2026") -> #REF! | T57: =COUNTIFS('Base de Datos'!$F:$F, $C57, 'Base de Datos'!$H:$H, $E57, 'Base de Datos'!$U:$U, $F57, 'Base de Datos'!$AA:$AA, "Finalizada", 'Base de Datos'!#REF!, ">=01/05/2026", 'Base de Datos'!#REF!, "<=31/05/2026") -> #REF! | U57: =COUNTIFS('Base de Datos'!$F:$F, $C57, 'Base de Datos'!$H:$H, $E57, 'Base de Datos'!$U:$U, $F57, 'Base de Datos'!$AA:$AA, "Finalizada", 'Base de Datos'!#REF!, ">=01/06/2026", 'Base de Datos'!#REF!, "<=30/06/2026") -> #REF!
C58: 2023 | D58: 88 | E58: 3.2.1.1.4 | F58: DIRECCIÓNDEGESTIÓNFINANCIERA | G58: =IF(COUNTIFS($C$4:C75, C58, $D$4:D75, D58, $E$4:E75, E58)=1, 1, 0) -> 1 | H58: {=SUMPRODUCT((TRIM(CLEAN('Base de Datos'!$F$2:$F$3000))&""=TRIM(CLEAN(C58))&"")*(TRIM(CLEAN('Base de Datos'!$G$2:$G$3000))&""=TRIM(CLEAN(D58))&"")*(TRIM(CLEAN('Base de Datos'!$H$2:$H$3000))&""=TRIM(CLEAN(E58))&"")*(TRIM(CLEAN('Base de Datos'!$U$2:$U$3000))&""=TRIM(CLEAN(F58))&""))} -> 0 | I58: =COUNTIFS('Base de Datos'!$F:$F,$C58,'Base de Datos'!$G:$G,$D58,'Base de Datos'!$H:$H,$E58,'Base de Datos'!$U:$U,$F58,'Base de Datos'!$AA:$AA,"Abierta") -> 0 | J58: =COUNTIFS('Base de Datos'!$F:$F,$C58,'Base de Datos'!$G:$G,$D58,'Base de Datos'!$H:$H,$E58,'Base de Datos'!$U:$U,$F58,'Base de Datos'!$AA:$AA,"Vencida") -> 0 | K58: =COUNTIFS('Base de Datos'!$F:$F,$C58,'Base de Datos'!$G:$G,$D58,'Base de Datos'!$H:$H,$E58,'Base de Datos'!$U:$U,$F58,'Base de Datos'!$AA:$AA,"Finalizada") -> 0 | L58: =COUNTIFS('Base de Datos'!$F:$F,$C58,'Base de Datos'!$G:$G,$D58,'Base de Datos'!$H:$H,$E58,'Base de Datos'!$U:$U,$F58,'Base de Datos'!$AA:$AA,"Abierta",'Base de Datos'!$AC:$AC,"<=10",'Base de Datos'!$AC:$AC,">0") -> 0 | M58: =COUNTIFS('Base de Datos'!$F:$F,$C58,'Base de Datos'!$G:$G,$D58,'Base de Datos'!$H:$H,$E58,'Base de Datos'!$U:$U,$F58,'Base de Datos'!$AA:$AA,"Abierta",'Base de Datos'!$AC:$AC,"<=20",'Base de Datos'!$AC:$AC,">10") -> 0 | N58: =COUNTIFS('Base de Datos'!$F:$F,$C58,'Base de Datos'!$G:$G,$D58,'Base de Datos'!$H:$H,$E58,'Base de Datos'!$U:$U,$F58,'Base de Datos'!$AA:$AA,"Abierta",'Base de Datos'!$AC:$AC,"<=30",'Base de Datos'!$AC:$AC,">20") -> 0 | O58: =COUNTIFS('Base de Datos'!$F:$F,$C58,'Base de Datos'!$G:$G,$D58,'Base de Datos'!$H:$H,$E58,'Base de Datos'!$U:$U,$F58,'Base de Datos'!$AA:$AA,"Abierta",'Base de Datos'!$AG:$AG,1) -> 0 | P58: =COUNTIFS('Base de Datos'!$F:$F, $C58, 'Base de Datos'!$H:$H, $E58, 'Base de Datos'!$U:$U, $F58, 'Base de Datos'!$AA:$AA, "Finalizada", 'Base de Datos'!#REF!, ">=01/01/2026", 'Base de Datos'!#REF!, "<=31/01/2026") -> #REF! | Q58: =COUNTIFS('Base de Datos'!$F:$F, $C58, 'Base de Datos'!$H:$H, $E58, 'Base de Datos'!$U:$U, $F58, 'Base de Datos'!$AA:$AA, "Finalizada", 'Base de Datos'!#REF!, ">=01/02/2026", 'Base de Datos'!#REF!, "<=28/02/2026") -> #REF! | R58: =COUNTIFS('Base de Datos'!$F:$F, $C58, 'Base de Datos'!$H:$H, $E58, 'Base de Datos'!$U:$U, $F58, 'Base de Datos'!$AA:$AA, "Finalizada", 'Base de Datos'!#REF!, ">=01/03/2026", 'Base de Datos'!#REF!, "<=31/03/2026") -> #REF! | S58: =COUNTIFS('Base de Datos'!$F:$F, $C58, 'Base de Datos'!$H:$H, $E58, 'Base de Datos'!$U:$U, $F58, 'Base de Datos'!$AA:$AA, "Finalizada", 'Base de Datos'!#REF!, ">=01/04/2026", 'Base de Datos'!#REF!, "<=30/04/2026") -> #REF! | T58: =COUNTIFS('Base de Datos'!$F:$F, $C58, 'Base de Datos'!$H:$H, $E58, 'Base de Datos'!$U:$U, $F58, 'Base de Datos'!$AA:$AA, "Finalizada", 'Base de Datos'!#REF!, ">=01/05/2026", 'Base de Datos'!#REF!, "<=31/05/2026") -> #REF! | U58: =COUNTIFS('Base de Datos'!$F:$F, $C58, 'Base de Datos'!$H:$H, $E58, 'Base de Datos'!$U:$U, $F58, 'Base de Datos'!$AA:$AA, "Finalizada", 'Base de Datos'!#REF!, ">=01/06/2026", 'Base de Datos'!#REF!, "<=30/06/2026") -> #REF!
C59: 2023 | D59: 88 | E59: 3.4.1.1.1 | F59: SUBGERENCIAPLANEACIÓNYPROYECTOS | G59: =IF(COUNTIFS($C$4:C59, C59, $D$4:D59, D59, $E$4:E59, E59)=1, 1, 0) -> 1 | H59: {=SUMPRODUCT((TRIM(CLEAN('Base de Datos'!$F$2:$F$3000))&""=TRIM(CLEAN(C59))&"")*(TRIM(CLEAN('Base de Datos'!$G$2:$G$3000))&""=TRIM(CLEAN(D59))&"")*(TRIM(CLEAN('Base de Datos'!$H$2:$H$3000))&""=TRIM(CLEAN(E59))&"")*(TRIM(CLEAN('Base de Datos'!$U$2:$U$3000))&""=TRIM(CLEAN(F59))&""))} -> 0 | I59: =COUNTIFS('Base de Datos'!$F:$F,$C59,'Base de Datos'!$G:$G,$D59,'Base de Datos'!$H:$H,$E59,'Base de Datos'!$U:$U,$F59,'Base de Datos'!$AA:$AA,"Abierta") -> 0 | J59: =COUNTIFS('Base de Datos'!$F:$F,$C59,'Base de Datos'!$G:$G,$D59,'Base de Datos'!$H:$H,$E59,'Base de Datos'!$U:$U,$F59,'Base de Datos'!$AA:$AA,"Vencida") -> 0 | K59: =COUNTIFS('Base de Datos'!$F:$F,$C59,'Base de Datos'!$G:$G,$D59,'Base de Datos'!$H:$H,$E59,'Base de Datos'!$U:$U,$F59,'Base de Datos'!$AA:$AA,"Finalizada") -> 0 | L59: =COUNTIFS('Base de Datos'!$F:$F,$C59,'Base de Datos'!$G:$G,$D59,'Base de Datos'!$H:$H,$E59,'Base de Datos'!$U:$U,$F59,'Base de Datos'!$AA:$AA,"Abierta",'Base de Datos'!$AC:$AC,"<=10",'Base de Datos'!$AC:$AC,">0") -> 0 | M59: =COUNTIFS('Base de Datos'!$F:$F,$C59,'Base de Datos'!$G:$G,$D59,'Base de Datos'!$H:$H,$E59,'Base de Datos'!$U:$U,$F59,'Base de Datos'!$AA:$AA,"Abierta",'Base de Datos'!$AC:$AC,"<=20",'Base de Datos'!$AC:$AC,">10") -> 0 | N59: =COUNTIFS('Base de Datos'!$F:$F,$C59,'Base de Datos'!$G:$G,$D59,'Base de Datos'!$H:$H,$E59,'Base de Datos'!$U:$U,$F59,'Base de Datos'!$AA:$AA,"Abierta",'Base de Datos'!$AC:$AC,"<=30",'Base de Datos'!$AC:$AC,">20") -> 0 | O59: =COUNTIFS('Base de Datos'!$F:$F,$C59,'Base de Datos'!$G:$G,$D59,'Base de Datos'!$H:$H,$E59,'Base de Datos'!$U:$U,$F59,'Base de Datos'!$AA:$AA,"Abierta",'Base de Datos'!$AG:$AG,1) -> 0 | P59: =COUNTIFS('Base de Datos'!$F:$F, $C59, 'Base de Datos'!$H:$H, $E59, 'Base de Datos'!$U:$U, $F59, 'Base de Datos'!$AA:$AA, "Finalizada", 'Base de Datos'!#REF!, ">=01/01/2026", 'Base de Datos'!#REF!, "<=31/01/2026") -> #REF! | Q59: =COUNTIFS('Base de Datos'!$F:$F, $C59, 'Base de Datos'!$H:$H, $E59, 'Base de Datos'!$U:$U, $F59, 'Base de Datos'!$AA:$AA, "Finalizada", 'Base de Datos'!#REF!, ">=01/02/2026", 'Base de Datos'!#REF!, "<=28/02/2026") -> #REF! | R59: =COUNTIFS('Base de Datos'!$F:$F, $C59, 'Base de Datos'!$H:$H, $E59, 'Base de Datos'!$U:$U, $F59, 'Base de Datos'!$AA:$AA, "Finalizada", 'Base de Datos'!#REF!, ">=01/03/2026", 'Base de Datos'!#REF!, "<=31/03/2026") -> #REF! | S59: =COUNTIFS('Base de Datos'!$F:$F, $C59, 'Base de Datos'!$H:$H, $E59, 'Base de Datos'!$U:$U, $F59, 'Base de Datos'!$AA:$AA, "Finalizada", 'Base de Datos'!#REF!, ">=01/04/2026", 'Base de Datos'!#REF!, "<=30/04/2026") -> #REF! | T59: =COUNTIFS('Base de Datos'!$F:$F, $C59, 'Base de Datos'!$H:$H, $E59, 'Base de Datos'!$U:$U, $F59, 'Base de Datos'!$AA:$AA, "Finalizada", 'Base de Datos'!#REF!, ">=01/05/2026", 'Base de Datos'!#REF!, "<=31/05/2026") -> #REF! | U59: =COUNTIFS('Base de Datos'!$F:$F, $C59, 'Base de Datos'!$H:$H, $E59, 'Base de Datos'!$U:$U, $F59, 'Base de Datos'!$AA:$AA, "Finalizada", 'Base de Datos'!#REF!, ">=01/06/2026", 'Base de Datos'!#REF!, "<=30/06/2026") -> #REF!
C60: 2023 | D60: 88 | E60: 3.4.2.1.1 | F60: SUBGERENCIAPLANEACIÓNYPROYECTOS(ZPP) | G60: =IF(COUNTIFS($C$4:C60, C60, $D$4:D60, D60, $E$4:E60, E60)=1, 1, 0) -> 1 | H60: {=SUMPRODUCT((TRIM(CLEAN('Base de Datos'!$F$2:$F$3000))&""=TRIM(CLEAN(C60))&"")*(TRIM(CLEAN('Base de Datos'!$G$2:$G$3000))&""=TRIM(CLEAN(D60))&"")*(TRIM(CLEAN('Base de Datos'!$H$2:$H$3000))&""=TRIM(CLEAN(E60))&"")*(TRIM(CLEAN('Base de Datos'!$U$2:$U$3000))&""=TRIM(CLEAN(F60))&""))} -> 0 | I60: =COUNTIFS('Base de Datos'!$F:$F,$C60,'Base de Datos'!$G:$G,$D60,'Base de Datos'!$H:$H,$E60,'Base de Datos'!$U:$U,$F60,'Base de Datos'!$AA:$AA,"Abierta") -> 0 | J60: =COUNTIFS('Base de Datos'!$F:$F,$C60,'Base de Datos'!$G:$G,$D60,'Base de Datos'!$H:$H,$E60,'Base de Datos'!$U:$U,$F60,'Base de Datos'!$AA:$AA,"Vencida") -> 0 | K60: =COUNTIFS('Base de Datos'!$F:$F,$C60,'Base de Datos'!$G:$G,$D60,'Base de Datos'!$H:$H,$E60,'Base de Datos'!$U:$U,$F60,'Base de Datos'!$AA:$AA,"Finalizada") -> 0 | L60: =COUNTIFS('Base de Datos'!$F:$F,$C60,'Base de Datos'!$G:$G,$D60,'Base de Datos'!$H:$H,$E60,'Base de Datos'!$U:$U,$F60,'Base de Datos'!$AA:$AA,"Abierta",'Base de Datos'!$AC:$AC,"<=10",'Base de Datos'!$AC:$AC,">0") -> 0 | M60: =COUNTIFS('Base de Datos'!$F:$F,$C60,'Base de Datos'!$G:$G,$D60,'Base de Datos'!$H:$H,$E60,'Base de Datos'!$U:$U,$F60,'Base de Datos'!$AA:$AA,"Abierta",'Base de Datos'!$AC:$AC,"<=20",'Base de Datos'!$AC:$AC,">10") -> 0 | N60: =COUNTIFS('Base de Datos'!$F:$F,$C60,'Base de Datos'!$G:$G,$D60,'Base de Datos'!$H:$H,$E60,'Base de Datos'!$U:$U,$F60,'Base de Datos'!$AA:$AA,"Abierta",'Base de Datos'!$AC:$AC,"<=30",'Base de Datos'!$AC:$AC,">20") -> 0 | O60: =COUNTIFS('Base de Datos'!$F:$F,$C60,'Base de Datos'!$G:$G,$D60,'Base de Datos'!$H:$H,$E60,'Base de Datos'!$U:$U,$F60,'Base de Datos'!$AA:$AA,"Abierta",'Base de Datos'!$AG:$AG,1) -> 0 | P60: =COUNTIFS('Base de Datos'!$F:$F, $C60, 'Base de Datos'!$H:$H, $E60, 'Base de Datos'!$U:$U, $F60, 'Base de Datos'!$AA:$AA, "Finalizada", 'Base de Datos'!#REF!, ">=01/01/2026", 'Base de Datos'!#REF!, "<=31/01/2026") -> #REF! | Q60: =COUNTIFS('Base de Datos'!$F:$F, $C60, 'Base de Datos'!$H:$H, $E60, 'Base de Datos'!$U:$U, $F60, 'Base de Datos'!$AA:$AA, "Finalizada", 'Base de Datos'!#REF!, ">=01/02/2026", 'Base de Datos'!#REF!, "<=28/02/2026") -> #REF! | R60: =COUNTIFS('Base de Datos'!$F:$F, $C60, 'Base de Datos'!$H:$H, $E60, 'Base de Datos'!$U:$U, $F60, 'Base de Datos'!$AA:$AA, "Finalizada", 'Base de Datos'!#REF!, ">=01/03/2026", 'Base de Datos'!#REF!, "<=31/03/2026") -> #REF! | S60: =COUNTIFS('Base de Datos'!$F:$F, $C60, 'Base de Datos'!$H:$H, $E60, 'Base de Datos'!$U:$U, $F60, 'Base de Datos'!$AA:$AA, "Finalizada", 'Base de Datos'!#REF!, ">=01/04/2026", 'Base de Datos'!#REF!, "<=30/04/2026") -> #REF! | T60: =COUNTIFS('Base de Datos'!$F:$F, $C60, 'Base de Datos'!$H:$H, $E60, 'Base de Datos'!$U:$U, $F60, 'Base de Datos'!$AA:$AA, "Finalizada", 'Base de Datos'!#REF!, ">=01/05/2026", 'Base de Datos'!#REF!, "<=31/05/2026") -> #REF! | U60: =COUNTIFS('Base de Datos'!$F:$F, $C60, 'Base de Datos'!$H:$H, $E60, 'Base de Datos'!$U:$U, $F60, 'Base de Datos'!$AA:$AA, "Finalizada", 'Base de Datos'!#REF!, ">=01/06/2026", 'Base de Datos'!#REF!, "<=30/06/2026") -> #REF!
C61: 2023 | D61: 88 | E61: 3.4.2.2.1 | F61: SUBGERENCIAPLANEACIÓNYPROYECTOS(ZPP) | G61: =IF(COUNTIFS($C$4:C61, C61, $D$4:D61, D61, $E$4:E61, E61)=1, 1, 0) -> 1 | H61: {=SUMPRODUCT((TRIM(CLEAN('Base de Datos'!$F$2:$F$3000))&""=TRIM(CLEAN(C61))&"")*(TRIM(CLEAN('Base de Datos'!$G$2:$G$3000))&""=TRIM(CLEAN(D61))&"")*(TRIM(CLEAN('Base de Datos'!$H$2:$H$3000))&""=TRIM(CLEAN(E61))&"")*(TRIM(CLEAN('Base de Datos'!$U$2:$U$3000))&""=TRIM(CLEAN(F61))&""))} -> 0 | I61: =COUNTIFS('Base de Datos'!$F:$F,$C61,'Base de Datos'!$G:$G,$D61,'Base de Datos'!$H:$H,$E61,'Base de Datos'!$U:$U,$F61,'Base de Datos'!$AA:$AA,"Abierta") -> 0 | J61: =COUNTIFS('Base de Datos'!$F:$F,$C61,'Base de Datos'!$G:$G,$D61,'Base de Datos'!$H:$H,$E61,'Base de Datos'!$U:$U,$F61,'Base de Datos'!$AA:$AA,"Vencida") -> 0 | K61: =COUNTIFS('Base de Datos'!$F:$F,$C61,'Base de Datos'!$G:$G,$D61,'Base de Datos'!$H:$H,$E61,'Base de Datos'!$U:$U,$F61,'Base de Datos'!$AA:$AA,"Finalizada") -> 0 | L61: =COUNTIFS('Base de Datos'!$F:$F,$C61,'Base de Datos'!$G:$G,$D61,'Base de Datos'!$H:$H,$E61,'Base de Datos'!$U:$U,$F61,'Base de Datos'!$AA:$AA,"Abierta",'Base de Datos'!$AC:$AC,"<=10",'Base de Datos'!$AC:$AC,">0") -> 0 | M61: =COUNTIFS('Base de Datos'!$F:$F,$C61,'Base de Datos'!$G:$G,$D61,'Base de Datos'!$H:$H,$E61,'Base de Datos'!$U:$U,$F61,'Base de Datos'!$AA:$AA,"Abierta",'Base de Datos'!$AC:$AC,"<=20",'Base de Datos'!$AC:$AC,">10") -> 0 | N61: =COUNTIFS('Base de Datos'!$F:$F,$C61,'Base de Datos'!$G:$G,$D61,'Base de Datos'!$H:$H,$E61,'Base de Datos'!$U:$U,$F61,'Base de Datos'!$AA:$AA,"Abierta",'Base de Datos'!$AC:$AC,"<=30",'Base de Datos'!$AC:$AC,">20") -> 0 | O61: =COUNTIFS('Base de Datos'!$F:$F,$C61,'Base de Datos'!$G:$G,$D61,'Base de Datos'!$H:$H,$E61,'Base de Datos'!$U:$U,$F61,'Base de Datos'!$AA:$AA,"Abierta",'Base de Datos'!$AG:$AG,1) -> 0 | P61: =COUNTIFS('Base de Datos'!$F:$F, $C61, 'Base de Datos'!$H:$H, $E61, 'Base de Datos'!$U:$U, $F61, 'Base de Datos'!$AA:$AA, "Finalizada", 'Base de Datos'!#REF!, ">=01/01/2026", 'Base de Datos'!#REF!, "<=31/01/2026") -> #REF! | Q61: =COUNTIFS('Base de Datos'!$F:$F, $C61, 'Base de Datos'!$H:$H, $E61, 'Base de Datos'!$U:$U, $F61, 'Base de Datos'!$AA:$AA, "Finalizada", 'Base de Datos'!#REF!, ">=01/02/2026", 'Base de Datos'!#REF!, "<=28/02/2026") -> #REF! | R61: =COUNTIFS('Base de Datos'!$F:$F, $C61, 'Base de Datos'!$H:$H, $E61, 'Base de Datos'!$U:$U, $F61, 'Base de Datos'!$AA:$AA, "Finalizada", 'Base de Datos'!#REF!, ">=01/03/2026", 'Base de Datos'!#REF!, "<=31/03/2026") -> #REF! | S61: =COUNTIFS('Base de Datos'!$F:$F, $C61, 'Base de Datos'!$H:$H, $E61, 'Base de Datos'!$U:$U, $F61, 'Base de Datos'!$AA:$AA, "Finalizada", 'Base de Datos'!#REF!, ">=01/04/2026", 'Base de Datos'!#REF!, "<=30/04/2026") -> #REF! | T61: =COUNTIFS('Base de Datos'!$F:$F, $C61, 'Base de Datos'!$H:$H, $E61, 'Base de Datos'!$U:$U, $F61, 'Base de Datos'!$AA:$AA, "Finalizada", 'Base de Datos'!#REF!, ">=01/05/2026", 'Base de Datos'!#REF!, "<=31/05/2026") -> #REF! | U61: =COUNTIFS('Base de Datos'!$F:$F, $C61, 'Base de Datos'!$H:$H, $E61, 'Base de Datos'!$U:$U, $F61, 'Base de Datos'!$AA:$AA, "Finalizada", 'Base de Datos'!#REF!, ">=01/06/2026", 'Base de Datos'!#REF!, "<=30/06/2026") -> #REF!
C62: 2023 | D62: 88 | E62: 3.4.2.2.2 | F62: SUBGERENCIAPLANEACIÓNYPROYECTOS(ZPP) | G62: =IF(COUNTIFS($C$4:C62, C62, $D$4:D62, D62, $E$4:E62, E62)=1, 1, 0) -> 1 | H62: {=SUMPRODUCT((TRIM(CLEAN('Base de Datos'!$F$2:$F$3000))&""=TRIM(CLEAN(C62))&"")*(TRIM(CLEAN('Base de Datos'!$G$2:$G$3000))&""=TRIM(CLEAN(D62))&"")*(TRIM(CLEAN('Base de Datos'!$H$2:$H$3000))&""=TRIM(CLEAN(E62))&"")*(TRIM(CLEAN('Base de Datos'!$U$2:$U$3000))&""=TRIM(CLEAN(F62))&""))} -> 0 | I62: =COUNTIFS('Base de Datos'!$F:$F,$C62,'Base de Datos'!$G:$G,$D62,'Base de Datos'!$H:$H,$E62,'Base de Datos'!$U:$U,$F62,'Base de Datos'!$AA:$AA,"Abierta") -> 0 | J62: =COUNTIFS('Base de Datos'!$F:$F,$C62,'Base de Datos'!$G:$G,$D62,'Base de Datos'!$H:$H,$E62,'Base de Datos'!$U:$U,$F62,'Base de Datos'!$AA:$AA,"Vencida") -> 0 | K62: =COUNTIFS('Base de Datos'!$F:$F,$C62,'Base de Datos'!$G:$G,$D62,'Base de Datos'!$H:$H,$E62,'Base de Datos'!$U:$U,$F62,'Base de Datos'!$AA:$AA,"Finalizada") -> 0 | L62: =COUNTIFS('Base de Datos'!$F:$F,$C62,'Base de Datos'!$G:$G,$D62,'Base de Datos'!$H:$H,$E62,'Base de Datos'!$U:$U,$F62,'Base de Datos'!$AA:$AA,"Abierta",'Base de Datos'!$AC:$AC,"<=10",'Base de Datos'!$AC:$AC,">0") -> 0 | M62: =COUNTIFS('Base de Datos'!$F:$F,$C62,'Base de Datos'!$G:$G,$D62,'Base de Datos'!$H:$H,$E62,'Base de Datos'!$U:$U,$F62,'Base de Datos'!$AA:$AA,"Abierta",'Base de Datos'!$AC:$AC,"<=20",'Base de Datos'!$AC:$AC,">10") -> 0 | N62: =COUNTIFS('Base de Datos'!$F:$F,$C62,'Base de Datos'!$G:$G,$D62,'Base de Datos'!$H:$H,$E62,'Base de Datos'!$U:$U,$F62,'Base de Datos'!$AA:$AA,"Abierta",'Base de Datos'!$AC:$AC,"<=30",'Base de Datos'!$AC:$AC,">20") -> 0 | O62: =COUNTIFS('Base de Datos'!$F:$F,$C62,'Base de Datos'!$G:$G,$D62,'Base de Datos'!$H:$H,$E62,'Base de Datos'!$U:$U,$F62,'Base de Datos'!$AA:$AA,"Abierta",'Base de Datos'!$AG:$AG,1) -> 0 | P62: =COUNTIFS('Base de Datos'!$F:$F, $C62, 'Base de Datos'!$H:$H, $E62, 'Base de Datos'!$U:$U, $F62, 'Base de Datos'!$AA:$AA, "Finalizada", 'Base de Datos'!#REF!, ">=01/01/2026", 'Base de Datos'!#REF!, "<=31/01/2026") -> #REF! | Q62: =COUNTIFS('Base de Datos'!$F:$F, $C62, 'Base de Datos'!$H:$H, $E62, 'Base de Datos'!$U:$U, $F62, 'Base de Datos'!$AA:$AA, "Finalizada", 'Base de Datos'!#REF!, ">=01/02/2026", 'Base de Datos'!#REF!, "<=28/02/2026") -> #REF! | R62: =COUNTIFS('Base de Datos'!$F:$F, $C62, 'Base de Datos'!$H:$H, $E62, 'Base de Datos'!$U:$U, $F62, 'Base de Datos'!$AA:$AA, "Finalizada", 'Base de Datos'!#REF!, ">=01/03/2026", 'Base de Datos'!#REF!, "<=31/03/2026") -> #REF! | S62: =COUNTIFS('Base de Datos'!$F:$F, $C62, 'Base de Datos'!$H:$H, $E62, 'Base de Datos'!$U:$U, $F62, 'Base de Datos'!$AA:$AA, "Finalizada", 'Base de Datos'!#REF!, ">=01/04/2026", 'Base de Datos'!#REF!, "<=30/04/2026") -> #REF! | T62: =COUNTIFS('Base de Datos'!$F:$F, $C62, 'Base de Datos'!$H:$H, $E62, 'Base de Datos'!$U:$U, $F62, 'Base de Datos'!$AA:$AA, "Finalizada", 'Base de Datos'!#REF!, ">=01/05/2026", 'Base de Datos'!#REF!, "<=31/05/2026") -> #REF! | U62: =COUNTIFS('Base de Datos'!$F:$F, $C62, 'Base de Datos'!$H:$H, $E62, 'Base de Datos'!$U:$U, $F62, 'Base de Datos'!$AA:$AA, "Finalizada", 'Base de Datos'!#REF!, ">=01/06/2026", 'Base de Datos'!#REF!, "<=30/06/2026") -> #REF!
C63: 2023 | D63: 88 | E63: 3.4.2.3.1 | F63: DIRECCIÓNDEGESTIÓNHUMANA | G63: =IF(COUNTIFS($C$4:C63, C63, $D$4:D63, D63, $E$4:E63, E63)=1, 1, 0) -> 1 | H63: {=SUMPRODUCT((TRIM(CLEAN('Base de Datos'!$F$2:$F$3000))&""=TRIM(CLEAN(C63))&"")*(TRIM(CLEAN('Base de Datos'!$G$2:$G$3000))&""=TRIM(CLEAN(D63))&"")*(TRIM(CLEAN('Base de Datos'!$H$2:$H$3000))&""=TRIM(CLEAN(E63))&"")*(TRIM(CLEAN('Base de Datos'!$U$2:$U$3000))&""=TRIM(CLEAN(F63))&""))} -> 0 | I63: =COUNTIFS('Base de Datos'!$F:$F,$C63,'Base de Datos'!$G:$G,$D63,'Base de Datos'!$H:$H,$E63,'Base de Datos'!$U:$U,$F63,'Base de Datos'!$AA:$AA,"Abierta") -> 0 | J63: =COUNTIFS('Base de Datos'!$F:$F,$C63,'Base de Datos'!$G:$G,$D63,'Base de Datos'!$H:$H,$E63,'Base de Datos'!$U:$U,$F63,'Base de Datos'!$AA:$AA,"Vencida") -> 0 | K63: =COUNTIFS('Base de Datos'!$F:$F,$C63,'Base de Datos'!$G:$G,$D63,'Base de Datos'!$H:$H,$E63,'Base de Datos'!$U:$U,$F63,'Base de Datos'!$AA:$AA,"Finalizada") -> 0 | L63: =COUNTIFS('Base de Datos'!$F:$F,$C63,'Base de Datos'!$G:$G,$D63,'Base de Datos'!$H:$H,$E63,'Base de Datos'!$U:$U,$F63,'Base de Datos'!$AA:$AA,"Abierta",'Base de Datos'!$AC:$AC,"<=10",'Base de Datos'!$AC:$AC,">0") -> 0 | M63: =COUNTIFS('Base de Datos'!$F:$F,$C63,'Base de Datos'!$G:$G,$D63,'Base de Datos'!$H:$H,$E63,'Base de Datos'!$U:$U,$F63,'Base de Datos'!$AA:$AA,"Abierta",'Base de Datos'!$AC:$AC,"<=20",'Base de Datos'!$AC:$AC,">10") -> 0 | N63: =COUNTIFS('Base de Datos'!$F:$F,$C63,'Base de Datos'!$G:$G,$D63,'Base de Datos'!$H:$H,$E63,'Base de Datos'!$U:$U,$F63,'Base de Datos'!$AA:$AA,"Abierta",'Base de Datos'!$AC:$AC,"<=30",'Base de Datos'!$AC:$AC,">20") -> 0 | O63: =COUNTIFS('Base de Datos'!$F:$F,$C63,'Base de Datos'!$G:$G,$D63,'Base de Datos'!$H:$H,$E63,'Base de Datos'!$U:$U,$F63,'Base de Datos'!$AA:$AA,"Abierta",'Base de Datos'!$AG:$AG,1) -> 0 | P63: =COUNTIFS('Base de Datos'!$F:$F, $C63, 'Base de Datos'!$H:$H, $E63, 'Base de Datos'!$U:$U, $F63, 'Base de Datos'!$AA:$AA, "Finalizada", 'Base de Datos'!#REF!, ">=01/01/2026", 'Base de Datos'!#REF!, "<=31/01/2026") -> #REF! | Q63: =COUNTIFS('Base de Datos'!$F:$F, $C63, 'Base de Datos'!$H:$H, $E63, 'Base de Datos'!$U:$U, $F63, 'Base de Datos'!$AA:$AA, "Finalizada", 'Base de Datos'!#REF!, ">=01/02/2026", 'Base de Datos'!#REF!, "<=28/02/2026") -> #REF! | R63: =COUNTIFS('Base de Datos'!$F:$F, $C63, 'Base de Datos'!$H:$H, $E63, 'Base de Datos'!$U:$U, $F63, 'Base de Datos'!$AA:$AA, "Finalizada", 'Base de Datos'!#REF!, ">=01/03/2026", 'Base de Datos'!#REF!, "<=31/03/2026") -> #REF! | S63: =COUNTIFS('Base de Datos'!$F:$F, $C63, 'Base de Datos'!$H:$H, $E63, 'Base de Datos'!$U:$U, $F63, 'Base de Datos'!$AA:$AA, "Finalizada", 'Base de Datos'!#REF!, ">=01/04/2026", 'Base de Datos'!#REF!, "<=30/04/2026") -> #REF! | T63: =COUNTIFS('Base de Datos'!$F:$F, $C63, 'Base de Datos'!$H:$H, $E63, 'Base de Datos'!$U:$U, $F63, 'Base de Datos'!$AA:$AA, "Finalizada", 'Base de Datos'!#REF!, ">=01/05/2026", 'Base de Datos'!#REF!, "<=31/05/2026") -> #REF! | U63: =COUNTIFS('Base de Datos'!$F:$F, $C63, 'Base de Datos'!$H:$H, $E63, 'Base de Datos'!$U:$U, $F63, 'Base de Datos'!$AA:$AA, "Finalizada", 'Base de Datos'!#REF!, ">=01/06/2026", 'Base de Datos'!#REF!, "<=30/06/2026") -> #REF!
C64: 2023 | D64: 88 | E64: 3.4.2.4.1 | F64: DIRECCIÓNDEGESTIÓNHUMANA | G64: =IF(COUNTIFS($C$4:C64, C64, $D$4:D64, D64, $E$4:E64, E64)=1, 1, 0) -> 1 | H64: {=SUMPRODUCT((TRIM(CLEAN('Base de Datos'!$F$2:$F$3000))&""=TRIM(CLEAN(C64))&"")*(TRIM(CLEAN('Base de Datos'!$G$2:$G$3000))&""=TRIM(CLEAN(D64))&"")*(TRIM(CLEAN('Base de Datos'!$H$2:$H$3000))&""=TRIM(CLEAN(E64))&"")*(TRIM(CLEAN('Base de Datos'!$U$2:$U$3000))&""=TRIM(CLEAN(F64))&""))} -> 0 | I64: =COUNTIFS('Base de Datos'!$F:$F,$C64,'Base de Datos'!$G:$G,$D64,'Base de Datos'!$H:$H,$E64,'Base de Datos'!$U:$U,$F64,'Base de Datos'!$AA:$AA,"Abierta") -> 0 | J64: =COUNTIFS('Base de Datos'!$F:$F,$C64,'Base de Datos'!$G:$G,$D64,'Base de Datos'!$H:$H,$E64,'Base de Datos'!$U:$U,$F64,'Base de Datos'!$AA:$AA,"Vencida") -> 0 | K64: =COUNTIFS('Base de Datos'!$F:$F,$C64,'Base de Datos'!$G:$G,$D64,'Base de Datos'!$H:$H,$E64,'Base de Datos'!$U:$U,$F64,'Base de Datos'!$AA:$AA,"Finalizada") -> 0 | L64: =COUNTIFS('Base de Datos'!$F:$F,$C64,'Base de Datos'!$G:$G,$D64,'Base de Datos'!$H:$H,$E64,'Base de Datos'!$U:$U,$F64,'Base de Datos'!$AA:$AA,"Abierta",'Base de Datos'!$AC:$AC,"<=10",'Base de Datos'!$AC:$AC,">0") -> 0 | M64: =COUNTIFS('Base de Datos'!$F:$F,$C64,'Base de Datos'!$G:$G,$D64,'Base de Datos'!$H:$H,$E64,'Base de Datos'!$U:$U,$F64,'Base de Datos'!$AA:$AA,"Abierta",'Base de Datos'!$AC:$AC,"<=20",'Base de Datos'!$AC:$AC,">10") -> 0 | N64: =COUNTIFS('Base de Datos'!$F:$F,$C64,'Base de Datos'!$G:$G,$D64,'Base de Datos'!$H:$H,$E64,'Base de Datos'!$U:$U,$F64,'Base de Datos'!$AA:$AA,"Abierta",'Base de Datos'!$AC:$AC,"<=30",'Base de Datos'!$AC:$AC,">20") -> 0 | O64: =COUNTIFS('Base de Datos'!$F:$F,$C64,'Base de Datos'!$G:$G,$D64,'Base de Datos'!$H:$H,$E64,'Base de Datos'!$U:$U,$F64,'Base de Datos'!$AA:$AA,"Abierta",'Base de Datos'!$AG:$AG,1) -> 0 | P64: =COUNTIFS('Base de Datos'!$F:$F, $C64, 'Base de Datos'!$H:$H, $E64, 'Base de Datos'!$U:$U, $F64, 'Base de Datos'!$AA:$AA, "Finalizada", 'Base de Datos'!#REF!, ">=01/01/2026", 'Base de Datos'!#REF!, "<=31/01/2026") -> #REF! | Q64: =COUNTIFS('Base de Datos'!$F:$F, $C64, 'Base de Datos'!$H:$H, $E64, 'Base de Datos'!$U:$U, $F64, 'Base de Datos'!$AA:$AA, "Finalizada", 'Base de Datos'!#REF!, ">=01/02/2026", 'Base de Datos'!#REF!, "<=28/02/2026") -> #REF! | R64: =COUNTIFS('Base de Datos'!$F:$F, $C64, 'Base de Datos'!$H:$H, $E64, 'Base de Datos'!$U:$U, $F64, 'Base de Datos'!$AA:$AA, "Finalizada", 'Base de Datos'!#REF!, ">=01/03/2026", 'Base de Datos'!#REF!, "<=31/03/2026") -> #REF! | S64: =COUNTIFS('Base de Datos'!$F:$F, $C64, 'Base de Datos'!$H:$H, $E64, 'Base de Datos'!$U:$U, $F64, 'Base de Datos'!$AA:$AA, "Finalizada", 'Base de Datos'!#REF!, ">=01/04/2026", 'Base de Datos'!#REF!, "<=30/04/2026") -> #REF! | T64: =COUNTIFS('Base de Datos'!$F:$F, $C64, 'Base de Datos'!$H:$H, $E64, 'Base de Datos'!$U:$U, $F64, 'Base de Datos'!$AA:$AA, "Finalizada", 'Base de Datos'!#REF!, ">=01/05/2026", 'Base de Datos'!#REF!, "<=31/05/2026") -> #REF! | U64: =COUNTIFS('Base de Datos'!$F:$F, $C64, 'Base de Datos'!$H:$H, $E64, 'Base de Datos'!$U:$U, $F64, 'Base de Datos'!$AA:$AA, "Finalizada", 'Base de Datos'!#REF!, ">=01/06/2026", 'Base de Datos'!#REF!, "<=30/06/2026") -> #REF!
C65: 2023 | D65: 88 | E65: 3.4.2.4.2 | F65: SUBGERENCIADEPLANEACIÓNYPROYECTOSDIRECCIÓNDEGESTIÓNHUMANA | G65: =IF(COUNTIFS($C$4:C65, C65, $D$4:D65, D65, $E$4:E65, E65)=1, 1, 0) -> 1 | H65: {=SUMPRODUCT((TRIM(CLEAN('Base de Datos'!$F$2:$F$3000))&""=TRIM(CLEAN(C65))&"")*(TRIM(CLEAN('Base de Datos'!$G$2:$G$3000))&""=TRIM(CLEAN(D65))&"")*(TRIM(CLEAN('Base de Datos'!$H$2:$H$3000))&""=TRIM(CLEAN(E65))&"")*(TRIM(CLEAN('Base de Datos'!$U$2:$U$3000))&""=TRIM(CLEAN(F65))&""))} -> 0 | I65: =COUNTIFS('Base de Datos'!$F:$F,$C65,'Base de Datos'!$G:$G,$D65,'Base de Datos'!$H:$H,$E65,'Base de Datos'!$U:$U,$F65,'Base de Datos'!$AA:$AA,"Abierta") -> 0 | J65: =COUNTIFS('Base de Datos'!$F:$F,$C65,'Base de Datos'!$G:$G,$D65,'Base de Datos'!$H:$H,$E65,'Base de Datos'!$U:$U,$F65,'Base de Datos'!$AA:$AA,"Vencida") -> 0 | K65: =COUNTIFS('Base de Datos'!$F:$F,$C65,'Base de Datos'!$G:$G,$D65,'Base de Datos'!$H:$H,$E65,'Base de Datos'!$U:$U,$F65,'Base de Datos'!$AA:$AA,"Finalizada") -> 0 | L65: =COUNTIFS('Base de Datos'!$F:$F,$C65,'Base de Datos'!$G:$G,$D65,'Base de Datos'!$H:$H,$E65,'Base de Datos'!$U:$U,$F65,'Base de Datos'!$AA:$AA,"Abierta",'Base de Datos'!$AC:$AC,"<=10",'Base de Datos'!$AC:$AC,">0") -> 0 | M65: =COUNTIFS('Base de Datos'!$F:$F,$C65,'Base de Datos'!$G:$G,$D65,'Base de Datos'!$H:$H,$E65,'Base de Datos'!$U:$U,$F65,'Base de Datos'!$AA:$AA,"Abierta",'Base de Datos'!$AC:$AC,"<=20",'Base de Datos'!$AC:$AC,">10") -> 0 | N65: =COUNTIFS('Base de Datos'!$F:$F,$C65,'Base de Datos'!$G:$G,$D65,'Base de Datos'!$H:$H,$E65,'Base de Datos'!$U:$U,$F65,'Base de Datos'!$AA:$AA,"Abierta",'Base de Datos'!$AC:$AC,"<=30",'Base de Datos'!$AC:$AC,">20") -> 0 | O65: =COUNTIFS('Base de Datos'!$F:$F,$C65,'Base de Datos'!$G:$G,$D65,'Base de Datos'!$H:$H,$E65,'Base de Datos'!$U:$U,$F65,'Base de Datos'!$AA:$AA,"Abierta",'Base de Datos'!$AG:$AG,1) -> 0 | P65: =COUNTIFS('Base de Datos'!$F:$F, $C65, 'Base de Datos'!$H:$H, $E65, 'Base de Datos'!$U:$U, $F65, 'Base de Datos'!$AA:$AA, "Finalizada", 'Base de Datos'!#REF!, ">=01/01/2026", 'Base de Datos'!#REF!, "<=31/01/2026") -> #REF! | Q65: =COUNTIFS('Base de Datos'!$F:$F, $C65, 'Base de Datos'!$H:$H, $E65, 'Base de Datos'!$U:$U, $F65, 'Base de Datos'!$AA:$AA, "Finalizada", 'Base de Datos'!#REF!, ">=01/02/2026", 'Base de Datos'!#REF!, "<=28/02/2026") -> #REF! | R65: =COUNTIFS('Base de Datos'!$F:$F, $C65, 'Base de Datos'!$H:$H, $E65, 'Base de Datos'!$U:$U, $F65, 'Base de Datos'!$AA:$AA, "Finalizada", 'Base de Datos'!#REF!, ">=01/03/2026", 'Base de Datos'!#REF!, "<=31/03/2026") -> #REF! | S65: =COUNTIFS('Base de Datos'!$F:$F, $C65, 'Base de Datos'!$H:$H, $E65, 'Base de Datos'!$U:$U, $F65, 'Base de Datos'!$AA:$AA, "Finalizada", 'Base de Datos'!#REF!, ">=01/04/2026", 'Base de Datos'!#REF!, "<=30/04/2026") -> #REF! | T65: =COUNTIFS('Base de Datos'!$F:$F, $C65, 'Base de Datos'!$H:$H, $E65, 'Base de Datos'!$U:$U, $F65, 'Base de Datos'!$AA:$AA, "Finalizada", 'Base de Datos'!#REF!, ">=01/05/2026", 'Base de Datos'!#REF!, "<=31/05/2026") -> #REF! | U65: =COUNTIFS('Base de Datos'!$F:$F, $C65, 'Base de Datos'!$H:$H, $E65, 'Base de Datos'!$U:$U, $F65, 'Base de Datos'!$AA:$AA, "Finalizada", 'Base de Datos'!#REF!, ">=01/06/2026", 'Base de Datos'!#REF!, "<=30/06/2026") -> #REF!
C66: 2023 | D66: 88 | E66: 3.4.2.4.3 | F66: DIRECCIÓNDEGESTIÓNHUMANA | G66: =IF(COUNTIFS($C$4:C66, C66, $D$4:D66, D66, $E$4:E66, E66)=1, 1, 0) -> 1 | H66: {=SUMPRODUCT((TRIM(CLEAN('Base de Datos'!$F$2:$F$3000))&""=TRIM(CLEAN(C66))&"")*(TRIM(CLEAN('Base de Datos'!$G$2:$G$3000))&""=TRIM(CLEAN(D66))&"")*(TRIM(CLEAN('Base de Datos'!$H$2:$H$3000))&""=TRIM(CLEAN(E66))&"")*(TRIM(CLEAN('Base de Datos'!$U$2:$U$3000))&""=TRIM(CLEAN(F66))&""))} -> 0 | I66: =COUNTIFS('Base de Datos'!$F:$F,$C66,'Base de Datos'!$G:$G,$D66,'Base de Datos'!$H:$H,$E66,'Base de Datos'!$U:$U,$F66,'Base de Datos'!$AA:$AA,"Abierta") -> 0 | J66: =COUNTIFS('Base de Datos'!$F:$F,$C66,'Base de Datos'!$G:$G,$D66,'Base de Datos'!$H:$H,$E66,'Base de Datos'!$U:$U,$F66,'Base de Datos'!$AA:$AA,"Vencida") -> 0 | K66: =COUNTIFS('Base de Datos'!$F:$F,$C66,'Base de Datos'!$G:$G,$D66,'Base de Datos'!$H:$H,$E66,'Base de Datos'!$U:$U,$F66,'Base de Datos'!$AA:$AA,"Finalizada") -> 0 | L66: =COUNTIFS('Base de Datos'!$F:$F,$C66,'Base de Datos'!$G:$G,$D66,'Base de Datos'!$H:$H,$E66,'Base de Datos'!$U:$U,$F66,'Base de Datos'!$AA:$AA,"Abierta",'Base de Datos'!$AC:$AC,"<=10",'Base de Datos'!$AC:$AC,">0") -> 0 | M66: =COUNTIFS('Base de Datos'!$F:$F,$C66,'Base de Datos'!$G:$G,$D66,'Base de Datos'!$H:$H,$E66,'Base de Datos'!$U:$U,$F66,'Base de Datos'!$AA:$AA,"Abierta",'Base de Datos'!$AC:$AC,"<=20",'Base de Datos'!$AC:$AC,">10") -> 0 | N66: =COUNTIFS('Base de Datos'!$F:$F,$C66,'Base de Datos'!$G:$G,$D66,'Base de Datos'!$H:$H,$E66,'Base de Datos'!$U:$U,$F66,'Base de Datos'!$AA:$AA,"Abierta",'Base de Datos'!$AC:$AC,"<=30",'Base de Datos'!$AC:$AC,">20") -> 0 | O66: =COUNTIFS('Base de Datos'!$F:$F,$C66,'Base de Datos'!$G:$G,$D66,'Base de Datos'!$H:$H,$E66,'Base de Datos'!$U:$U,$F66,'Base de Datos'!$AA:$AA,"Abierta",'Base de Datos'!$AG:$AG,1) -> 0 | P66: =COUNTIFS('Base de Datos'!$F:$F, $C66, 'Base de Datos'!$H:$H, $E66, 'Base de Datos'!$U:$U, $F66, 'Base de Datos'!$AA:$AA, "Finalizada", 'Base de Datos'!#REF!, ">=01/01/2026", 'Base de Datos'!#REF!, "<=31/01/2026") -> #REF! | Q66: =COUNTIFS('Base de Datos'!$F:$F, $C66, 'Base de Datos'!$H:$H, $E66, 'Base de Datos'!$U:$U, $F66, 'Base de Datos'!$AA:$AA, "Finalizada", 'Base de Datos'!#REF!, ">=01/02/2026", 'Base de Datos'!#REF!, "<=28/02/2026") -> #REF! | R66: =COUNTIFS('Base de Datos'!$F:$F, $C66, 'Base de Datos'!$H:$H, $E66, 'Base de Datos'!$U:$U, $F66, 'Base de Datos'!$AA:$AA, "Finalizada", 'Base de Datos'!#REF!, ">=01/03/2026", 'Base de Datos'!#REF!, "<=31/03/2026") -> #REF! | S66: =COUNTIFS('Base de Datos'!$F:$F, $C66, 'Base de Datos'!$H:$H, $E66, 'Base de Datos'!$U:$U, $F66, 'Base de Datos'!$AA:$AA, "Finalizada", 'Base de Datos'!#REF!, ">=01/04/2026", 'Base de Datos'!#REF!, "<=30/04/2026") -> #REF! | T66: =COUNTIFS('Base de Datos'!$F:$F, $C66, 'Base de Datos'!$H:$H, $E66, 'Base de Datos'!$U:$U, $F66, 'Base de Datos'!$AA:$AA, "Finalizada", 'Base de Datos'!#REF!, ">=01/05/2026", 'Base de Datos'!#REF!, "<=31/05/2026") -> #REF! | U66: =COUNTIFS('Base de Datos'!$F:$F, $C66, 'Base de Datos'!$H:$H, $E66, 'Base de Datos'!$U:$U, $F66, 'Base de Datos'!$AA:$AA, "Finalizada", 'Base de Datos'!#REF!, ">=01/06/2026", 'Base de Datos'!#REF!, "<=30/06/2026") -> #REF!
C67: 2023 | D67: 88 | E67: 3.4.2.4.4 | F67: DIRECCIÓNDEGESTIÓNHUMANA | G67: =IF(COUNTIFS($C$4:C67, C67, $D$4:D67, D67, $E$4:E67, E67)=1, 1, 0) -> 1 | H67: {=SUMPRODUCT((TRIM(CLEAN('Base de Datos'!$F$2:$F$3000))&""=TRIM(CLEAN(C67))&"")*(TRIM(CLEAN('Base de Datos'!$G$2:$G$3000))&""=TRIM(CLEAN(D67))&"")*(TRIM(CLEAN('Base de Datos'!$H$2:$H$3000))&""=TRIM(CLEAN(E67))&"")*(TRIM(CLEAN('Base de Datos'!$U$2:$U$3000))&""=TRIM(CLEAN(F67))&""))} -> 0 | I67: =COUNTIFS('Base de Datos'!$F:$F,$C67,'Base de Datos'!$G:$G,$D67,'Base de Datos'!$H:$H,$E67,'Base de Datos'!$U:$U,$F67,'Base de Datos'!$AA:$AA,"Abierta") -> 0 | J67: =COUNTIFS('Base de Datos'!$F:$F,$C67,'Base de Datos'!$G:$G,$D67,'Base de Datos'!$H:$H,$E67,'Base de Datos'!$U:$U,$F67,'Base de Datos'!$AA:$AA,"Vencida") -> 0 | K67: =COUNTIFS('Base de Datos'!$F:$F,$C67,'Base de Datos'!$G:$G,$D67,'Base de Datos'!$H:$H,$E67,'Base de Datos'!$U:$U,$F67,'Base de Datos'!$AA:$AA,"Finalizada") -> 0 | L67: =COUNTIFS('Base de Datos'!$F:$F,$C67,'Base de Datos'!$G:$G,$D67,'Base de Datos'!$H:$H,$E67,'Base de Datos'!$U:$U,$F67,'Base de Datos'!$AA:$AA,"Abierta",'Base de Datos'!$AC:$AC,"<=10",'Base de Datos'!$AC:$AC,">0") -> 0 | M67: =COUNTIFS('Base de Datos'!$F:$F,$C67,'Base de Datos'!$G:$G,$D67,'Base de Datos'!$H:$H,$E67,'Base de Datos'!$U:$U,$F67,'Base de Datos'!$AA:$AA,"Abierta",'Base de Datos'!$AC:$AC,"<=20",'Base de Datos'!$AC:$AC,">10") -> 0 | N67: =COUNTIFS('Base de Datos'!$F:$F,$C67,'Base de Datos'!$G:$G,$D67,'Base de Datos'!$H:$H,$E67,'Base de Datos'!$U:$U,$F67,'Base de Datos'!$AA:$AA,"Abierta",'Base de Datos'!$AC:$AC,"<=30",'Base de Datos'!$AC:$AC,">20") -> 0 | O67: =COUNTIFS('Base de Datos'!$F:$F,$C67,'Base de Datos'!$G:$G,$D67,'Base de Datos'!$H:$H,$E67,'Base de Datos'!$U:$U,$F67,'Base de Datos'!$AA:$AA,"Abierta",'Base de Datos'!$AG:$AG,1) -> 0 | P67: =COUNTIFS('Base de Datos'!$F:$F, $C67, 'Base de Datos'!$H:$H, $E67, 'Base de Datos'!$U:$U, $F67, 'Base de Datos'!$AA:$AA, "Finalizada", 'Base de Datos'!#REF!, ">=01/01/2026", 'Base de Datos'!#REF!, "<=31/01/2026") -> #REF! | Q67: =COUNTIFS('Base de Datos'!$F:$F, $C67, 'Base de Datos'!$H:$H, $E67, 'Base de Datos'!$U:$U, $F67, 'Base de Datos'!$AA:$AA, "Finalizada", 'Base de Datos'!#REF!, ">=01/02/2026", 'Base de Datos'!#REF!, "<=28/02/2026") -> #REF! | R67: =COUNTIFS('Base de Datos'!$F:$F, $C67, 'Base de Datos'!$H:$H, $E67, 'Base de Datos'!$U:$U, $F67, 'Base de Datos'!$AA:$AA, "Finalizada", 'Base de Datos'!#REF!, ">=01/03/2026", 'Base de Datos'!#REF!, "<=31/03/2026") -> #REF! | S67: =COUNTIFS('Base de Datos'!$F:$F, $C67, 'Base de Datos'!$H:$H, $E67, 'Base de Datos'!$U:$U, $F67, 'Base de Datos'!$AA:$AA, "Finalizada", 'Base de Datos'!#REF!, ">=01/04/2026", 'Base de Datos'!#REF!, "<=30/04/2026") -> #REF! | T67: =COUNTIFS('Base de Datos'!$F:$F, $C67, 'Base de Datos'!$H:$H, $E67, 'Base de Datos'!$U:$U, $F67, 'Base de Datos'!$AA:$AA, "Finalizada", 'Base de Datos'!#REF!, ">=01/05/2026", 'Base de Datos'!#REF!, "<=31/05/2026") -> #REF! | U67: =COUNTIFS('Base de Datos'!$F:$F, $C67, 'Base de Datos'!$H:$H, $E67, 'Base de Datos'!$U:$U, $F67, 'Base de Datos'!$AA:$AA, "Finalizada", 'Base de Datos'!#REF!, ">=01/06/2026", 'Base de Datos'!#REF!, "<=30/06/2026") -> #REF!
C68: 2023 | D68: 88 | E68: 3.4.2.5.1 | F68: SUBGERENCIAJURÍDICA | G68: =IF(COUNTIFS($C$4:C68, C68, $D$4:D68, D68, $E$4:E68, E68)=1, 1, 0) -> 1 | H68: {=SUMPRODUCT((TRIM(CLEAN('Base de Datos'!$F$2:$F$3000))&""=TRIM(CLEAN(C68))&"")*(TRIM(CLEAN('Base de Datos'!$G$2:$G$3000))&""=TRIM(CLEAN(D68))&"")*(TRIM(CLEAN('Base de Datos'!$H$2:$H$3000))&""=TRIM(CLEAN(E68))&"")*(TRIM(CLEAN('Base de Datos'!$U$2:$U$3000))&""=TRIM(CLEAN(F68))&""))} -> 0 | I68: =COUNTIFS('Base de Datos'!$F:$F,$C68,'Base de Datos'!$G:$G,$D68,'Base de Datos'!$H:$H,$E68,'Base de Datos'!$U:$U,$F68,'Base de Datos'!$AA:$AA,"Abierta") -> 0 | J68: =COUNTIFS('Base de Datos'!$F:$F,$C68,'Base de Datos'!$G:$G,$D68,'Base de Datos'!$H:$H,$E68,'Base de Datos'!$U:$U,$F68,'Base de Datos'!$AA:$AA,"Vencida") -> 0 | K68: =COUNTIFS('Base de Datos'!$F:$F,$C68,'Base de Datos'!$G:$G,$D68,'Base de Datos'!$H:$H,$E68,'Base de Datos'!$U:$U,$F68,'Base de Datos'!$AA:$AA,"Finalizada") -> 0 | L68: =COUNTIFS('Base de Datos'!$F:$F,$C68,'Base de Datos'!$G:$G,$D68,'Base de Datos'!$H:$H,$E68,'Base de Datos'!$U:$U,$F68,'Base de Datos'!$AA:$AA,"Abierta",'Base de Datos'!$AC:$AC,"<=10",'Base de Datos'!$AC:$AC,">0") -> 0 | M68: =COUNTIFS('Base de Datos'!$F:$F,$C68,'Base de Datos'!$G:$G,$D68,'Base de Datos'!$H:$H,$E68,'Base de Datos'!$U:$U,$F68,'Base de Datos'!$AA:$AA,"Abierta",'Base de Datos'!$AC:$AC,"<=20",'Base de Datos'!$AC:$AC,">10") -> 0 | N68: =COUNTIFS('Base de Datos'!$F:$F,$C68,'Base de Datos'!$G:$G,$D68,'Base de Datos'!$H:$H,$E68,'Base de Datos'!$U:$U,$F68,'Base de Datos'!$AA:$AA,"Abierta",'Base de Datos'!$AC:$AC,"<=30",'Base de Datos'!$AC:$AC,">20") -> 0 | O68: =COUNTIFS('Base de Datos'!$F:$F,$C68,'Base de Datos'!$G:$G,$D68,'Base de Datos'!$H:$H,$E68,'Base de Datos'!$U:$U,$F68,'Base de Datos'!$AA:$AA,"Abierta",'Base de Datos'!$AG:$AG,1) -> 0 | P68: =COUNTIFS('Base de Datos'!$F:$F, $C68, 'Base de Datos'!$H:$H, $E68, 'Base de Datos'!$U:$U, $F68, 'Base de Datos'!$AA:$AA, "Finalizada", 'Base de Datos'!#REF!, ">=01/01/2026", 'Base de Datos'!#REF!, "<=31/01/2026") -> #REF! | Q68: =COUNTIFS('Base de Datos'!$F:$F, $C68, 'Base de Datos'!$H:$H, $E68, 'Base de Datos'!$U:$U, $F68, 'Base de Datos'!$AA:$AA, "Finalizada", 'Base de Datos'!#REF!, ">=01/02/2026", 'Base de Datos'!#REF!, "<=28/02/2026") -> #REF! | R68: =COUNTIFS('Base de Datos'!$F:$F, $C68, 'Base de Datos'!$H:$H, $E68, 'Base de Datos'!$U:$U, $F68, 'Base de Datos'!$AA:$AA, "Finalizada", 'Base de Datos'!#REF!, ">=01/03/2026", 'Base de Datos'!#REF!, "<=31/03/2026") -> #REF! | S68: =COUNTIFS('Base de Datos'!$F:$F, $C68, 'Base de Datos'!$H:$H, $E68, 'Base de Datos'!$U:$U, $F68, 'Base de Datos'!$AA:$AA, "Finalizada", 'Base de Datos'!#REF!, ">=01/04/2026", 'Base de Datos'!#REF!, "<=30/04/2026") -> #REF! | T68: =COUNTIFS('Base de Datos'!$F:$F, $C68, 'Base de Datos'!$H:$H, $E68, 'Base de Datos'!$U:$U, $F68, 'Base de Datos'!$AA:$AA, "Finalizada", 'Base de Datos'!#REF!, ">=01/05/2026", 'Base de Datos'!#REF!, "<=31/05/2026") -> #REF! | U68: =COUNTIFS('Base de Datos'!$F:$F, $C68, 'Base de Datos'!$H:$H, $E68, 'Base de Datos'!$U:$U, $F68, 'Base de Datos'!$AA:$AA, "Finalizada", 'Base de Datos'!#REF!, ">=01/06/2026", 'Base de Datos'!#REF!, "<=30/06/2026") -> #REF!
C69: 2023 | D69: 88 | E69: 3.4.2.5.2 | F69: SUBGERENCIAJURÍDICA | G69: =IF(COUNTIFS($C$4:C69, C69, $D$4:D69, D69, $E$4:E69, E69)=1, 1, 0) -> 1 | H69: {=SUMPRODUCT((TRIM(CLEAN('Base de Datos'!$F$2:$F$3000))&""=TRIM(CLEAN(C69))&"")*(TRIM(CLEAN('Base de Datos'!$G$2:$G$3000))&""=TRIM(CLEAN(D69))&"")*(TRIM(CLEAN('Base de Datos'!$H$2:$H$3000))&""=TRIM(CLEAN(E69))&"")*(TRIM(CLEAN('Base de Datos'!$U$2:$U$3000))&""=TRIM(CLEAN(F69))&""))} -> 0 | I69: =COUNTIFS('Base de Datos'!$F:$F,$C69,'Base de Datos'!$G:$G,$D69,'Base de Datos'!$H:$H,$E69,'Base de Datos'!$U:$U,$F69,'Base de Datos'!$AA:$AA,"Abierta") -> 0 | J69: =COUNTIFS('Base de Datos'!$F:$F,$C69,'Base de Datos'!$G:$G,$D69,'Base de Datos'!$H:$H,$E69,'Base de Datos'!$U:$U,$F69,'Base de Datos'!$AA:$AA,"Vencida") -> 0 | K69: =COUNTIFS('Base de Datos'!$F:$F,$C69,'Base de Datos'!$G:$G,$D69,'Base de Datos'!$H:$H,$E69,'Base de Datos'!$U:$U,$F69,'Base de Datos'!$AA:$AA,"Finalizada") -> 0 | L69: =COUNTIFS('Base de Datos'!$F:$F,$C69,'Base de Datos'!$G:$G,$D69,'Base de Datos'!$H:$H,$E69,'Base de Datos'!$U:$U,$F69,'Base de Datos'!$AA:$AA,"Abierta",'Base de Datos'!$AC:$AC,"<=10",'Base de Datos'!$AC:$AC,">0") -> 0 | M69: =COUNTIFS('Base de Datos'!$F:$F,$C69,'Base de Datos'!$G:$G,$D69,'Base de Datos'!$H:$H,$E69,'Base de Datos'!$U:$U,$F69,'Base de Datos'!$AA:$AA,"Abierta",'Base de Datos'!$AC:$AC,"<=20",'Base de Datos'!$AC:$AC,">10") -> 0 | N69: =COUNTIFS('Base de Datos'!$F:$F,$C69,'Base de Datos'!$G:$G,$D69,'Base de Datos'!$H:$H,$E69,'Base de Datos'!$U:$U,$F69,'Base de Datos'!$AA:$AA,"Abierta",'Base de Datos'!$AC:$AC,"<=30",'Base de Datos'!$AC:$AC,">20") -> 0 | O69: =COUNTIFS('Base de Datos'!$F:$F,$C69,'Base de Datos'!$G:$G,$D69,'Base de Datos'!$H:$H,$E69,'Base de Datos'!$U:$U,$F69,'Base de Datos'!$AA:$AA,"Abierta",'Base de Datos'!$AG:$AG,1) -> 0 | P69: =COUNTIFS('Base de Datos'!$F:$F, $C69, 'Base de Datos'!$H:$H, $E69, 'Base de Datos'!$U:$U, $F69, 'Base de Datos'!$AA:$AA, "Finalizada", 'Base de Datos'!#REF!, ">=01/01/2026", 'Base de Datos'!#REF!, "<=31/01/2026") -> #REF! | Q69: =COUNTIFS('Base de Datos'!$F:$F, $C69, 'Base de Datos'!$H:$H, $E69, 'Base de Datos'!$U:$U, $F69, 'Base de Datos'!$AA:$AA, "Finalizada", 'Base de Datos'!#REF!, ">=01/02/2026", 'Base de Datos'!#REF!, "<=28/02/2026") -> #REF! | R69: =COUNTIFS('Base de Datos'!$F:$F, $C69, 'Base de Datos'!$H:$H, $E69, 'Base de Datos'!$U:$U, $F69, 'Base de Datos'!$AA:$AA, "Finalizada", 'Base de Datos'!#REF!, ">=01/03/2026", 'Base de Datos'!#REF!, "<=31/03/2026") -> #REF! | S69: =COUNTIFS('Base de Datos'!$F:$F, $C69, 'Base de Datos'!$H:$H, $E69, 'Base de Datos'!$U:$U, $F69, 'Base de Datos'!$AA:$AA, "Finalizada", 'Base de Datos'!#REF!, ">=01/04/2026", 'Base de Datos'!#REF!, "<=30/04/2026") -> #REF! | T69: =COUNTIFS('Base de Datos'!$F:$F, $C69, 'Base de Datos'!$H:$H, $E69, 'Base de Datos'!$U:$U, $F69, 'Base de Datos'!$AA:$AA, "Finalizada", 'Base de Datos'!#REF!, ">=01/05/2026", 'Base de Datos'!#REF!, "<=31/05/2026") -> #REF! | U69: =COUNTIFS('Base de Datos'!$F:$F, $C69, 'Base de Datos'!$H:$H, $E69, 'Base de Datos'!$U:$U, $F69, 'Base de Datos'!$AA:$AA, "Finalizada", 'Base de Datos'!#REF!, ">=01/06/2026", 'Base de Datos'!#REF!, "<=30/06/2026") -> #REF!
C70: 2023 | D70: 88 | E70: 3.4.2.6.1 | F70: SUBGERENCIAJURÍDICA | G70: =IF(COUNTIFS($C$4:C70, C70, $D$4:D70, D70, $E$4:E70, E70)=1, 1, 0) -> 1 | H70: {=SUMPRODUCT((TRIM(CLEAN('Base de Datos'!$F$2:$F$3000))&""=TRIM(CLEAN(C70))&"")*(TRIM(CLEAN('Base de Datos'!$G$2:$G$3000))&""=TRIM(CLEAN(D70))&"")*(TRIM(CLEAN('Base de Datos'!$H$2:$H$3000))&""=TRIM(CLEAN(E70))&"")*(TRIM(CLEAN('Base de Datos'!$U$2:$U$3000))&""=TRIM(CLEAN(F70))&""))} -> 0 | I70: =COUNTIFS('Base de Datos'!$F:$F,$C70,'Base de Datos'!$G:$G,$D70,'Base de Datos'!$H:$H,$E70,'Base de Datos'!$U:$U,$F70,'Base de Datos'!$AA:$AA,"Abierta") -> 0 | J70: =COUNTIFS('Base de Datos'!$F:$F,$C70,'Base de Datos'!$G:$G,$D70,'Base de Datos'!$H:$H,$E70,'Base de Datos'!$U:$U,$F70,'Base de Datos'!$AA:$AA,"Vencida") -> 0 | K70: =COUNTIFS('Base de Datos'!$F:$F,$C70,'Base de Datos'!$G:$G,$D70,'Base de Datos'!$H:$H,$E70,'Base de Datos'!$U:$U,$F70,'Base de Datos'!$AA:$AA,"Finalizada") -> 0 | L70: =COUNTIFS('Base de Datos'!$F:$F,$C70,'Base de Datos'!$G:$G,$D70,'Base de Datos'!$H:$H,$E70,'Base de Datos'!$U:$U,$F70,'Base de Datos'!$AA:$AA,"Abierta",'Base de Datos'!$AC:$AC,"<=10",'Base de Datos'!$AC:$AC,">0") -> 0 | M70: =COUNTIFS('Base de Datos'!$F:$F,$C70,'Base de Datos'!$G:$G,$D70,'Base de Datos'!$H:$H,$E70,'Base de Datos'!$U:$U,$F70,'Base de Datos'!$AA:$AA,"Abierta",'Base de Datos'!$AC:$AC,"<=20",'Base de Datos'!$AC:$AC,">10") -> 0 | N70: =COUNTIFS('Base de Datos'!$F:$F,$C70,'Base de Datos'!$G:$G,$D70,'Base de Datos'!$H:$H,$E70,'Base de Datos'!$U:$U,$F70,'Base de Datos'!$AA:$AA,"Abierta",'Base de Datos'!$AC:$AC,"<=30",'Base de Datos'!$AC:$AC,">20") -> 0 | O70: =COUNTIFS('Base de Datos'!$F:$F,$C70,'Base de Datos'!$G:$G,$D70,'Base de Datos'!$H:$H,$E70,'Base de Datos'!$U:$U,$F70,'Base de Datos'!$AA:$AA,"Abierta",'Base de Datos'!$AG:$AG,1) -> 0 | P70: =COUNTIFS('Base de Datos'!$F:$F, $C70, 'Base de Datos'!$H:$H, $E70, 'Base de Datos'!$U:$U, $F70, 'Base de Datos'!$AA:$AA, "Finalizada", 'Base de Datos'!#REF!, ">=01/01/2026", 'Base de Datos'!#REF!, "<=31/01/2026") -> #REF! | Q70: =COUNTIFS('Base de Datos'!$F:$F, $C70, 'Base de Datos'!$H:$H, $E70, 'Base de Datos'!$U:$U, $F70, 'Base de Datos'!$AA:$AA, "Finalizada", 'Base de Datos'!#REF!, ">=01/02/2026", 'Base de Datos'!#REF!, "<=28/02/2026") -> #REF! | R70: =COUNTIFS('Base de Datos'!$F:$F, $C70, 'Base de Datos'!$H:$H, $E70, 'Base de Datos'!$U:$U, $F70, 'Base de Datos'!$AA:$AA, "Finalizada", 'Base de Datos'!#REF!, ">=01/03/2026", 'Base de Datos'!#REF!, "<=31/03/2026") -> #REF! | S70: =COUNTIFS('Base de Datos'!$F:$F, $C70, 'Base de Datos'!$H:$H, $E70, 'Base de Datos'!$U:$U, $F70, 'Base de Datos'!$AA:$AA, "Finalizada", 'Base de Datos'!#REF!, ">=01/04/2026", 'Base de Datos'!#REF!, "<=30/04/2026") -> #REF! | T70: =COUNTIFS('Base de Datos'!$F:$F, $C70, 'Base de Datos'!$H:$H, $E70, 'Base de Datos'!$U:$U, $F70, 'Base de Datos'!$AA:$AA, "Finalizada", 'Base de Datos'!#REF!, ">=01/05/2026", 'Base de Datos'!#REF!, "<=31/05/2026") -> #REF! | U70: =COUNTIFS('Base de Datos'!$F:$F, $C70, 'Base de Datos'!$H:$H, $E70, 'Base de Datos'!$U:$U, $F70, 'Base de Datos'!$AA:$AA, "Finalizada", 'Base de Datos'!#REF!, ">=01/06/2026", 'Base de Datos'!#REF!, "<=30/06/2026") -> #REF!

Sheet Cálculos
A12: Etiquetas de fila | B12: Suma de Total Planes de acción
A13: 2023 | B13: 24 | F13: Valores
A14: 2024 | B14: 26 | F14: Suma de Abiertos | G14: 11
A15: 2025 | B15: 34 | F15: Suma de Vencidos | G15: 6
A16: Total general | B16: 84 | F16: Suma de Finalizados | G16: 67
A19: Valores
A20: Suma de Alerta 5 | B20: 0 | C20: =GETPIVOTDATA("Suma de Alerta 5",$A$19) -> 0
A21: Suma de Alerta 10 | B21: 0 | C21: =GETPIVOTDATA("Suma de Alerta 10",$A$19) -> 0
A22: Suma de Alerta 20 | B22: 0 | C22: =GETPIVOTDATA("Suma de Alerta 20",$A$19) -> 0
A23: Suma de Alerta 30 | B23: 0 | C23: =GETPIVOTDATA("Suma de Alerta 30",$A$19) -> 0
A26: Valores
A27: Suma de Total Planes de acción | B27: 84 | C27: =GETPIVOTDATA("Suma de Total Planes de acción",$A$26) -> 84
A28: Suma de Total hallazgos | B28: 54 | C28: =GETPIVOTDATA("Suma de Total hallazgos",$A$26) -> 54
A29: Suma de Abiertos | B29: 11 | C29: =GETPIVOTDATA("Suma de Abiertos",$A$26) -> 11
A30: Suma de Vencidos | B30: 6 | C30: =GETPIVOTDATA("Suma de Vencidos",$A$26) -> 6
A31: Suma de Finalizados | B31: 67 | C31: =GETPIVOTDATA("Suma de Finalizados",$A$26) -> 67
A34: =C31/C27 -> 0.79761905
A35: =1-A34 -> 0.20238095

Sheet Hoja1
A3: Etiquetas de fila | B3: Cuenta de ESTADO
A4: Abierta | B4: 11
A5: Finalizada | B5: 67
A6: Vencida | B6: 6
A7: Total general | B7: 84

Sheet Base de Datos
A1: No. | B1: FECHA REPORTE DE LA INFORMACIÓN | C1: SECTORIAL | D1: NOMBRE DE LA ENTIDAD | E1: CÓDIGO ENTIDAD | F1: VIGENCIA DE LA AUDITORÍA O VISITA | G1: CODIGO AUDITORÍA SEGÚN PAD DE LA VIGENCIA | H1: No. HALLAZGO | I1: CODIGO ACCION | J1: SECTORIAL QUE GENERO LA AUDITORÍA | K1: Columna1 | L1: MODALIDAD | M1: COMPONENTE | N1: FACTOR | O1: DESCRIPCIÓN HALLAZGO | P1: CAUSA HALLAZGO | Q1: DESCRIPCIÓN ACCIÓN | R1: NOMBRE INDICADOR | S1: FORMULA INDICADOR | T1: VALOR META | U1: AREA RESPONSABLE | V1: FECHA DE INICIO | W1: FECHA DE TERMINACIÓN | X1: ESTADO ENT+W3+X:X:AH | Y1: ESTADO AUDITOR | Z1: OBSERVACIÓN | AA1: ESTADO | AB1: ENLACE PARA CARGAR EVIDENCIAS | AC1: Vencimiento | AD1: Alerta 10 | AE1: Alerta 20 | AF1: Alerta 30 | AG1: Alerta 5 | AH1: Correo Responsables | AI1: Fecha cierre x Auditoría | AJ1: % Hallazgos
A2: 117 | B2: 2025-10-10 | C2: MOVILIDAD | D2: TERMINAL DE TRANSPORTE S.A. | E2: 311 | F2: 2025 | G2: 90 | H2: 3.1.1 | I2: 1 | J2: DIRECCIÓN SECTOR MOVILIDAD | L2: AUDITORÍA FINANCIERA Y DE GESTIÓN Y RESULTADOS | O2: HALLAZGO ADMINISTRATIVO CON PRESUNTA INCIDENCIA DISCIPLINARIA POR INCONSISTENCIAS EN LA ENTREGA DE INFORMACIÓN REQUERIDA POR EL ORGANISMO DE CONTROL | P2: FALENCIAS EN LA COMUNICACIÓN Y CONCILIACIÓN DE LA INFORMACIÓN DE LAS DIFERENTES DEPENDENCIAS CON DESTINO A LOS ESTADOS FINANCIEROS DE LA TTSA | Q2: DEFINICIÓN DE LA POLITICA CONTABLE QUE INCLUYA DIFERENCIAS DE CONCEPTO ENTRE UN ACTIVO Y EL MANEJO DE LOS PREDIOS PROPIEDAD DE TTSA | R2: POLITICA CONTABLE PROPIEDAD PLANTA Y EQUIPO | S2: PUBLICAR EN EL SIG - POLÍTICA PROPIEDAD PLANTA Y EQUIPO PUBLICADO | T2: 100 | U2: DIRECCIÓN DE GESTIÓN FINANCIERA/ DIRECCIÓN DE RECURSOS FÍSICOS Y NEGOCIOS | V2: 45957 | W2: 2026-06-30 | Y2: ABIERTA | AA2: Vencida | AB2: https://drive.google.com/drive/u/0/folders/1bmZSYTZPlrSq234glXYiTJCO48SccgqJ | AC2: =IF(AA2="Abierta", DATE(LEFT(W2,4), MID(W2,6,2), RIGHT(W2,2)) - TODAY(), "") | AD2: =IF(AND($AA2="Abierta", $AC2<=10, $AC2>0), 1, 0) -> 0 | AE2: =IF(AND($AA2="Abierta", $AC2<=20, $AC2>10), 1, 0) -> 0 | AF2: =IF(AND($AA2="Abierta", $AC2<=30, $AC2>20), 1, 0) -> 0 | AG2: =IF(AND($AA2="Abierta", $AC2<=5, $AC2>0), 1, 0) -> 0 | AH2: manuel.cifuentes@terminaldetransporte.gov.co,edgar.ortiz@terminaldetransporte.gov.co,roberto.bermudez@terminaldetransporte.gov.co,miguel.salina@terminaldetransporte.gov.co | AJ2: 0.5
A3: 118 | B3: 2025-10-10 | C3: MOVILIDAD | D3: TERMINAL DE TRANSPORTE S.A. | E3: 311 | F3: 2025 | G3: 90 | H3: 3.1.1 | I3: 2 | J3: DIRECCIÓN SECTOR MOVILIDAD | L3: AUDITORÍA FINANCIERA Y DE GESTIÓN Y RESULTADOS | O3: HALLAZGO ADMINISTRATIVO CON PRESUNTA INCIDENCIA DISCIPLINARIA POR INCONSISTENCIAS EN LA ENTREGA DE INFORMACIÓN REQUERIDA POR EL ORGANISMO DE CONTROL | P3: FALENCIAS EN LA COMUNICACIÓN Y CONCILIACIÓN DE LA INFORMACIÓN DE LAS DIFERENTES DEPENDENCIAS CON DESTINO A LOS ESTADOS FINANCIEROS DE LA TTSA | Q3: DEFINICIÓN Y/O ACTUALIZACIÓN DE PROCEDIMIETNO DE CONCILIACIÓN QUE INCLUYA LA LÍNEA DE ZPP, QUE DESCRIBIRÁ LA INFORMACIÓN A CONCILIAR DEL RECAUDO EN EFECTIVO COMO DEL RECAUDO ELECTRÓNICO | R3: PROCEDIMIENTO DE CONCILIACIÓN QUE INCLUYA COMPONENTE DEL RECAUDO ZONA DE PARQUEO PAGO | S3: PUBLICAR EN EL SIG - PROCEDIMIENTO DE CONCILIACIÓN DEL RECAUDO ZPP, ACTUALIZADO Y PUBLICADO | T3: 100 | U3: DIRECCIÓN DE GESTIÓN FINANCIERA | V3: 45957 | W3: 46172 | Y3: ABIERTA | Z3: Se implementa el Procedimiento Conciliación Contable entre Dependencias CÓDIGO: GFI-PR12, el cual establece los lineamientos técnicos para la ejecución del procedimiento de conciliación contable entre dependencias y módulos del sistema. | AA3: Finalizada | AB3: https://drive.google.com/drive/u/0/folders/1CI3HiTEJGC17Z1LFphzunlSzJ1WBkwbD | AC3: =IF(AA3="Abierta", DATE(LEFT(W3,4), MID(W3,6,2), RIGHT(W3,2)) - TODAY(), "") | AD3: =IF(AND($AA3="Abierta", $AC3<=10, $AC3>0), 1, 0) -> 0 | AE3: =IF(AND($AA3="Abierta", $AC3<=20, $AC3>10), 1, 0) -> 0 | AF3: =IF(AND($AA3="Abierta", $AC3<=30, $AC3>20), 1, 0) -> 0 | AG3: =IF(AND($AA3="Abierta", $AC3<=5, $AC3>0), 1, 0) -> 0 | AH3: roberto.bermudez@terminaldetransporte.gov.co,miguel.salina@terminaldetransporte.gov.co | AI3: 46172 | AJ3: 0.5
A4: 123 | B4: 2025-10-10 | C4: MOVILIDAD | D4: TERMINAL DE TRANSPORTE S.A. | E4: 311 | F4: 2025 | G4: 90 | H4: 3.1.2 | I4: 1 | J4: DIRECCIÓN SECTOR MOVILIDAD | L4: AUDITORÍA FINANCIERA Y DE GESTIÓN Y RESULTADOS | O4: HALLAZGO ADMINISTRATIVO CON INCIDENCIA FISCAL POR VALOR DE CINCO MILLONES DOSCIENTOS CUARENTA Y SEIS MIL TREINTA PESOS M/CTE $5.246.030, Y PRESUNTA INCIDENCIA DISCIPLINARIA POR EL PAGO DE INTERESES CON OCASIÓN DE LOS CONTRATOS INTERADMINISTRATIVOS NOS. 1724/2021 Y 1684/2022, SUSCRITOS ENTRE LA TTSA Y EL INSTITUTO DE DESARROLLO URBANO – IDU. | P4: FALTA DE SEGUIMIENTO Y CUMPLIMIENTO OPORTUNO DE LOS TÉRMINOS ESTABLECIDOS EN LAS CLÁUSULAS CONTRACTUALES, Y DE LAS OBLIGACIONES A CARGO DE LA TTSA | Q4: ELABORAR Y PRESENTAR A IDU PROPUESTA DE UNA NUEVA ESTRUCTURA DE CONTRATO EN LA QUE SE ELIMINA LA OBLIGACIÓN DE PAGOS DE INTERESES CON OCASIÓN DE RETRIBUCIÓN | R4: PROPUESTA DE NEGOCIO | S4: RADICACIÓN DE LA PROPUESTA ENTREGADA AL IDU | T4: 100 | U4: DIRECCIÓN DE RECURSOS FÍSICOS Y NEGOCIOS | V4: 2025-10-27 | W4: 45991 | Y4: ABIERTA | Z4: Mediante la solicitud de modificación y prórroga al Contrato Interadministrativo 1684 de 2022 con radicado 20250310109791 se solicita la eliminación de la obligación de pagos de intereses con ocasión de retribución toda vez que, con la nueva metodología ya no existiría aplicabilidad de estas obligaciones. | AA4: Finalizada | AB4: https://drive.google.com/drive/u/0/folders/13AEf4WR13iErgZmA4pnPJeQYbfGTDHtV | AC4: =IF(AA4="Abierta", DATE(LEFT(W4,4), MID(W4,6,2), RIGHT(W4,2)) - TODAY(), "") | AD4: =IF(AND($AA4="Abierta", $AC4<=10, $AC4>0), 1, 0) -> 0 | AE4: =IF(AND($AA4="Abierta", $AC4<=20, $AC4>10), 1, 0) -> 0 | AF4: =IF(AND($AA4="Abierta", $AC4<=30, $AC4>20), 1, 0) -> 0 | AG4: =IF(AND($AA4="Abierta", $AC4<=5, $AC4>0), 1, 0) -> 0 | AH4: manuel.cifuentes@terminaldetransporte.gov.coedgar.ortiz@terminaldetransporte.gov.co | AI4: 45991 | AJ4: 0.5
A5: 124 | B5: 2025-10-10 | C5: MOVILIDAD | D5: TERMINAL DE TRANSPORTE S.A. | E5: 311 | F5: 2025 | G5: 90 | H5: 3.1.2 | I5: 2 | J5: DIRECCIÓN SECTOR MOVILIDAD | L5: AUDITORÍA FINANCIERA Y DE GESTIÓN Y RESULTADOS | O5: HALLAZGO ADMINISTRATIVO CON INCIDENCIA FISCAL POR VALOR DE CINCO MILLONES DOSCIENTOS CUARENTA Y SEIS MIL TREINTA PESOS M/CTE $5.246.030, Y PRESUNTA INCIDENCIA DISCIPLINARIA POR EL PAGO DE INTERESES CON OCASIÓN DE LOS CONTRATOS INTERADMINISTRATIVOS NOS. 1724/2021 Y 1684/2022, SUSCRITOS ENTRE LA TTSA Y EL INSTITUTO DE DESARROLLO URBANO – IDU. | P5: FALTA DE SEGUIMIENTO Y CUMPLIMIENTO OPORTUNO DE LOS TÉRMINOS ESTABLECIDOS EN LAS CLÁUSULAS CONTRACTUALES, Y DE LAS OBLIGACIONES A CARGO DE LA TTSA | Q5: AJUSTE DE METODOLOGÍA PARA LA REVISIÓN DE LA RETRIBUCIÓN AL IDU | R5: OTROSÍ A LOS CONTRATOS | S5: ACEPTACIÓN DEL AJUSTE DE LA METODOLOGÍA POR PARTE DEL IDU A LOS CONTRATOS | T5: 100 | U5: DIRECCIÓN DE RECURSOS FÍSICOS Y NEGOCIOS | V5: 2025-10-27 | W5: 45991 | Y5: ABIERTA | Z5: Mediante la prórroga 3 y modificación 3 al contrato interadministrativo IDU - 1684 - 2022 se realiza ajuste de metodología para el pago y revisión de la retribución al IDU. | AA5: Finalizada | AB5: https://drive.google.com/drive/u/0/folders/1_mR8Cs1sgxiV3mkUbPhb1XH-SO4cn6b9 | AC5: =IF(AA5="Abierta", DATE(LEFT(W5,4), MID(W5,6,2), RIGHT(W5,2)) - TODAY(), "") | AD5: =IF(AND($AA5="Abierta", $AC5<=10, $AC5>0), 1, 0) -> 0 | AE5: =IF(AND($AA5="Abierta", $AC5<=20, $AC5>10), 1, 0) -> 0 | AF5: =IF(AND($AA5="Abierta", $AC5<=30, $AC5>20), 1, 0) -> 0 | AG5: =IF(AND($AA5="Abierta", $AC5<=5, $AC5>0), 1, 0) -> 0 | AI5: 45991 | AJ5: 0.5
A6: 189 | B6: 2025-10-10 | C6: MOVILIDAD | D6: TERMINAL DE TRANSPORTE S.A. | E6: 311 | F6: 2025 | G6: 90 | H6: 3.2.1.1.1 | I6: 1 | J6: DIRECCIÓN SECTOR MOVILIDAD | L6: AUDITORÍA FINANCIERA Y DE GESTIÓN Y RESULTADOS | O6: HALLAZGO ADMINISTRATIVO CON INCIDENCIA FISCAL POR VALOR DE CIENTO VEINTISÉIS MILLONES NOVECIENTOS NOVENTA MIL DOSCIENTOS CINCUENTA Y TRES PESOS M/CTE $126.990.253 Y PRESUNTA INCIDENCIA DISCIPLINARIA POR LA PRESCRIPCIÓN DE LA ACCIÓN DE COBRO POR PARTE DE LA TTSA ANTE LAS ENTIDADES PROMOTORAS DE SALUD – EPS POR CONCEPTO DE INCAPACIDADES LABORALES. | P6: AUSENCIA DE CONTROLES EFECTIVOS, SEGUIMIENTO OPORTUNO, DEFICIENTE COMUNICACIÓN ENTRE LAS DEPENDENCIAS DE LA ENTIDAD, FALTA DE CONCILIACIÓN Y COBRO DE LAS INCAPACIDADES | Q6: ELABORACIÓN PROCEDIMIENTO DEL SEGUIMIENTO A LAS INCAPACIDADES | R6: PROCEDIMIENTO DE COBRO DE LAS INCAPACIDADES | S6: PUBLICAR EN SIG - PROCEDIMIENTO DE COBRO DE INCAPACIDADES | T6: 100 | U6: DIRECCIÓN DE GESTIÓN HUMANA | V6: 2025-10-27 | W6: 46112 | Y6: ABIERTA | Z6: Se implementa el Procedimiento Trámite de Incapacidades CÓDIGO: GTS-PR22, el cual establece los lineamientos para el trámite de reconocimiento, liquidación, pago, cobro y conciliación de las incapacidades y licencias del personal de la Terminal de Transporte S.A. | AA6: Finalizada | AB6: https://drive.google.com/drive/u/0/folders/1JnOu0yV7hzMBf-kTsas1TYZS8BWLGu6l | AC6: =IF(AA6="Abierta", DATE(LEFT(W6,4), MID(W6,6,2), RIGHT(W6,2)) - TODAY(), "") | AD6: =IF(AND($AA6="Abierta", $AC6<=10, $AC6>0), 1, 0) -> 0 | AE6: =IF(AND($AA6="Abierta", $AC6<=20, $AC6>10), 1, 0) -> 0 | AF6: =IF(AND($AA6="Abierta", $AC6<=30, $AC6>20), 1, 0) -> 0 | AG6: =IF(AND($AA6="Abierta", $AC6<=5, $AC6>0), 1, 0) -> 0 | AH6: diana.ortiz@terminaldetransporte.gov.co,linda.florez@terminaldetransporte.gov.co | AI6: 46112 | AJ6: 0.33
A7: 190 | B7: 2025-10-10 | C7: MOVILIDAD | D7: TERMINAL DE TRANSPORTE S.A. | E7: 311 | F7: 2025 | G7: 90 | H7: 3.2.1.1.1 | I7: 2 | J7: DIRECCIÓN SECTOR MOVILIDAD | L7: AUDITORÍA FINANCIERA Y DE GESTIÓN Y RESULTADOS | O7: HALLAZGO ADMINISTRATIVO CON INCIDENCIA FISCAL POR VALOR DE CIENTO VEINTISÉIS MILLONES NOVECIENTOS NOVENTA MIL DOSCIENTOS CINCUENTA Y TRES PESOS M/CTE $126.990.253 Y PRESUNTA INCIDENCIA DISCIPLINARIA POR LA PRESCRIPCIÓN DE LA ACCIÓN DE COBRO POR PARTE DE LA TTSA ANTE LAS ENTIDADES PROMOTORAS DE SALUD – EPS POR CONCEPTO DE INCAPACIDADES LABORALES. | P7: AUSENCIA DE CONTROLES EFECTIVOS, SEGUIMIENTO OPORTUNO, DEFICIENTE COMUNICACIÓN ENTRE LAS DEPENDENCIAS DE LA ENTIDAD, FALTA DE CONCILIACIÓN Y COBRO DE LAS INCAPACIDADES | Q7: CONTRATACIÓN DE UNA PERSONA PARA EJECUTAR LA ACTIVIDAD DE SEGUIMIENTO AL COBRO DE INCAPACIDADES | R7: CONTRATACIÓN DE PROFESIONAL PARA RECOBRO | S7: CONTRATO DEL PERSONAL ASIGNADO PARA EL PROCESO DE COBRO A LAS EPS | T7: 100 | U7: DIRECCIÓN DE GESTIÓN HUMANA | V7: 2025-10-27 | W7: 45991 | Y7: ABIERTA | Z7: Se evidencia el cumplimiento de la acción, toda vez que se aportó el contrato de trabajo mediante el cual se vinculó una persona para el desempeño de funciones como Profesional de Seguridad Social y Cartera, cargo que guarda relación directa con la actividad de seguimiento al cobro de incapacidades, conforme al objeto contractual aportado. | AA7: Finalizada | AB7: https://drive.google.com/drive/u/0/folders/1JnOu0yV7hzMBf-kTsas1TYZS8BWLGu6l | AC7: =IF(AA7="Abierta", DATE(LEFT(W7,4), MID(W7,6,2), RIGHT(W7,2)) - TODAY(), "") | AD7: =IF(AND($AA7="Abierta", $AC7<=10, $AC7>0), 1, 0) -> 0 | AE7: =IF(AND($AA7="Abierta", $AC7<=20, $AC7>10), 1, 0) -> 0 | AF7: =IF(AND($AA7="Abierta", $AC7<=30, $AC7>20), 1, 0) -> 0 | AG7: =IF(AND($AA7="Abierta", $AC7<=5, $AC7>0), 1, 0) -> 0 | AH7: diana.ortiz@terminaldetransporte.gov.co,linda.florez@terminaldetransporte.gov.co | AI7: 45991 | AJ7: 0.33
A8: 191 | B8: 2025-10-10 | C8: MOVILIDAD | D8: TERMINAL DE TRANSPORTE S.A. | E8: 311 | F8: 2025 | G8: 90 | H8: 3.2.1.1.1 | I8: 3 | J8: DIRECCIÓN SECTOR MOVILIDAD | L8: AUDITORÍA FINANCIERA Y DE GESTIÓN Y RESULTADOS | O8: HALLAZGO ADMINISTRATIVO CON INCIDENCIA FISCAL POR VALOR DE CIENTO VEINTISÉIS MILLONES NOVECIENTOS NOVENTA MIL DOSCIENTOS CINCUENTA Y TRES PESOS M/CTE $126.990.253 Y PRESUNTA INCIDENCIA DISCIPLINARIA POR LA PRESCRIPCIÓN DE LA ACCIÓN DE COBRO POR PARTE DE LA TTSA ANTE LAS ENTIDADES PROMOTORAS DE SALUD – EPS POR CONCEPTO DE INCAPACIDADES LABORALES. | P8: AUSENCIA DE CONTROLES EFECTIVOS, SEGUIMIENTO OPORTUNO, DEFICIENTE COMUNICACIÓN ENTRE LAS DEPENDENCIAS DE LA ENTIDAD, FALTA DE CONCILIACIÓN Y COBRO DE LAS INCAPACIDADES | Q8: PRESENTACIÓN DE DEMANDA EN GESTIÓN DE RECOBRO EN CONTRA DE LAS EPS | R8: DEMANDA DE GESTIÓN DE RECOBRO | S8: DEMANDAS PRESENTADAS RADICADAS EN LAS EPS | T8: 100 | U8: DIRECCIÓN DE GESTIÓN HUMANA | V8: 2025-10-27 | W8: 46022 | Y8: ABIERTA | Z8: Se presentan demandas a las EPS Compensar, Sanitas, Famisanar, Nueva EPS,Salud Total EPS, Alianza Salud EPS y Sura. | AA8: Finalizada | AB8: https://drive.google.com/drive/u/0/folders/1LP5j8uUh8jyIwVIk_TVn3HdU5R3Ej52K | AC8: =IF(AA8="Abierta", DATE(LEFT(W8,4), MID(W8,6,2), RIGHT(W8,2)) - TODAY(), "") | AD8: =IF(AND($AA8="Abierta", $AC8<=10, $AC8>0), 1, 0) -> 0 | AE8: =IF(AND($AA8="Abierta", $AC8<=20, $AC8>10), 1, 0) -> 0 | AF8: =IF(AND($AA8="Abierta", $AC8<=30, $AC8>20), 1, 0) -> 0 | AG8: =IF(AND($AA8="Abierta", $AC8<=5, $AC8>0), 1, 0) -> 0 | AH8: diana.ortiz@terminaldetransporte.gov.co,linda.florez@terminaldetransporte.gov.co | AI8: 46022 | AJ8: 0.34
A9: 193 | B9: 2025-10-10 | C9: MOVILIDAD | D9: TERMINAL DE TRANSPORTE S.A. | E9: 311 | F9: 2025 | G9: 90 | H9: 3.2.1.1.2 | I9: 1 | J9: DIRECCIÓN SECTOR MOVILIDAD | L9: AUDITORÍA FINANCIERA Y DE GESTIÓN Y RESULTADOS | O9: HALLAZGO ADMINISTRATIVO CON PRESUNTA INCIDENCIA DISCIPLINARIA POR DEFICIENCIAS EN EL COBRO DE LOS CÁNONES DE ARRENDAMIENTO CAUSADOS DURANTE LA EJECUCIÓN DE LOS CONTRATOS DE ARRENDAMIENTO A-027-TQLL-2003; A-024-P.D.-2003; T-S.-2009 CÓDIGO A – L.3 EN Z.T.; Y TT NO. 90 DE 2015. | P9: DEBILIDADES EN EL COBRO DE CÁNONES DE ARRENDAMIENTO DURANTE LA EJECUCIÓN DE CONTRATOS DE ARRENDAMIENTO | Q9: ACTUALIZACIÓN DEL PROCEDIMIENTO DE GESTIÓN INMOBILIARIA QUE DEFINA LOS CONTROLES PARA EJERCER LAS ACCIONES DE COBRO DE CANONES DE ARRENDAMIENTO, EL PROCESO Y RESPONSABLES DE DECLARATORIA DE SINIESTRO EN LOS CASOS EN LOS QUE SE CUENTE CON GARANTÍAS DE ARRENDAMIENTO, O, LOS REQUISITOS, PROCEDIMIENTO Y RESPONSABLES PARA EL EJERCICIO DE ACCIONES DE COBRO COACTIVO | R9: PROCEDIMIENTO DE GESTIÓN INMOBILIARIA | S9: PUBLICACIÓN EN EL SIG - PROCEDIMIENTO DE GESTIÓN INMOBILIARIA | T9: 100 | U9: DIRECCIÓN DE RECURSOS FÍSICOS Y NEGOCIOS/ SUBGERENCIA JURÍDICA | V9: 2025-10-27 | W9: 2026-10-13 | Y9: ABIERTA | Z9: Se implementa el Manual Gestión Inmobiliaria Código: GIM-MN01, con el fin de proporcionar al personal involucrado en el proceso, una guía que regule su accionar en las actividades administrativas y de control inherentes a los bienes inmuebles de la TTSA. | AA9: Finalizada | AB9: https://drive.google.com/drive/u/0/folders/1QT49y1L5HwPHxc-EwvXz5gLce7HGc71K | AC9: =IF(AA9="Abierta", DATE(LEFT(W9,4), MID(W9,6,2), RIGHT(W9,2)) - TODAY(), "") | AD9: =IF(AND($AA9="Abierta", $AC9<=10, $AC9>0), 1, 0) -> 0 | AE9: =IF(AND($AA9="Abierta", $AC9<=20, $AC9>10), 1, 0) -> 0 | AF9: =IF(AND($AA9="Abierta", $AC9<=30, $AC9>20), 1, 0) -> 0 | AG9: =IF(AND($AA9="Abierta", $AC9<=5, $AC9>0), 1, 0) -> 0 | AH9: manuel.cifuentes@terminaldetransporte.gov.co,edgar.ortiz@terminaldetransporte.gov.co,carlos.salcedo@terminaldetransporte.gov.co,juan.alviz@terminaldetransporte.gov.co,omar.gamboa@terminaldetransporte.gov.co | AI9: 46293 | AJ9: 1
A10: 196 | B10: 2025-10-10 | C10: MOVILIDAD | D10: TERMINAL DE TRANSPORTE S.A. | E10: 311 | F10: 2025 | G10: 90 | H10: 3.2.1.1.3 | I10: 1 | J10: DIRECCIÓN SECTOR MOVILIDAD | L10: AUDITORÍA FINANCIERA Y DE GESTIÓN Y RESULTADOS | O10: HALLAZGO ADMINISTRATIVO CON PRESUNTA INCIDENCIA DISCIPLINARIA POR LA GESTIÓN INEFICIENTE DE LA TERMINAL DE TRANSPORTE S.A. DURANTE DEL PROCESO DE EXPROPIACIÓN ADMINISTRATIVA ADELANTADO POR LA EMPRESA FÉRREA REGIONAL S.A.S. RESPECTO DEL PREDIO DENOMINADO “SANTA HELENA”, IDENTIFICADO CON LA MATRÍCULA INMOBILIARIA 051-191183, ASÍ COMO SU GESTIÓN INOPORTUNA EN LA DEFENSA DE LOS INTERESES DE LA ENTIDAD RESPECTO DEL COBRO DEL IMPUESTO PREDIAL | P10: DEBILIDADES DE GESTIÓN Y CONTROL POR PARTE DE LA TTSA A LO LARGO DEL CICLO DE ADQUISICIÓN/EXPROPIACIÓN Y EN LA FASE POSTERIOR DE DEPURACIÓN REGISTRAL, CATASTRAL Y TRIBUTARIA DEL INMUEBLE CON MATRÍCULA 051-191183 | Q10: GESTIÓN PARA LA MODIFICACIÓN DE LA RESOLUCIÓN NO. 25-75400001616-2025 EXPEDIDA POR EL MUNICIPIO DE SOACHA, CON EL FIN DE QUE SE AJUSTE EL ÁREA DEL PREDIO | R10: COMUNICACIONES DE GESTIÓN DE LA TTS.A. Y/O RESOLUCIÓN DEL MUNICIPIO DE SOACHA | S10: RADICADOS DE LAS COMUNICACIONES Y/O RESOLUCIÓN EXPEDIDA POR EL MUNICIPIO SOACHA | T10: 100 | U10: DIRECCIÓN DE RECURSOS FÍSICOS Y NEGOCIOS | V10: 2025-10-27 | W10: 2026-10-13 | Y10: ABIERTA | Z10: Se verifica la efectividad de la acción mediante la Resolución No. 0090 del 25/03/2026 de la Secretaría de Hacienda de Soacha (saneamiento de intereses moratorios) y el Recibo de Impuesto Predial No. 26982690 (Vigencias 2025-2026). Los soportes acreditan la depuración de la cartera y la actualización oficial del área del predio | AA10: Finalizada | AB10: https://drive.google.com/drive/u/0/folders/1kilX7Bb9sV8Qh-eNoVoUyX1WaRol3HVN | AC10: =IF(AA10="Abierta", DATE(LEFT(W10,4), MID(W10,6,2), RIGHT(W10,2)) - TODAY(), "") | AD10: =IF(AND($AA10="Abierta", $AC10<=10, $AC10>0), 1, 0) -> 0 | AE10: =IF(AND($AA10="Abierta", $AC10<=20, $AC10>10), 1, 0) -> 0 | AF10: =IF(AND($AA10="Abierta", $AC10<=30, $AC10>20), 1, 0) -> 0 | AG10: =IF(AND($AA10="Abierta", $AC10<=5, $AC10>0), 1, 0) -> 0 | AH10: manuel.cifuentes@terminaldetransporte.gov.co,edgar.ortiz@terminaldetransporte.gov.co | AI10: 46293 | AJ10: 0.33
A11: 197 | B11: 2025-10-10 | C11: MOVILIDAD | D11: TERMINAL DE TRANSPORTE S.A. | E11: 311 | F11: 2025 | G11: 90 | H11: 3.2.1.1.3 | I11: 2 | J11: DIRECCIÓN SECTOR MOVILIDAD | L11: AUDITORÍA FINANCIERA Y DE GESTIÓN Y RESULTADOS | O11: HALLAZGO ADMINISTRATIVO CON PRESUNTA INCIDENCIA DISCIPLINARIA POR LA GESTIÓN INEFICIENTE DE LA TERMINAL DE TRANSPORTE S.A. DURANTE DEL PROCESO DE EXPROPIACIÓN ADMINISTRATIVA ADELANTADO POR LA EMPRESA FÉRREA REGIONAL S.A.S. RESPECTO DEL PREDIO DENOMINADO “SANTA HELENA”, IDENTIFICADO CON LA MATRÍCULA INMOBILIARIA 051-191183, ASÍ COMO SU GESTIÓN INOPORTUNA EN LA DEFENSA DE LOS INTERESES DE LA ENTIDAD RESPECTO DEL COBRO DEL IMPUESTO PREDIAL | P11: DEBILIDADES DE GESTIÓN Y CONTROL POR PARTE DE LA TTSA A LO LARGO DEL CICLO DE ADQUISICIÓN/EXPROPIACIÓN Y EN LA FASE POSTERIOR DE DEPURACIÓN REGISTRAL, CATASTRAL Y TRIBUTARIA DEL INMUEBLE CON MATRÍCULA 051-191183 | Q11: RELIQUIDACIÓN DE IMPUESTOS CON FUNDAMENTO EN LA REDEFINICIÓN DEL ÁREA DEL PREDIO, CONFORME A LA MODIFICACIÓN DE LA RESOLUCIÓN CITADA | R11: RELIQUIDACIÓN PAGO IMPUESTOS | S11: RECIBOS DE PAGO IMPUESTOS | T11: 100 | U11: DIRECCIÓN DE GESTIÓN FINANCIERA | V11: 2025-10-27 | W11: 2026-10-13 | Y11: ABIERTA | AA11: Abierta | AB11: https://drive.google.com/drive/u/0/folders/1EubnA9GmEsmbl7UFcOUTjsykCzJiqONA | AC11: =IF(AA11="Abierta", DATE(LEFT(W11,4), MID(W11,6,2), RIGHT(W11,2)) - TODAY(), "") -> -6 | AD11: =IF(AND($AA11="Abierta", $AC11<=10, $AC11>0), 1, 0) -> 0 | AE11: =IF(AND($AA11="Abierta", $AC11<=20, $AC11>10), 1, 0) -> 0 | AF11: =IF(AND($AA11="Abierta", $AC11<=30, $AC11>20), 1, 0) -> 0 | AG11: =IF(AND($AA11="Abierta", $AC11<=5, $AC11>0), 1, 0) -> 0 | AH11: roberto.bermudez@terminaldetransporte.gov.co,miguel.salina@terminaldetransporte.gov.co | AJ11: 0.33
A12: 198 | B12: 2025-10-10 | C12: MOVILIDAD | D12: TERMINAL DE TRANSPORTE S.A. | E12: 311 | F12: 2025 | G12: 90 | H12: 3.2.1.1.3 | I12: 3 | J12: DIRECCIÓN SECTOR MOVILIDAD | L12: AUDITORÍA FINANCIERA Y DE GESTIÓN Y RESULTADOS | O12: HALLAZGO ADMINISTRATIVO CON PRESUNTA INCIDENCIA DISCIPLINARIA POR LA GESTIÓN INEFICIENTE DE LA TERMINAL DE TRANSPORTE S.A. DURANTE DEL PROCESO DE EXPROPIACIÓN ADMINISTRATIVA ADELANTADO POR LA EMPRESA FÉRREA REGIONAL S.A.S. RESPECTO DEL PREDIO DENOMINADO “SANTA HELENA”, IDENTIFICADO CON LA MATRÍCULA INMOBILIARIA 051-191183, ASÍ COMO SU GESTIÓN INOPORTUNA EN LA DEFENSA DE LOS INTERESES DE LA ENTIDAD RESPECTO DEL COBRO DEL IMPUESTO PREDIAL | P12: DEBILIDADES DE GESTIÓN Y CONTROL POR PARTE DE LA TTSA A LO LARGO DEL CICLO DE ADQUISICIÓN/EXPROPIACIÓN Y EN LA FASE POSTERIOR DE DEPURACIÓN REGISTRAL, CATASTRAL Y TRIBUTARIA DEL INMUEBLE CON MATRÍCULA 051-191183 | Q12: CREACIÓN DE PROCEDIMIENTO PARA TRÁMITE DE EXPROPIACIONES DE LOS BIENES DE LA TTSA | R12: PROCEDIMIENTO PARA GESTIONAR EXPROPIACIONES | S12: PUBLICACIÓN EN SIG - PROCEDIMIENTO PARA GESTIONAR EXPROPIACIONES | T12: 100 | U12: SUBGERENCIA JURÍDICA | V12: 2025-10-27 | W12: 2026-10-13 | Y12: ABIERTA | AA12: Abierta | AB12: https://drive.google.com/drive/u/0/folders/1RljHJeJbF-CMMxCEgzMTaJzp2W7ejDiQ | AC12: =IF(AA12="Abierta", DATE(LEFT(W12,4), MID(W12,6,2), RIGHT(W12,2)) - TODAY(), "") -> -6 | AD12: =IF(AND($AA12="Abierta", $AC12<=10, $AC12>0), 1, 0) -> 0 | AE12: =IF(AND($AA12="Abierta", $AC12<=20, $AC12>10), 1, 0) -> 0 | AF12: =IF(AND($AA12="Abierta", $AC12<=30, $AC12>20), 1, 0) -> 0 | AG12: =IF(AND($AA12="Abierta", $AC12<=5, $AC12>0), 1, 0) -> 0 | AH12: carlos.salcedo@terminaldetransporte.gov.co,juan.alviz@terminaldetransporte.gov.co,omar.gamboa@terminaldetransporte.gov.co | AJ12: 0.34
A13: 199 | B13: 2025-10-10 | C13: MOVILIDAD | D13: TERMINAL DE TRANSPORTE S.A. | E13: 311 | F13: 2025 | G13: 90 | H13: 3.2.1.1.4 | I13: 1 | J13: DIRECCIÓN SECTOR MOVILIDAD | L13: AUDITORÍA FINANCIERA Y DE GESTIÓN Y RESULTADOS | O13: HALLAZGO ADMINISTRATIVO CON PRESUNTA INCIDENCIA DISCIPLINARIA POR INCONSISTENCIAS ENTRE LOS REGISTROS CONTABLES Y LOS SOPORTES ALLEGADOS POR LA TTSA EN REFERENCIA A LA INFORMACIÓN CONTABLE DEL INMUEBLE IDENTIFICADO COMO “LOTE SOACHA” | P13: FALTA DE VERIFICACIÓN Y ANÁLISIS OPORTUNOS DE LOS HECHOS ECONÓMICOS OBJETO DE REGISTRO EN LOS ESTADOS FINANCIEROS DE LA EMPRESA | Q13: AVALÚO Y SOPORTES QUE SUSTENTAN EL REGISTRO CONTABLE DEL LOTE SOACHA, EN EL REPOSITORIO DE LA DIRECCIÓN FINANCIERA | R13: REPOSITORIO DE DOCUMENTOS DIRECCIÓN FINANCIERA | S13: REPOSITORIO CON LA DOCUMENTACIÓN DE CONSULTA | T13: 100 | U13: DIRECCIÓN DE RECURSOS FÍSICOS Y NEGOCIOS | V13: 2025-10-27 | W13: 2026-02-15 | Y13: ABIERTA | Z13: Se elaboró un informe de ajuste contable y cumplimiento del activo denominado "Lote Soacha" | AA13: Finalizada | AB13: https://drive.google.com/drive/u/0/folders/1BUliexC8UzwR6MWBai4BqV4CPPVNLOo_ | AC13: =IF(AA13="Abierta", DATE(LEFT(W13,4), MID(W13,6,2), RIGHT(W13,2)) - TODAY(), "") | AD13: =IF(AND($AA13="Abierta", $AC13<=10, $AC13>0), 1, 0) -> 0 | AE13: =IF(AND($AA13="Abierta", $AC13<=20, $AC13>10), 1, 0) -> 0 | AF13: =IF(AND($AA13="Abierta", $AC13<=30, $AC13>20), 1, 0) -> 0 | AG13: =IF(AND($AA13="Abierta", $AC13<=5, $AC13>0), 1, 0) -> 0 | AH13: manuel.cifuentes@terminaldetransporte.gov.co,edgar.ortiz@terminaldetransporte.gov.co | AI13: 46100 | AJ13: 0.5
A14: 200 | B14: 2025-10-10 | C14: MOVILIDAD | D14: TERMINAL DE TRANSPORTE S.A. | E14: 311 | F14: 2025 | G14: 90 | H14: 3.2.1.1.4 | I14: 2 | J14: DIRECCIÓN SECTOR MOVILIDAD | L14: AUDITORÍA FINANCIERA Y DE GESTIÓN Y RESULTADOS | O14: HALLAZGO ADMINISTRATIVO CON PRESUNTA INCIDENCIA DISCIPLINARIA POR INCONSISTENCIAS ENTRE LOS REGISTROS CONTABLES Y LOS SOPORTES ALLEGADOS POR LA TTSA EN REFERENCIA A LA INFORMACIÓN CONTABLE DEL INMUEBLE IDENTIFICADO COMO “LOTE SOACHA” | P14: FALTA DE VERIFICACIÓN Y ANÁLISIS OPORTUNOS DE LOS HECHOS ECONÓMICOS OBJETO DE REGISTRO EN LOS ESTADOS FINANCIEROS DE LA EMPRESA | Q14: ELABORACIÓN DE ANÁLISIS DE AJUSTE EN RECONOCIMIETO DEL ACTIVO DENOMINADO " LOTE SOACHA" CON LA ACTUALIZACION POR AVALUO DEL AÑO 2023 COMO NOS INDICA EL MARCO NORMATIVO PARA LAS EMPRESAS QUE NO COTIZAN EN BOLSA DE VALORES Y NO RECAUDAN DINERO PUBLICO | R14: INFORME DE ANÁLISIS DEL AJUSTE DEL DETERIORO DEL ACTIVO DENOMINADO "LOTE SOACHA " | S14: INFORME DE ANÁLISIS DEL AJUSTE DEL DETERIORO DEL ACTIVO DENOMINADO "LOTE SOACHA " PRESENTADO A LA REVISORÍA | T14: 100 | U14: DIRECCIÓN DE GESTIÓN FINANCIERA | V14: 2025-10-27 | W14: 2026-02-15 | Y14: ABIERTA | Z14: Se elaboró un informe de ajuste contable y cumplimiento del activo denominado "Lote Soacha" | AA14: Finalizada | AB14: https://drive.google.com/drive/u/0/folders/1LrFlVUaxg4S1i_lDBuFwT2tUX6bRFlsT | AC14: =IF(AA14="Abierta", DATE(LEFT(W14,4), MID(W14,6,2), RIGHT(W14,2)) - TODAY(), "") | AD14: =IF(AND($AA14="Abierta", $AC14<=10, $AC14>0), 1, 0) -> 0 | AE14: =IF(AND($AA14="Abierta", $AC14<=20, $AC14>10), 1, 0) -> 0 | AF14: =IF(AND($AA14="Abierta", $AC14<=30, $AC14>20), 1, 0) -> 0 | AG14: =IF(AND($AA14="Abierta", $AC14<=5, $AC14>0), 1, 0) -> 0 | AH14: roberto.bermudez@terminaldetransporte.gov.co,miguel.salina@terminaldetransporte.gov.co | AI14: 46064 | AJ14: 0.5
A15: 213 | B15: 2025-10-10 | C15: MOVILIDAD | D15: TERMINAL DE TRANSPORTE S.A. | E15: 311 | F15: 2025 | G15: 90 | H15: 3.2.1.5.1 | I15: 1 | J15: DIRECCIÓN SECTOR MOVILIDAD | L15: AUDITORÍA FINANCIERA Y DE GESTIÓN Y RESULTADOS | O15: HALLAZGO ADMINISTRATIVO CON INCIDENCIA FISCAL POR LA SUMA DE CUATRO MIL OCHOCIENTOS NOVENTA Y SEIS MILLONES OCHOCIENTOS VEINTIDÓS MIL OCHOCIENTOS VEINTINUEVE PESOS M/CTE $4.896.822.829 Y PRESUNTA INCIDENCIA DISCIPLINARIA POR FALTA DE GESTIÓN OPORTUNA EN LA PRESENTACIÓN DE LAS DECLARACIONES DEL IMPUESTO PREDIAL UNIFICADO DEL INMUEBLE IDENTIFICADO CON CHIP AAA0077FYUH, VIGENCIAS 2015, 2016, 2017, 2020,2021, 2022 Y 2023 | P15: FALTA DE SEGUIMIENTO, GESTIONES OPORTUNAS Y EFECTIVAS POR PARTE DE LA EMPRESA A FIN DE CUMPLIR CON LAS OBLIGACIONES EN MATERIA TRIBUTARIA Y SANEAR LA SITUACIÓN DE LA EMPRESA ANTE LA ADMINISTRACIÓN DE IMPUESTOS DISTRITALES | Q15: ELABORACIÓN DE MANUAL, PROCEDIMIENTO E INSTRUCTIVO PARA PAGO DE TODOS LOS IMPUESTOS EN LOS QUE LA TERMINAL DE TRANSPORTE S.A. ES SUJETO PASIVO, DEFINICIÓN DE LAS RESPONSABILIDADES Y ACTUACIONES FRENTE A CADA TIPO DE TRIBUTO | R15: MANUAL, PROCEDIMIENTO E INSTRUCTIVO DE PAGO DE LOS IMPUESTOS A CARGO DE LA TTSA | S15: PUBLICACIÓN MANUAL, PROCEDIMIENTO E INSTRUCTIVO DE PAGO DE LOS IMPUESTOS A CARGO DE LA TTSA | T15: 100 | U15: DIRECCIÓN DE GESTIÓN FINANCIERA | V15: 2025-10-27 | W15: 46081 | Y15: ABIERTA | Z15: Se implementa el Manual de Cumplimiento Tributario Nacional y Territorial CÓDIGO: GFI-MN02, el cual establece los lineamientos para la identificación, determinación, presentación y pago oportuno de las obligaciones tributarias del orden nacional y territorial de la Terminal de Transporte S.A.. | AA15: Finalizada | AB15: https://drive.google.com/drive/u/0/folders/1IS9BzI07vze98OgBUC7T6wwNdSXGpNkr | AC15: =IF(AA15="Abierta", DATE(LEFT(W15,4), MID(W15,6,2), RIGHT(W15,2)) - TODAY(), "") | AD15: =IF(AND($AA15="Abierta", $AC15<=10, $AC15>0), 1, 0) -> 0 | AE15: =IF(AND($AA15="Abierta", $AC15<=20, $AC15>10), 1, 0) -> 0 | AF15: =IF(AND($AA15="Abierta", $AC15<=30, $AC15>20), 1, 0) -> 0 | AG15: =IF(AND($AA15="Abierta", $AC15<=5, $AC15>0), 1, 0) -> 0 | AH15: roberto.bermudez@terminaldetransporte.gov.co,miguel.salina@terminaldetransporte.gov.co | AI15: 46081 | AJ15: 0.5
A16: 214 | B16: 2025-10-10 | C16: MOVILIDAD | D16: TERMINAL DE TRANSPORTE S.A. | E16: 311 | F16: 2025 | G16: 90 | H16: 3.2.1.5.1 | I16: 2 | J16: DIRECCIÓN SECTOR MOVILIDAD | L16: AUDITORÍA FINANCIERA Y DE GESTIÓN Y RESULTADOS | O16: HALLAZGO ADMINISTRATIVO CON INCIDENCIA FISCAL POR LA SUMA DE CUATRO MIL OCHOCIENTOS NOVENTA Y SEIS MILLONES OCHOCIENTOS VEINTIDÓS MIL OCHOCIENTOS VEINTINUEVE PESOS M/CTE $4.896.822.829 Y PRESUNTA INCIDENCIA DISCIPLINARIA POR FALTA DE GESTIÓN OPORTUNA EN LA PRESENTACIÓN DE LAS DECLARACIONES DEL IMPUESTO PREDIAL UNIFICADO DEL INMUEBLE IDENTIFICADO CON CHIP AAA0077FYUH, VIGENCIAS 2015, 2016, 2017, 2020,2021, 2022 Y 2023 | P16: FALTA DE SEGUIMIENTO, GESTIONES OPORTUNAS Y EFECTIVAS POR PARTE DE LA EMPRESA A FIN DE CUMPLIR CON LAS OBLIGACIONES EN MATERIA TRIBUTARIA Y SANEAR LA SITUACIÓN DE LA EMPRESA ANTE LA ADMINISTRACIÓN DE IMPUESTOS DISTRITALES | Q16: DECISIÓN DE LA DEMANDA INTERPUESTA EL 12/MARZ/2025 CON RADICADO NO. 25000234100020250038300, EN EL TRIBUNAL ADMINISTRATIVO DE CUNDINAMARCA | R16: ADMISIÓN DE LA DEMANDA | S16: DECISIÓN DE LA DEMANDA | T16: 100 | U16: SUBGERENCIA JURÍDICA | V16: 2025-10-27 | W16: 46308 | Y16: ABIERTA | AA16: Abierta | AB16: https://drive.google.com/drive/u/0/folders/1IS9BzI07vze98OgBUC7T6wwNdSXGpNkr | AC16: =IF(AA16="Abierta", DATE(LEFT(W16,4), MID(W16,6,2), RIGHT(W16,2)) - TODAY(), "") -> #VALUE! | AD16: =IF(AND($AA16="Abierta", $AC16<=10, $AC16>0), 1, 0) -> #VALUE! | AE16: =IF(AND($AA16="Abierta", $AC16<=20, $AC16>10), 1, 0) -> #VALUE! | AF16: =IF(AND($AA16="Abierta", $AC16<=30, $AC16>20), 1, 0) -> #VALUE! | AG16: =IF(AND($AA16="Abierta", $AC16<=5, $AC16>0), 1, 0) -> #VALUE! | AH16: carlos.salcedo@terminaldetransporte.gov.co,juan.alviz@terminaldetransporte.gov.co,omar.gamboa@terminaldetransporte.gov.co | AJ16: 0.5
